Workbook
Name page\x2dtotal: #REF!
Name page\x2dtotal\x2dmaster0: #REF!

Sheet Budget
BJ2: =304*Benchmarks!B72 -> 3272.2256
Y3: GBP Version | AF3: USD Version
F6: MMC Fixed FX Rate 25 | X6: Estimated AV Costs based on WH Rates: | Y6: =W43*Y10 -> #REF! | Z6: =Y6 -> #REF! | AE6: Estimated AV Costs based on WH Rates: | AF6: =AD43*AF10 -> #REF! | AG6: =AF6 -> #REF! | AJ6: ='2025 FX Rates'!F41 -> 0.04169429
F7: Key Data
G8: 79 | H8: 165 | I8: 34 | J8: 159 | K8: 4550
F9: Heads | H9: 116 | I9: 25 | M9: 78 | N9: 78 | O9: =72+36+36+72+36+24 -> 276 | P9: =O9 -> 276 | Q9: 270 | R9: 270 | S9: 600 | T9: 600 | U9: =S9 -> 600 | V9: 600 | W9: 1050 | X9: 1050 | Y9: 1050 | Z9: =Y9 -> 1050 | AA9: 1050 | AB9: =AA9 -> 1050 | AD9: 1050 | AE9: 1050 | AF9: 1050 | AG9: =AF9 -> 1050 | AH9: 1050 | AI9: =AH9 -> 1050 | AK9: 220
F10: Area (m²) | G10: 6405 | H10: 8143 | I10: 3280 | J10: 8477 | K10: 350000 | M10: =3114+3916 -> 7030 | N10: =M10 -> 7030 | O10: 25953 | P10: =O10 -> 25953 | Q10: 26000 | R10: 26000 | S10: 67382 | T10: =S10/2 -> 33691 | U10: =S10 -> 67382 | V10: 42000 | W10: 61718 | X10: 61718 | Y10: 66978 | Z10: =Y10 -> 66978 | AA10: =Y10 -> 66978 | AB10: =AA10 -> 66978 | AD10: 61718 | AE10: 61718 | AF10: 66978 | AG10: =AF10 -> 66978 | AH10: =AF10 -> 66978 | AI10: =AH10 -> 66978 | AK10: 1148
F11: Area (ft²) | AK11: =AK10*Benchmarks!B72 -> 12356.957
S13: OW London Project
F14: Prague Renewal | G14: Haywards Heath 2019 | H14: Worcester 2020 | I14: Cardiff 2021 | J14: Milton Keynes 2021 | K14: Tower Place 2021 | L14: Low Cost London fit-out (Benchmarks) | M14: Sackville House 5 & 6 (TP Rates) | N14: Sackville house 5 & 6 (Low Cost) | O14: Tower Bridge House (TP Rates) | P14: Tower Bridge House (Low Cost) | Q14: SBB 4th Floor (Half Floor) Short Term | R14: SBB 4th Floor (Half Floor) Long Term | S14: Renew in Baker Street | T14: Renew in Baker Street (1 Floor only) | U14: Renew in Baker Street (Light Touch) | V14: Relocation Option | W14: Norwich Willow House (from Financial Analysis) | X14: Norwich Willow House (MMC Rates) | Y14: Norwich Victoria House Bronze (From Financial Analysis) | Z14: Norwich Victoria House Gold (From Financial Analysis) | AA14: Norwich Victoria House Bronze (MMC Rates) | AB14: Norwich Victoria House Gold (MMC Rates) | AD14: Norwich Willow House (from Financial Analysis) | AE14: Norwich Willow House (MMC Rates) | AF14: Norwich Victoria House Bronze (From Financial Analysis) | AG14: Norwich Victoria House Gold (From Financial Analysis) | AH14: Norwich Victoria House Bronze (MMC Rates) | AI14: Norwich Victoria House Gold (MMC Rates) | AK14: Prague - Palac Flora
AK15: Benchmark - PMO Benchmark | AN15: Option Local Consultant rates | AQ15: Benchmark Previous project rates YEAR | AT15: Option 4 | AW15: Option 5
F16: CAPEX | J16: CAPEX BUDGET | K16: Ongoing Budget | AJ16: Factor | AK16: (CZK) | AL16: (USD) | AO16: (EUR) | AP16: (USD) | AR16: (EUR) | AS16: (USD) | AU16: (EUR) | AV16: (USD) | AX16: (EUR) | AY16: (USD)
F17: Professional Fees | G17: 47582 | H17: ='[1]Final Account'!I9 -> 45360.5 | I17: 20991.5 | J17: 23550 | K17: =4164229 -> 4164229 | M17: =M39*$M$10 -> 39160.545 | N17: =$N$10*N39 -> 39160.545 | O17: =O10*$H$39 -> 144570.93 | P17: =P10*$H$39 -> 144570.93 | Q17: 45000 | R17: =R39*R10 -> 117000 | S17: 750000 | T17: =T39*T10 -> 375000 | U17: =U39*U10 -> 336910 | V17: =V39*$V$10 -> 467483.9 | W17: =#REF! -> #REF! | X17: =X39*$X$10 -> 370308 | Y17: =#REF! -> #REF! | Z17: =#REF! -> #REF! | AA17: =AA39*AA10 -> #REF! | AB17: =AB39*AB10 -> #REF! | AD17: =W17*$W$86 -> #REF! | AE17: =X17*$W$86 -> 499915.8 | AF17: =Y17*$W$86 -> #REF! | AG17: =Z17*$W$86 -> #REF! | AH17: =AA17*$W$86 -> #REF! | AI17: =AB17*$W$86 -> #REF! | AK17: =AK39*AK11 -> 2118777.9 | AL17: =AL39*AK11 -> 88340.94 | AO17: =AO39*$AO$10 -> 0 | AP17: =AP39*$AO$10 -> 0 | AR17: =AR39*$AR$10 -> 0 | AS17: =AS39*$AO$10 -> 0 | AU17: =SUM(AU18:AU21)*Benchmarks!A92 -> 0 | AV17: =SUM(AV18:AV21)*Benchmarks!A92 -> 0 | AX17: =SUM(AX18:AX21)*Benchmarks!A92 -> 0 | AY17: =SUM(AY18:AY21)*Benchmarks!A92 -> 0
F18: Fit-out | G18: 336979 | H18: ='[1]Final Account'!I10 -> 398819.34 | I18: 224045.83 | J18: 541514 | K18: =48062290+2694850+2508770 -> 53265910 | M18: =M40*$M$10 -> 1069883.8 | N18: =$N$10*N40 -> 492100 | O18: =K40*O10 -> 3949743.3 | P18: =L40*P10 -> 1816710 | Q18: =Q40*Q10 -> 260000 | R18: =R40*R10 -> 1560000 | S18: =S40*S10+(S10*S40)*10% -> 11280228 | T18: =T40*T10+(T40+T10)*10% -> 5130760.8 | U18: =U40*U10+(U10*U40)*10% -> 5188414 | V18: =V40*$V$10 -> 6391909.2 | W18: =#REF!+#REF! -> #REF! | X18: =X40*$X$10 -> 3703080 | Y18: =#REF!+#REF!+#REF!+#REF!-Y6 -> #REF! | Z18: =#REF!+#REF!+#REF!+#REF!-Z6 -> #REF! | AA18: =AA40*AA10 -> #REF! | AB18: =AB40*AB10 -> #REF! | AD18: =W18*$W$86 -> #REF! | AE18: =X18*$W$86 -> 4999158 | AF18: =Y18*$W$86 -> #REF! | AG18: =Z18*$W$86 -> #REF! | AH18: =AA18*$W$86 -> #REF! | AI18: =AB18*$W$86 -> #REF! | AJ18: =AJ40 -> 0.6 | AK18: =AK40*AK11 -> 8719846.8 | AL18: =AL40*AK11 -> 363567.82 | AN18: =AN40 -> 1 | AO18: =AO40*$AO$10 -> 0 | AP18: =AP40*$AO$10 -> 0 | AQ18: =AQ40 -> 1 | AR18: =AR40*$AR$10 -> 0 | AS18: =AS40*$AR$10 -> 0 | AU18: =AU40*$AU$10 -> 0 | AV18: =AV40*$AU$10 -> 0 | AX18: =AX40*$AU$10 -> 0 | AY18: =AY40*$AU$10 -> 0
F19: CAT A Works | W19: 0 | X19: 0 | Y19: =SUM(#REF!) -> #REF! | Z19: =SUM(#REF!) -> #REF! | AA19: =SUM(#REF!) -> #REF! | AB19: =SUM(#REF!) -> #REF! | AD19: 0 | AE19: 0 | AF19: =Y19*$W$86 -> #REF! | AG19: =Z19*$W$86 -> #REF! | AH19: =AA19*$W$86 -> #REF! | AI19: =AB19*$W$86 -> #REF! | AJ19: =AJ41 -> 0 | AK19: 0 | AL19: 0 | AN19: =AN41 -> 1 | AO19: =AO41*$AO$10 -> 0 | AP19: =AP41*$AO$10 -> 0 | AQ19: =AQ41 -> 1 | AR19: =AR41*$AR$10 -> 0 | AS19: =AS41*$AR$10 -> 0 | AU19: =AU41*$AU$10 -> 0 | AV19: =AV41*$AU$10 -> 0 | AX19: =AX41*$AU$10 -> 0 | AY19: =AY41*$AU$10 -> 0
F20: Furniture | G20: 144402 | H20: ='[1]Final Account'!I11 -> 193768.67 | I20: 0 | J20: 150288 | K20: =7975676 -> 7975676 | M20: =M42*$M$10 -> 160197.15 | N20: =$N$10*N42 -> 160197.15 | O20: =K42*O10 -> 591407.77 | P20: =L42*P10 -> 591407.77 | Q20: 0 | R20: 0 | S20: =S42*S10 -> 1535477.1 | T20: =T10*T42 -> 767738.57 | U20: =U42*U10 -> 1347640 | V20: =V42*$V$10 -> 957081.12 | W20: =#REF! -> #REF! | X20: =X42*$X$10 -> 1419514 | Y20: =#REF! -> #REF! | Z20: =#REF! -> #REF! | AA20: =AA42*AA10 -> 1540494 | AB20: =AB42*AB10 -> 1540494 | AD20: =W20*$W$86 -> #REF! | AE20: =X20*$W$86 -> 1916343.9 | AF20: =Y20*$W$86 -> #REF! | AG20: =Z20*$W$86 -> #REF! | AH20: =AA20*$W$86 -> 2079666.9 | AI20: =AB20*$W$86 -> 2079666.9 | AJ20: =AJ42 -> 0.2 | AK20: =AK42*AK11 -> 1806674.5 | AL20: =AL42*AK11 -> 75328.011 | AN20: =AN42 -> 1 | AO20: =AO42*$AO$10 -> 0 | AP20: =AP42*$AO$10 -> 0 | AQ20: =AQ42 -> 1 | AR20: =AR42*$AR$10 -> 0 | AS20: =AS42*$AR$10 -> 0 | AU20: =AU42*$AU$10 -> 0 | AV20: =AV42*$AU$10 -> 0 | AX20: =AX42*$AU$10 -> 0 | AY20: =AY42*$AU$10 -> 0
F21: AV & Equipment | G21: 108580.29 | H21: ='[1]Final Account'!I12 -> 70503 | I21: 30111 | J21: 130681 | K21: =4578826 -> 4578826 | M21: =M43*$M$10 -> 105450 | N21: =N43*$N$10 -> 91968.991 | O21: =L43*O10 -> 389295 | P21: =P10*K43 -> 339526.49 | Q21: 50000 | R21: =R43*R10 -> 340600 | S21: =S43*S10 -> 1010730 | T21: =T43*T10 -> 505365 | U21: =U43*U10 -> 881515.58 | V21: =V43*$V$10 -> 630000 | W21: =#REF! -> #REF! | X21: =X43*X10 -> 925770 | Y21: =Y6 -> #REF! | Z21: =Z6 -> #REF! | AA21: =AA43*AA10 -> 1004670 | AB21: =AB43*AB10 -> 1004670 | AD21: =W21*$W$86 -> #REF! | AE21: =X21*$W$86 -> 1249789.5 | AF21: =Y21*$W$86 -> #REF! | AG21: =Z21*$W$86 -> #REF! | AH21: =AA21*$W$86 -> 1356304.5 | AI21: =AB21*$W$86 -> 1356304.5 | AJ21: =AJ43 -> 0.25 | AK21: =AK43*AK11 -> 1505562.1 | AL21: =AL43*AK11 -> 62773.343 | AN21: =AN43 -> 1 | AO21: =AO43*$AO$10 -> 0 | AP21: =AP43*$AO$10 -> 0 | AQ21: =AQ43 -> 1 | AR21: =AR43*$AR$10 -> 0 | AS21: =AS43*$AR$10 -> 0 | AU21: =AU43*$AU$10 -> 0 | AV21: =AV43*$AU$10 -> 0 | AX21: =AX43*$AU$10 -> 0 | AY21: =AY43*$AU$10 -> 0
F22: Total | G22: =SUM(G17:G21) -> 637543.29 | H22: =SUM(H17:H21) -> 708451.51 | I22: =SUM(I17:I21) -> 275148.33 | J22: =SUM(J17:J21) -> 846033 | K22: =SUM(K17:K21) -> 69984641 | M22: =SUM(M17:M21) -> 1374691.5 | N22: =SUM(N17:N21) -> 783426.68 | O22: =SUM(O17:O21) -> 5075017 | P22: =SUM(P17:P21) -> 2892215.2 | Q22: =SUM(Q17:Q21) -> 355000 | R22: =SUM(R17:R21) -> 2017600 | S22: =SUM(S17:S21) -> 14576435 | T22: =SUM(T17:T21) -> 6778864.4 | ... X22: =SUM(X17:X21) -> 6418672 | Y22: =Y21+Y20+Y19+Y18+Y17 -> #REF! | Z22: =Z21+Z20+Z19+Z18+Z17 -> #REF! | AA22: =AA21+AA20+AA19+AA18+AA17 -> #REF! | AB22: =AB21+AB20+AB19+AB18+AB17 -> #REF! | AD22: =SUM(AD17:AD21) -> #REF! | AE22: =SUM(AE17:AE21) -> 8665207.2 | AF22: =AF21+AF20+AF19+AF18+AF17 -> #REF! | AG22: =AG21+AG20+AG19+AG18+AG17 -> #REF! | AH22: =AH21+AH20+AH19+AH18+AH17 -> #REF! | AI22: =AI21+AI20+AI19+AI18+AI17 -> #REF! | AK22: =SUM(AK17:AK21) -> 14150861 | AL22: =SUM(AL17:AL21) -> 590010.11 | AO22: =SUM(AO17:AO21) -> 0 | AP22: =SUM(AP17:AP21) -> 0 | AR22: =SUM(AR17:AR21) -> 0 | AS22: =SUM(AS17:AS21) -> 0 | AU22: =SUM(AU17:AU21) -> 0 | AV22: =SUM(AV17:AV21) -> 0 | AX22: =SUM(AX17:AX21) -> 0 | AY22: =SUM(AY17:AY21) -> 0
F23: Rate per SQM | AK23: =AK22/AK10 -> 12326.534 | AL23: =AL22/AK10 -> 513.94609 | AO23: =AO22/AO10 -> #DIV/0! | AR23: =AR22/AR10 -> #DIV/0!
F24: Rate per SQFT | AK24: =AK22/AK11 -> 1145.1736 | AL24: =AL22/AK11 -> 47.747201
F26: LL Contribution | AK26: =AK49*AK11 -> 5782086.7 | AL26: =AL49*AK11 -> 241080
F28: P&L - One Off
F29: Moves | G29: 31699 | H29: ='[1]Final Account'!I15 -> 20343.65 | I29: 49200 | K29: 1000000 | M29: =N29 -> #VALUE! | N29: =N9*Benchmarks!C91 -> #VALUE! | O29: =Benchmarks!C91*Budget!O9 -> #VALUE! | P29: =O29 -> #VALUE! | Q29: =Benchmarks!C91*270 -> #VALUE! | R29: =Q29 -> #VALUE! | S29: =S47*S9*2 -> #VALUE! | T29: =T47*T9*2 -> #VALUE! | U29: =U9*U47*2 -> #VALUE! | V29: =V9*V47 -> #VALUE! | W29: =#REF! -> #REF! | X29: =X47*750 -> 83250 | Y29: =#REF! -> #REF! | Z29: =#REF! -> #REF! | AA29: =AA47*750 -> #REF! | AB29: =AB47*750 -> #REF! | AD29: =W29*$W$86 -> #REF! | AE29: =X29*$W$86 -> 112387.5 | AF29: =Y29*$W$86 -> #REF! | AG29: =Z29*$W$86 -> #REF! | AH29: =AA29*$W$86 -> #REF! | AI29: =AB29*$W$86 -> #REF! | AK29: =AK47*AK9 -> 237442.59 | AL29: =AL47*AK9 -> 9900 | AO29: =AO47*AO9 -> 0 | AP29: =AP47*AO9 -> 0 | AR29: =AR47*AR9 -> 0 | AS29: =AS47*AR9 -> 0 | AU29: =AU47*AU9 -> 0 | AV29: =AV47*AU9 -> 0 | AX29: =AX47*AX9 -> 0 | AY29: =AY47*AX9 -> 0
F30: MMC Tech Costs (5y)
F31: MMC Tech Costs (5y) | S31: =S48*S10 -> 1010730 | T31: =T48*T10 -> 505365 | U31: =U48*U10 -> 1010730 | V31: =V48*V10 -> 630000 | W31: =#REF! -> #REF! | X31: =X48*X10 -> 925770 | Y31: =#REF! -> #REF! | Z31: =#REF! -> #REF! | AA31: =AA48*AA10 -> #REF! | AB31: =AB48*AB10 -> #REF! | AD31: =W31*$W$86 -> #REF! | AE31: =X31*$W$86 -> 1249789.5 | AF31: =Y31*$W$86 -> #REF! | AG31: =Z31*$W$86 -> #REF! | AH31: =AA31*$W$86 -> #REF! | AI31: =AB31*$W$86 -> #REF! | AK31: =AK48*AK10 -> 206503.1 | AL31: =AL48*AK10 -> 8610 | AO31: =AO48*AO10 -> 0 | AP31: =AP48*AO10 -> 0 | AR31: =AR48*AR10 -> 0 | AS31: =AS48*AR10 -> 0 | AU31: =AU10*AU48 -> 0 | AV31: =AV48*AU10 -> 0 | AX31: =AX10*AX48 -> 0 | AY31: =AY48*AX10 -> 0
F34: GRAND TOTAL | G34: Full-fit out | H34: Full Refurb | I34: light-mid touch refurb | J34: Full Fit-out | W34: =W31+W29+W22 -> #REF! | X34: =X31+X29+X22 -> 7427692 | Y34: =Y31+Y29+Y22 -> #REF! | Z34: =Z31+Z29+Z22 -> #REF! | AA34: =AA31+AA29+AA22 -> #REF! | AB34: =AB31+AB29+AB22 -> #REF! | AD34: =AD31+AD29+AD22 -> #REF! | AE34: =AE31+AE29+AE22 -> 10027384 | AF34: =AF31+AF29+AF22 -> #REF! | AG34: =AG31+AG29+AG22 -> #REF! | AH34: =AH31+AH29+AH22 -> #REF! | AI34: =AI31+AI29+AI22 -> #REF! | AK34: =AK31+AK29+AK22-AK26 -> 8812720.3 | AL34: =AL31+AL29+AL22-AL26 -> 367440.11 | AO34: =AO31+AO29+AO22 -> 0 | AP34: =AP31+AP29+AP22 -> 0 | AR34: =AR31+AR29+AR22 -> 0 | AS34: =AS31+AS29+AS22 -> 0 | AU34: =AU31+AU29+AU22 -> 0 | AV34: =AV31+AV29+AV22 -> 0 | AX34: =AX31+AX29+AX22 -> 0 | AY34: =AY31+AY29+AY22 -> 0
G35: 5% sit-stand (all rest are with crank) | H35: Full Sit-stand | I35: Reused Furniture | J35: Full-Sit Stand + HS Monitor Arms
G36: Old AV Standards | H36: All DTENs | I36: New AV Standards | J36: New AV Standards
J37: Improved LED Lighting (GCL) circa 4£/ft²
F38: Rates (/m²) | AD38: Rates ($/ft²) | AJ38: Factor | AN38: Factor | AQ38: Factor | AT38: Factor | AW38: Factor
F39: Professional Fees | G39: =G17/$G$10 -> 7.4288837 | H39: =H17/$H$10 -> 5.57049 | I39: =I17/$I$10 -> 6.3998476 | J39: =J17/$J$10 -> 2.7781055 | K39: =K17/$K$10 -> 11.897797 | M39: =O39 -> 5.57049 | N39: =O39 -> 5.57049 | O39: =O17/$O$10 -> 5.57049 | P39: =P17/$P$10 -> 5.57049 | Q39: =Q17/Q10 -> 1.7307692 | R39: 4.5 | S39: =S17/S10 -> 11.130569 | T39: =S39 -> 11.130569 | U39: 5 | V39: =S39 -> 11.130569 | W39: =W17/$W$10 -> #REF! | X39: 6 | Y39: =Y17/Y10 -> #REF! | Z39: =Z17/Z10 -> #REF! | AA39: =Z39 -> #REF! | AB39: =AA39 -> #REF! | AD39: =W39*$W$86 -> #REF! | AE39: =X39*$W$86 -> 8.1 | AF39: =Y39*$W$86 -> #REF! | AG39: =Z39*$W$86 -> #REF! | AH39: =AA39*$W$86 -> #REF! | AI39: =AB39*$W$86 -> #REF! | AJ39: 0.5 | AK39: =Benchmarks!$C$92*AJ39 -> 171.46437 | AL39: =Benchmarks!$G$92*AJ39 -> 7.1490852 | AO39: =Benchmarks!E92 -> 0 | AP39: =Benchmarks!I92 -> 0 | AR39: =10%*SUM(AR40:AR43) -> 211.10092 | AS39: =AR39*$AJ$6 -> 8.801703 | AU39: =(AU40+AU42+AU43)*Benchmarks!$A$92 -> 84.679553 | AV39: =Benchmarks!$G$92 -> 14.29817 | AX39: =(AX40+AX42+AX43)*Benchmarks!$A$92 -> 267.79314 | AY39: =Benchmarks!$G$92 -> 14.29817
F40: Fit Out | G40: =G18/$G$10 -> 52.611866 | H40: =H18/$H$10 -> 48.976954 | I40: =I18/$I$10 -> 68.306655 | J40: =J18/$J$10 -> 63.880382 | K40: =K18/$K$10 -> 152.18831 | L40: 70 | M40: =O40 -> 152.18831 | N40: =P40 -> 70 | O40: =O18/$O$10 -> 152.18831 | P40: =P18/$P$10 -> 70 | Q40: 10 | R40: 60 | S40: =O40 -> 152.18831 | T40: =S40 -> 152.18831 | U40: =P40 -> 70 | V40: =S40 -> 152.18831 | W40: =W18/$W$10 -> #REF! | X40: 60 | Y40: =Y18/Y10 -> #REF! | Z40: =Z18/Z10 -> #REF! | AA40: =Y40 -> #REF! | AB40: =Z40 -> #REF! | AD40: =W40*$W$86 -> #REF! | AE40: =X40*$W$86 -> 81 | AF40: =Y40*$W$86 -> #REF! | AG40: =Z40*$W$86 -> #REF! | AH40: =AA40*$W$86 -> #REF! | AI40: =AB40*$W$86 -> #REF! | AJ40: 0.6 | AK40: =Benchmarks!$E$93*AJ40 -> 705.66294 | AL40: =Benchmarks!$G$93*AJ40 -> 29.422115 | AN40: 1 | AO40: =Benchmarks!E93*AN40 -> 1176.1049 | AP40: =Benchmarks!I93 -> 49.036859 | AQ40: 1 | AR40: =527.7523*AQ40 -> 527.7523 | AS40: =AR40*$AJ$6 -> 22.004257 | AT40: 1 | AU40: =AK40 -> 705.66294 | AV40: =AL40 -> 29.422115 | AW40: 1 | AX40: =AO40 -> 1176.1049 | AY40: =AP40*80% -> 39.229487
F41: CAT A Works | AJ41: 0 | AK41: =0*AJ41 -> 0 | AL41: =0*AJ41 -> 0 | AN41: 1 | AO41: =Benchmarks!E94*AN41 -> 0 | AQ41: 1 | AR41: =527.7523*AQ41 -> 527.7523 | AS41: =AR41*$AJ$6 -> 22.004257 | AT41: 1 | AW41: 1
F42: Furniture | G42: =G20/$G$10 -> 22.545199 | H42: =H20/$H$10 -> 23.795735 | I42: =I20/$I$10 -> 0 | J42: =J20/$J$10 -> 17.728914 | K42: =K20/$K$10 -> 22.787646 | L42: =K42 -> 22.787646 | M42: =O42 -> 22.787646 | N42: =P42 -> 22.787646 | O42: =O20/$O$10 -> 22.787646 | P42: =P20/$P$10 -> 22.787646 | Q42: 0 | R42: 0 | S42: =O42 -> 22.787646 | T42: =S42 -> 22.787646 | U42: 20 | V42: =P42 -> 22.787646 | W42: =W20/$W$10 -> #REF! | X42: 23 | Y42: =Y20/$Y$10 -> #REF! | Z42: =Z20/$Z$10 -> #REF! | AA42: =X42 -> 23 | AB42: =X42 -> 23 | AD42: =W42*$W$86 -> #REF! | AE42: =X42*$W$86 -> 31.05 | AF42: =Y42*$W$86 -> #REF! | AG42: =Z42*$W$86 -> #REF! | AH42: =AA42*$W$86 -> 31.05 | AI42: =AB42*$W$86 -> 31.05 | AJ42: 0.2 | AK42: =Benchmarks!$C$95*AJ42 -> 146.20707 | AL42: =Benchmarks!$G$95*AJ42 -> 6.096 | AN42: 1 | AO42: =Benchmarks!E95*AN42 -> 0 | AP42: =Benchmarks!I95 -> 0 | AQ42: 1 | AR42: =527.7523*AQ42 -> 527.7523 | AS42: =AR42*$AJ$6 -> 22.004257 | AT42: 1 | AU42: =AO42 -> 0 | AV42: =AP42 -> 0 | AW42: 1 | AX42: =AR42 -> 527.7523 | AY42: =AS42 -> 22.004257
F43: AV & Equipment | G43: =G21/$G$10 -> 16.952426 | H43: =H21/$H$10 -> 8.6581113 | I43: =I21/$I$10 -> 9.1801829 | J43: =J21/$J$10 -> 15.415949 | K43: =K21/$K$10 -> 13.08236 | L43: 15 | M43: =O43 -> 15 | N43: =P43 -> 13.08236 | O43: =O21/$O$10 -> 15 | P43: =P21/$P$10 -> 13.08236 | Q43: =Q21/Q10 -> 1.9230769 | R43: 13.1 | S43: =O43 -> 15 | T43: =S43 -> 15 | U43: =P43 -> 13.08236 | V43: =S43 -> 15 | W43: =W21/$W$10 -> #REF! | X43: 15 | Y43: =Y21/$Y$10 -> #REF! | Z43: =Z21/$Z$10 -> #REF! | AA43: 15 | AB43: 15 | AD43: =W43*$W$86 -> #REF! | AE43: =X43*$W$86 -> 20.25 | AF43: =Y43*$W$86 -> #REF! | AG43: =Z43*$W$86 -> #REF! | AH43: =AA43*$W$86 -> 20.25 | AI43: =AB43*$W$86 -> 20.25 | AJ43: 0.25 | AK43: =Benchmarks!$C$96*AJ43 -> 121.83923 | AL43: =Benchmarks!$G$96*AJ43 -> 5.08 | AN43: 1 | AO43: =Benchmarks!E96*AN43 -> 0 | AP43: =Benchmarks!I96 -> 0 | AQ43: 1 | AR43: =527.7523*AQ43 -> 527.7523 | AS43: =AR43*AJ6 -> 22.004257 | AT43: 1 | AU43: =AO43 -> 0 | AV43: =AP43 -> 0 | AW43: 1 | AX43: =AR43 -> 527.7523 | AY43: =AS43 -> 22.004257
F44: Total | AK44: =SUM(AK39:AK43) -> 1145.1736 | AL44: =SUM(AL39:AL43) -> 47.747201 | AO44: =SUM(AO39:AO43) -> 1176.1049 | AP44: =SUM(AP39:AP43) -> 49.036859 | AR44: =SUM(AR39:AR43) -> 2322.1101 | AS44: =SUM(AS39:AS43) -> 96.818733 | AU44: =SUM(AU39:AU43) -> 790.3425 | AV44: =SUM(AV39:AV43) -> 43.720286 | AX44: =SUM(AX39:AX43) -> 2499.4026 | AY44: =SUM(AY39:AY43) -> 97.536172
F47: Moves (/person) | G47: =Benchmarks!C91 -> Global Benchmark | H47: =G47 -> Global Benchmark | I47: =H47 -> Global Benchmark | J47: =I47 -> Global Benchmark | K47: =J47 -> Global Benchmark | L47: =K47 -> Global Benchmark | M47: =L47 -> Global Benchmark | N47: =M47 -> Global Benchmark | O47: =N47 -> Global Benchmark | ... T47: =S47 -> Global Benchmark | U47: =S47 -> Global Benchmark | V47: =S47 -> Global Benchmark | W47: =W29/750 -> #REF! | X47: 111 | Y47: =Y29/750 -> #REF! | Z47: =Z29/750 -> #REF! | AA47: =Y47 -> #REF! | AB47: =Z47 -> #REF! | AD47: =W47*$W$86 -> #REF! | AE47: =X47*$W$86 -> 149.85 | AF47: =Y47*$W$86 -> #REF! | AG47: =Z47*$W$86 -> #REF! | AH47: =AA47*$W$86 -> #REF! | AI47: =AB47*$W$86 -> #REF! | AJ47: 0.3 | AK47: =AL47/Benchmarks!B68 -> 1079.2845 | AL47: =Benchmarks!B85*AJ47 -> 45 | AO47: =AP47/Benchmarks!B68 -> 1079.2845 | AP47: =AL47 -> 45 | AR47: =AO47 -> 1079.2845 | AS47: =AP47 -> 45 | AU47: =AR47 -> 1079.2845 | AV47: =AS47 -> 45 | AX47: =AU47 -> 1079.2845 | AY47: =AV47 -> 45
F48: MMC Tech Costs (5y) | G48: 15 | H48: =G48 -> 15 | I48: =H48 -> 15 | J48: =I48 -> 15 | K48: =J48 -> 15 | L48: =K48 -> 15 | M48: =L48 -> 15 | N48: =M48 -> 15 | O48: =N48 -> 15 | ... T48: =S48 -> 15 | U48: =S48 -> 15 | V48: =S48 -> 15 | W48: =W31/W10 -> #REF! | X48: 15 | Y48: =Y31/Y10 -> #REF! | Z48: =Z31/Z10 -> #REF! | AA48: =Y48 -> #REF! | AB48: =Z48 -> #REF! | AD48: =W48*$W$86 -> #REF! | AE48: =X48*$W$86 -> 20.25 | AF48: =Y48*$W$86 -> #REF! | AG48: =Z48*$W$86 -> #REF! | AH48: =AA48*$W$86 -> #REF! | AI48: =AB48*$W$86 -> #REF! | AJ48: 0.5 | AK48: =AL48/Benchmarks!B68 -> 179.88075 | AL48: =Benchmarks!B84*Budget!AJ48 -> 7.5 | AO48: =AP48/Benchmarks!B68 -> 179.88075 | AP48: =AL48 -> 7.5 | AR48: =AO48 -> 179.88075 | AS48: =AL48 -> 7.5 | AU48: =AR48 -> 179.88075 | AV48: =AS48 -> 7.5 | AX48: =AU48 -> 179.88075 | AY48: =AV48 -> 7.5
F49: LL Contribution | AK49: =Benchmarks!C108 -> 467.92156 | AL49: =AK49*AJ6 -> 19.509657
AK54: Assumptions | AO54: Assumptions | AR54: Assumptions | AU54: Assumptions | AX54: Assumptions
AK56: Minimal building works as refresh the space and improve acoustics. No partitions ot be moved
AK57: Some furniture to be purchased including phone booths
AK58: Minimal AV Upgrade
AK59: Minimal moves required
AK60: Minimal MMC Tech upgrades required.
AK61: Office area estimated by CBRE
M69: New Fit-out | N69: New Fit-out | O69: New Fit-out | P69: New Fit-out | S69: New Fit-out | T69: New Fit-out | U69: New Fit-out | V69: New Fit-out
M70: Sit-stand Desks | N70: Sit-stand Desks | O70: Sit-stand Desks | P70: Sit-stand Desks | S70: Sit-stand Desks | T70: Sit-stand Desks | U70: Sit-stand Desks | V70: Sit-stand Desks
M71: New AV Standards | N71: New AV Standards | O71: New AV Standards | P71: New AV Standards | S71: New AV Standards | T71: New AV Standards | U71: Refresh to AV | V71: New AV Standards
M72: No works in-situ | N72: No works in-situ | O72: No works in-situ | P72: No works in-situ | S72: Works in-situ | T72: Works in-situ | U72: Works in-situ | V72: No Works in-situ
M73: Smart-office | N73: Smart-office | O73: Smart-office | P73: Smart-office | S73: Smart-office | T73: Smart-office | U73: Smart-office | V73: Smart-office
N74: Mid-low end rates | P74: Mid-low end rates | T74: One floor fit-out only | U74: Light Touch
W86: 1.35

Sheet Benchmarks
A1: Country | B1: City | C1: CAT B AGILE | F1: Furniture Trad | I1: Furniture Agile | L1: Security | M1: AV traditional | P1: AV AGILE | S1: Fees | T1: IT | W1: Contingency | X1: Traditional Fitout | Z1: Agile Fit-out | AC1: Furniture
C2: LOW | D2: MED | E2: HIGH | F2: LOW | G2: MED | H2: HIGH | I2: LOW | J2: MED | K2: HIGH | L2: LOW, MED & High | M2: LOW | N2: MED | O2: HIGH | P2: LOW | Q2: MED | R2: HIGH | S2: % | T2: LOW | U2: MED | V2: HIGH | W2: % | X2: LOW | Y2: HIGH | Z2: LOW | AA2: HIGH | AC2: INSTALL | AD2: LOGISTICS | AE2: IMPORT Tax | AF2: TIME (wks)
A3: Angola | B3: Luanda | C3: 995 | D3: 1194 | E3: 1830 | F3: 95+ | G3: 120+ | H3: 165+ | I3: 145+ | J3: 175+ | K3: 220+ | L3: 40+ | M3: 60+ | N3: 100+ | O3: 180+ | P3: 85+ | Q3: 130+ | R3: 245+ | S3: 0.22 | T3: 65+ | V3: 125+ | W3: 0.1 | X3: 1,740+ | Y3: 3,239+ | Z3: 1,769+ | AA3: 3,271+
A4: Austria | B4: Vienna | C4: 547 | D4: 670 | E4: 1022 | F4: 105 | G4: 132 | H4: 182 | I4: 160 | J4: 193 | K4: 242 | L4: 40 | M4: 60 | N4: 100 | O4: 180 | P4: 85 | Q4: 131 | R4: 246 | S4: 0.18 | T4: 65 | V4: 125 | W4: 0.1 | X4: 1084 | Y4: 2056 | Z4: 1150 | AA4: 2150
A5: Belgium | B5: Brussels | C5: 436 | D5: 551 | E5: 847 | F5: 105 | G5: 132 | H5: 182 | I5: 160 | J5: 193 | K5: 242 | L5: 40 | M5: 60 | N5: 100 | O5: 180 | P5: 85 | Q5: 131 | R5: 246 | S5: 0.18 | T5: 65 | V5: 125 | W5: 0.1 | X5: 933 | Y5: 1816 | Z5: 1006 | AA5: 1923
A6: Botswana | B6: Gaborone | C6: 752 | D6: 896 | E6: 1368 | F6: 151 | G6: 191 | H6: 262 | I6: 231 | J6: 278 | K6: 350 | L6: 48 | M6: 72 | N6: 120 | O6: 216 | P6: 102 | Q6: 157 | R6: 296 | S6: 0.19 | T6: 78 | V6: 150 | W6: 0.1 | X6: 1477 | Y6: 2738 | Z6: 1568 | AA6: 2863
A7: Bulgaria | B7: Sofia | C7: 320 | D7: 498 | E7: 682 | F7: 108 | G7: 137 | H7: 188 | I7: 165 | J7: 200 | K7: 251 | L7: 40 | M7: 60 | N7: 100 | O7: 180 | P7: 85 | Q7: 131 | R7: 246 | S7: 0.17 | T7: 65 | V7: 125 | W7: 0.1 | X7: 773 | Y7: 1586 | Z7: 857 | AA7: 1706
A8: Croatia | B8: Zagreb | C8: 445 | D8: 540 | E8: 782 | F8: 109 | G8: 138 | H8: 190 | I8: 167 | J8: 201 | K8: 253 | L8: 40 | M8: 60 | N8: 100 | O8: 180 | P8: 85 | Q8: 131 | R8: 246 | S8: 0.21 | T8: 65 | V8: 125 | W8: 0.1 | X8: 973 | Y8: 1778 | Z8: 1052 | AA8: 1896
A9: Czech republic | B9: Prague | C9: 395 | D9: 506 | E9: 759 | F9: 105 | G9: 133 | H9: 183 | I9: 161 | J9: 194 | K9: 244 | L9: 40 | M9: 60 | N9: 100 | O9: 180 | P9: 85 | Q9: 131 | R9: 246 | S9: 0.17 | T9: 65 | V9: 125 | W9: 0.1 | X9: 871 | Y9: 1685 | Z9: 947 | AA9: 1797
A10: Denmark | B10: Copenhagen | C10: 588 | D10: 728 | E10: 1192 | F10: 110 | G10: 139 | H10: 191 | I10: 168 | J10: 203 | K10: 255 | L10: 40 | M10: 60 | N10: 100 | O10: 180 | P10: 85 | Q10: 131 | R10: 246 | S10: 0.26 | T10: 65 | V10: 125 | W10: 0.1 | X10: 1220 | Y10: 2447 | Z10: 1292 | AA10: 2541
A11: Egypt | B11: Cairo | C11: 525 | D11: 783 | E11: 1142 | F11: 182 | G11: 230 | H11: 317 | I11: 278 | J11: 336 | K11: 422 | L11: 64 | M11: 96 | N11: 160 | O11: 288 | P11: 136 | Q11: 209 | R11: 394 | S11: 0.15 | T11: 104 | V11: 200 | W11: 0.1 | X11: 1247 | Y11: 2586 | Z11: 1383 | AA11: 2778
A12: Estonia | B12: Tallinn | C12: 431 | D12: 522 | E12: 857 | F12: 109 | G12: 138 | H12: 190 | I12: 167 | J12: 201 | K12: 253 | L12: 40 | M12: 60 | N12: 100 | O12: 180 | P12: 85 | Q12: 131 | R12: 246 | S12: 0.14 | T12: 65 | V12: 125 | W12: 0.1 | X12: 903 | Y12: 1782 | Z12: 978 | AA12: 1888
A13: Ethiopia | B13: Addis Ababa | C13: 768 | D13: 917 | E13: 1409 | F13: 161 | G13: 203 | H13: 279 | I13: 245 | J13: 296 | K13: 372 | L13: 52 | M13: 78 | N13: 130 | O13: 234 | P13: 110 | Q13: 170 | R13: 320 | S13: 0.17 | T13: 85 | V13: 163 | W13: 0.1 | X13: 1508 | Y13: 2815 | Z13: 1606 | AA13: 2950
A14: Finland | B14: Helsinki | C14: 775 | D14: 928 | E14: 1382 | F14: 114 | G14: 144 | H14: 198 | I14: 174 | J14: 210 | K14: 264 | L14: 40 | M14: 60 | N14: 100 | O14: 180 | P14: 85 | Q14: 131 | R14: 246 | S14: 0.16 | T14: 65 | V14: 125 | W14: 0.1 | X14: 1386 | Y14: 2530 | Z14: 1442 | AA14: 2606
A15: France | B15: Paris | C15: 737 | D15: 890 | E15: 1384 | F15: 105 | G15: 132 | H15: 182 | I15: 160 | J15: 193 | K15: 242 | L15: 40 | M15: 60 | N15: 100 | O15: 180 | P15: 85 | Q15: 131 | R15: 246 | S15: 0.18 | T15: 65 | V15: 125 | W15: 0.1 | X15: 1344 | Y15: 2550 | Z15: 1397 | AA15: 2620
... A37: Netherlands | B37: Amsterdam | C37: 650 | D37: 800 | E37: 1090 | F37: 105 | G37: 132 | H37: 182 | I37: 160 | J37: 193 | K37: 242 | L37: 40 | M37: 60 | N37: 100 | O37: 180 | P37: 85 | Q37: 131 | R37: 246 | S37: 0.18 | T37: 65 | V37: 125 | W37: 0.1 | X37: 1224 | Y37: 2147 | Z37: 1284 | AA37: 2238
A38: Nigeria | B38: Abuja | C38: 1089 | D38: 1445 | E38: 2048 | F38: 95+ | G38: 120+ | H38: 165+ | I38: 145+ | J38: 175+ | K38: 220+ | L38: 40+ | M38: 60+ | N38: 100+ | O38: 180+ | P38: 85+ | Q38: 130+ | R38: 245+ | S38: 0.22 | T38: 65+ | V38: 125+ | W38: 0.1 | X38: 1,871+ | Y38: 3,547+ | Z38: 1,895+ | AA38: 3,564+
A39: Norway | B39: Oslo | C39: 697 | D39: 1100 | E39: 1667 | F39: 114 | G39: 144 | H39: 198 | I39: 174 | J39: 210 | K39: 264 | L39: 40 | M39: 60 | N39: 100 | O39: 180 | P39: 85 | Q39: 131 | R39: 246 | S39: 0.19 | T39: 65 | V39: 125 | W39: 0.1 | X39: 1312 | Y39: 2981 | Z39: 1374 | AA39: 3040
A40: Oman | B40: Muscat | C40: 672 | D40: 877 | E40: 1271 | F40: 126 | G40: 160 | H40: 219 | I40: 193 | J40: 233 | K40: 293 | L40: 42 | M40: 63 | N40: 105 | O40: 189 | P40: 89 | Q40: 137 | R40: 259 | S40: 0.18 | T40: 68 | V40: 131 | W40: 0.1 | X40: 1293 | Y40: 2466 | Z40: 1368 | AA40: 2565
A41: Poland | B41: Warsaw | C41: 486 | D41: 604 | E41: 863 | F41: 109 | G41: 138 | H41: 190 | I41: 167 | J41: 201 | K41: 253 | L41: 40 | M41: 60 | N41: 100 | O41: 180 | P41: 85 | Q41: 131 | R41: 246 | S41: 0.17 | T41: 65 | V41: 125 | W41: 0.1 | X41: 1000 | Y41: 1834 | Z41: 1073 | AA41: 1942
A42: Portugal | B42: Lisbon | C42: 454 | D42: 608 | E42: 922 | F42: 105 | G42: 132 | H42: 182 | I42: 160 | J42: 193 | K42: 242 | L42: 40 | M42: 60 | N42: 100 | O42: 180 | P42: 85 | Q42: 131 | R42: 246 | S42: 0.15 | T42: 65 | V42: 125 | W42: 0.1 | X42: 935 | Y42: 1873 | Z42: 1005 | AA42: 1973
A43: Qatar | B43: Doha | C43: 782 | D43: 1072 | E43: 1516 | F43: 125 | G43: 158 | H43: 218 | I43: 191 | J43: 231 | K43: 290 | L43: 42 | M43: 63 | N43: 105 | O43: 189 | P43: 89 | Q43: 137 | R43: 259 | S43: 0.18 | T43: 68 | V43: 131 | W43: 0.1 | X43: 1443 | Y43: 2798 | Z43: 1509 | AA43: 2879
A44: Romania | B44: Bucharest | C44: 346 | D44: 468 | E44: 751 | F44: 111 | G44: 140 | H44: 193 | I44: 170 | J44: 205 | K44: 257 | L44: 40 | M44: 60 | N44: 100 | O44: 180 | P44: 85 | Q44: 131 | R44: 246 | S44: 0.18 | T44: 65 | V44: 125 | W44: 0.1 | X44: 819 | Y44: 1699 | Z44: 903 | AA44: 1818
A45: Russia | B45: Moscow | C45: 480 | D45: 625 | E45: 1000 | F45: 138 | G45: 174 | H45: 239 | I45: 210 | J45: 254 | K45: 319 | L45: 50 | M45: 75 | N45: 125 | O45: 225 | P45: 106 | Q45: 164 | R45: 308 | S45: 0.12 | T45: 81 | V45: 156 | W45: 0.1 | X45: 1035 | Y45: 2102 | Z45: 1131 | AA45: 2238
A46: Saudi Arabia | B46: Riyadh | C46: 725 | D46: 930 | E46: 1336 | F46: 141 | G46: 178 | H46: 244 | I46: 215 | J46: 259 | K46: 326 | L46: 48 | M46: 72 | N46: 120 | O46: 216 | P46: 102 | Q46: 157 | R46: 296 | S46: 0.17 | T46: 78 | V46: 150 | W46: 0.1 | X46: 1403 | Y46: 2630 | Z46: 1487 | AA46: 2746
A47: Serbia | B47: Belgrade | C47: 340 | D47: 418 | E47: 648 | F47: 135 | G47: 170 | H47: 234 | I47: 206 | J47: 249 | K47: 312 | L47: 48 | M47: 72 | N47: 120 | O47: 216 | P47: 102 | Q47: 157 | R47: 296 | S47: 0.17 | T47: 78 | V47: 150 | W47: 0.1 | X47: 875 | Y47: 1684 | Z47: 981 | AA47: 1843
A48: Slovakia | B48: Bratislava | C48: 319 | D48: 528 | E48: 690 | F48: 109 | G48: 138 | H48: 190 | I48: 167 | J48: 201 | K48: 253 | L48: 40 | M48: 60 | N48: 100 | O48: 180 | P48: 85 | Q48: 131 | R48: 246 | S48: 0.15 | T48: 65 | V48: 125 | W48: 0.1 | X48: 760 | Y48: 1574 | Z48: 843 | AA48: 1692
A49: South Africa | B49: Cape Town | C49: 556 | D49: 711 | E49: 1085 | F49: 142 | G49: 179 | H49: 246 | I49: 216 | J49: 261 | K49: 328 | L49: 48 | M49: 72 | N49: 120 | O49: 216 | P49: 102 | Q49: 157 | R49: 296 | S49: 0.18 | T49: 78 | V49: 150 | W49: 0.1 | X49: 1186 | Y49: 2309 | Z49: 1283 | AA49: 2445
A50: South Africa | B50: Johannesburg | C50: 551 | D50: 704 | E50: 1075 | F50: 142 | G50: 179 | H50: 246 | I50: 216 | J50: 261 | K50: 328 | L50: 48 | M50: 72 | N50: 120 | O50: 216 | P50: 102 | Q50: 157 | R50: 296 | S50: 0.18 | T50: 78 | V50: 150 | W50: 0.1 | X50: 1178 | Y50: 2295 | Z50: 1276 | AA50: 2432
... A66: Zambia | B66: Lusaka | C66: 765 | D66: 907 | E66: 1342 | F66: 156 | G66: 197 | H66: 271 | I66: 238 | J66: 287 | K66: 361 | L66: 50 | M66: 75 | N66: 125 | O66: 225 | P66: 106 | Q66: 164 | R66: 308 | S66: 0.19 | T66: 81 | V66: 156 | W66: 0.1 | X66: 1510 | Y66: 2735 | Z66: 1605 | AA66: 2869
A67: EUR / USD | B67: ='2025 FX Rates'!F49 -> 1.05 | C67: =C9*$B$67 -> 414.75 | D67: =D9*$B$67 -> 531.3 | E67: =E9*$B$67 -> 796.95 | F67: =F9*$B$67 -> 110.25 | G67: =G9*$B$67 -> 139.65 | H67: =H9*$B$67 -> 192.15 | I67: =I9*$B$67 -> 169.05 | J67: =J9*$B$67 -> 203.7 | ... AA67: =AA9*$B$67 -> 1886.85
A68: USD/CZK | B68: ='2025 FX Rates'!F41 -> 0.04169429 | C68: =C67/$B$68 -> 9947.4053 | D68: =D67/$B$68 -> 12742.752 | E68: =E67/$B$68 -> 19114.128 | F68: =F67/$B$68 -> 2644.247 | G68: =G67/$B$68 -> 3349.3795 | H68: =H67/$B$68 -> 4608.5447 | I68: =I67/$B$68 -> 4054.512 | J68: =J67/$B$68 -> 4885.5611 | ... T68: =T67/$B$68 -> 1636.9148 | V68: =V67/$B$68 -> 3147.9131 | W68: =W67/$B$68 -> 2.5183304 | X68: =X67/$B$68 -> 21934.658 | Y68: =Y67/$B$68 -> 42433.868 | Z68: =Z67/$B$68 -> 23848.589 | AA68: =AA67/$B$68 -> 45254.398
A69: Inflation rate | B69: 0.2 | C69: =C68+C68*$B$69 -> 11936.886 | D69: =D68+D68*$B$69 -> 15291.302 | E69: =E68+E68*$B$69 -> 22936.954 | F69: =F68+F68*$B$69 -> 3173.0964 | G69: =G68+G68*$B$69 -> 4019.2554 | H69: =H68+H68*$B$69 -> 5530.2537 | I69: =I68+I68*$B$69 -> 4865.4144 | J69: =J68+J68*$B$69 -> 5862.6733 | ... R69: =R68+R68*$B$69 -> 7434.1115 | T69: =T68+T68*$B$69 -> 1964.2977 | V69: =V68+V68*$B$69 -> 3777.4957 | X69: =X68+X68*$B$69 -> 26321.59 | Y69: =Y68+Y68*$B$69 -> 50920.642 | Z69: =Z68+Z68*$B$69 -> 28618.307 | AA69: =AA68+AA68*$B$69 -> 54305.278
I70: Med High | J70: =(J69+K69)/2 -> 6618.1724 | P70: Med High | Q70: =(Q69+R69)/2 -> 5696.4635 | Z70: =(Z69+AA69)/2 -> 41461.792 | AC70: Medium grade benchmark
Z71: =(AA69+Z70)/2 -> 47883.535 | AC71: Medium to high grade benchmark
A72: sqmt to sqft | B72: 10.7639 | C72: =C69/$B$72 -> 1108.9741 | D72: =D69/$B$72 -> 1420.6099 | E72: =E69/$B$72 -> 2130.9148 | F72: =F69/$B$72 -> 294.79058 | G72: =G69/$B$72 -> 373.40141 | H72: =H69/$B$72 -> 513.77787 | I72: =I69/$B$72 -> 452.01223 | J72: =J69/$B$72 -> 544.6607 | ... R72: =R69/$B$72 -> 690.65222 | T72: =T69/$B$72 -> 182.48941 | U72: =(T72+V72)/2 -> 266.71529 | V72: =V69/$B$72 -> 350.94117 | X72: =X69/$B$72 -> 2445.3581 | Y72: =Y69/$B$72 -> 4730.687 | Z72: =Z69/$B$72 -> 2658.7303 | AA72: =AA69/$B$72 -> 5045.1303
P73: Med High | Q73: =(Q72+R72)/2 -> 529.21929
A74: Local Consultant Rate | B74: ='Local Consultant Advice1'!G81+'Local consultant Advice 2'!G54 -> 418.91099 | C74: =B74*B67 -> 439.85654
C75: =C74/B68 -> 10549.563
A76: Inflation rate | B76: 0.2 | C76: =C75+C75*$B$69 -> 12659.476
A77: sqmt to sqft | B77: 10.7639 | C77: =C76/$B$77 -> 1176.1049
A79: Fit Out Quality Summary
A80: Low | B80: Medium | C80: High
A81: =C77+L72+V72 -> 1639.3473 | B81: =D72+L72+V72 -> 1883.8522 | C81: =E72+L72+V72 -> 2594.1571 | D81: CZK /Sqft
A83: BENCHMARK
A84: MGTI 5 Year | B84: 15 | C84: $/sqm | D84: =(B84*B68)/B72 -> 0.058102951 | E84: CZK/Sqft
A85: Move | B85: 150 | C85: $/ HC | D85: =B85/B68 -> 3597.6149 | E85: CZK/HC
A86: AV | B86: 16 | C86: £/sqft | D86: =(B86*'2025 FX Rates'!F138)/B68 -> 487.3569 | E86: CZK/sqft
A87: Furniture | B87: 24 | C87: £/sqft | D87: =(B87*'2025 FX Rates'!F138)/B68 -> 731.03535 | E87: CZK/sqft | Z87: =(Z55+AA55)/2 -> 2417.5 | AA87: medium eur/sqm
Z88: =Z87+(Z87*$B$69) -> 2901 | AA88: incl inflation
C90: Rates (CZK/ft²) | E90: Local Consultant Advice | G90: Rates (USD/ft²) | I90: Local Consultant Advice | AB90: =(Z87+AA55)/2 -> 2774.25 | AC90: medium to high eur/ sqm
C91: Global Benchmark | D91: Benchmark previous Project (N/A) | E91: TBC - Date | G91: =C91 -> Global Benchmark | H91: Benchmark previous Project | I91: =E91 -> TBC - Date | L91: Check | AB91: =AB90+(AB90*$B$69) -> 3329.1 | AC91: incl inflation
A92: 0.12 | B92: Professional Fees | C92: =(SUM(C93:C96)*A92) -> 342.92874 | E92: ='Local Consultant Advice1'!C21/Budget!AK10 -> 0 | F92: =E92/(E93+E95+E96) -> 0 | G92: =C92*$B$68 -> 14.29817 | H92: =D92*$B$68 -> 0 | I92: =E92*$B$68 -> 0 | K92: =I92/(I93+I95+I96) -> 0 | L92: =E92/I92 -> #DIV/0!
A93: Low grade | B93: Internal Works | C93: =A81 -> 1639.3473 | E93: =C77 -> 1176.1049 | G93: =E93*$B$68 -> 49.036859 | H93: =D93*$B$68 -> 0 | I93: =E93*$B$68 -> 49.036859
B94: CAT A Works | G94: =C94*$B$68 -> 0 | H94: =D94*$B$68 -> 0 | I94: =E94*$B$68 -> 0
A95: Medium grade | B95: Furniture | C95: =D87 -> 731.03535 | E95: ='Local Consultant Advice1'!C19/Budget!AK10 -> 0 | G95: =C95*$B$68 -> 30.48 | H95: =D95*$B$68 -> 0 | I95: =E95*$B$68 -> 0
A96: Medium to high grade | B96: AV & Equipment | C96: =D86 -> 487.3569 | E96: ='Local Consultant Advice1'!M45*1.1 -> 0 | G96: =C96*$B$68 -> 20.32 | H96: =D96*$B$68 -> 0 | I96: =E96*$B$68 -> 0
C97: =SUM(C92:C96) -> 3200.6682 | E97: =SUM(E92:E96) -> 1176.1049 | G97: =SUM(G92:G96) -> 114.13503 | H97: =SUM(H92:H96) -> 0 | I97: =SUM(I92:I96) -> 49.036859
N99: 24 | O99: £
B100: Moves per H/C | D100: =G100/$B$68 -> 3597.6149 | G100: 150 | N100: =N99*1.18 -> 28.32 | O100: USD
N101: =N100/B67 -> 26.971429 | O101: EUR
B103: LL Contribution | C103: =200*$B$67 -> 210 | D103: PER SQ/M
C104: =C103/B68 -> 5036.6609 | D104: PER SQ/M
C107: =C103/B72 -> 19.509657 | D107: PER SQ FT
C108: =C104/B72 -> 467.92156 | D108: PER SQ FT

Sheet Local Consultant Advice1
A1: Project:
A2: Marsh, s.r.o. | J2: Works dealt with by LL Contribution
B3: Offices Fit-out works
A4: Atrium Flora, Vinohradská 2828/151, 130 00 Praha 3
B5: Estimated office area | C5: =1216-14.8-0.13-22.9-1.5-1.47-15.8-11.6 -> 1147.8 | D5: sqm
B7: PRELIMINARY ROUGH COST ESTIMATE
A8: No. | B8: Description | C8: Comments | D8: Unit | E8: Quantity | F8: Material & Work
A9: K/P | C9: Dopl. popis | E9: Výměra | F9: Unit price CZK | G9: Total price CZK | H9: Total price EUR
A10: 1 | B10: EXCHANGE OF SUSPENDED MINERAL CEILING | G10: =SUBTOTAL(9,G11:G19) -> 2527530 | H10: =G10/$B$85 -> 100458.27
A11: =ROW(A11)-ROW($A$10) -> 1 | B11: Dismantling of suspended mineral ceiling /incl. grid/ | D11: sqm | E11: =C5-210-60 -> 877.8 | F11: 350 | G11: =ROUND(E11*F11,0) -> 307230 | H11: =G11/$B$85 -> 12211.049
A12: =ROW(A12)-ROW($A$10) -> 2 | B12: Suspended mineral ceiling /incl. grid/ | D12: sqm | E12: =E11 -> 877.8 | F12: 2000 | G12: =ROUND(E12*F12,0) -> 1755600 | H12: =G12/$B$85 -> 69777.424
A13: =ROW(A13)-ROW($A$10) -> 3 | B13: Shift of existing detectors | D13: pcs | E13: 34 | F13: 1500 | G13: =ROUND(F13*E13,0) -> 51000 | H13: =G13/$B$85 -> 2027.027
A14: =ROW(A14)-ROW($A$10) -> 4 | B14: Inspection & protocols | D14: set | E14: 1 | F14: 10000 | G14: =ROUND(F14*E14,0) -> 10000 | H14: =G14/$B$85 -> 397.45628
A15: =ROW(A15)-ROW($A$10) -> 5 | B15: Removal of sprinkler head | D15: pcs | E15: 116 | F15: 500 | G15: =ROUND(F15*E15,0) -> 58000 | H15: =G15/$B$85 -> 2305.2464
A16: =ROW(A16)-ROW($A$10) -> 6 | B16: Sprinkler head | D16: pcs | E16: =E15 -> 116 | F16: 2700 | G16: =ROUND(F16*E16,0) -> 313200 | H16: =G16/$B$85 -> 12448.331
A17: =ROW(A17)-ROW($A$10) -> 7 | B17: Installation works & other material | D17: set | E17: 1 | F17: 15000 | G17: =ROUND(F17*E17,0) -> 15000 | H17: =G17/$B$85 -> 596.18442
A18: =ROW(A18)-ROW($A$10) -> 8 | B18: Draining & filling of system | D18: set | E18: 1 | F18: 7500 | G18: =ROUND(F18*E18,0) -> 7500 | H18: =G18/$B$85 -> 298.09221
A19: =ROW(A19)-ROW($A$10) -> 9 | B19: Pressure test & system set-up | D19: set | E19: 1 | F19: 10000 | G19: =F19*E19 -> 10000 | H19: =G19/$B$85 -> 397.45628
A21: 2 | B21: EXCHANGE OF LIGHTS | G21: =SUBTOTAL(9,G22:G27) -> 1479700 | H21: =G21/$B$85 -> 58811.606
A22: =ROW(A22)-ROW($A$21) -> 1 | B22: Removal of existing lights | D22: pcs | E22: =E23+E24 -> 343 | F22: 400 | G22: =ROUND(E22*F22,0) -> 137200 | H22: =G22/$B$85 -> 5453.1002
A23: =ROW(A23)-ROW($A$21) -> 2 | B23: New module lights | D23: pcs | E23: 169 | F23: 3500 | G23: =ROUND(E23*F23,0) -> 591500 | H23: =G23/$B$85 -> 23509.539
A24: =ROW(A24)-ROW($A$21) -> 3 | B24: New downlights | D24: pcs | E24: 174 | F24: 4000 | G24: =ROUND(E24*F24,0) -> 696000 | H24: =G24/$B$85 -> 27662.957
A25: =ROW(A25)-ROW($A$21) -> 4 | B25: Installation works & other material | D25: set | E25: 1 | F25: 20000 | G25: =ROUND(E25*F25,0) -> 20000 | H25: =G25/$B$85 -> 794.91256
A26: =ROW(A26)-ROW($A$21) -> 5 | B26: Lighting measurement | D26: set | E26: 1 | F26: 15000 | G26: =ROUND(E26*F26,0) -> 15000 | H26: =G26/$B$85 -> 596.18442
A27: =ROW(A27)-ROW($A$21) -> 6 | B27: Inspection & protocols | D27: set | E27: 1 | F27: 20000 | G27: =ROUND(E27*F27,0) -> 20000 | H27: =G27/$B$85 -> 794.91256
A29: 3 | B29: EXCHANGE OF CARPET, PAINTING | G29: =SUBTOTAL(9,G30:G35) -> 1422199 | H29: =G29/$B$85 -> 56526.192
A30: =ROW(A30)-ROW($A$29) -> 1 | B30: Flooring removal incl. Disposal | D30: sqm | E30: =C5-162-22-19 -> 944.8 | F30: 100 | G30: =ROUND(E30*F30,0) -> 94480 | H30: =G30/$B$85 -> 3755.1669
A31: =ROW(A31)-ROW($A$29) -> 2 | B31: Mechanical cleaning of suspended double floor after carpet removal | D31: sqm | E31: =E30 -> 944.8 | F31: 80 | G31: =ROUND(E31*F31,0) -> 75584 | H31: =G31/$B$85 -> 3004.1335
A32: =ROW(A32)-ROW($A$29) -> 3 | B32: Carpet - material only | D32: sqm | E32: =CEILING(1.1*E33,5) -> 1040 | F32: 800 | G32: =ROUND(E32*F32,0) -> 832000 | H32: =G32/$B$85 -> 33068.362
A33: =ROW(A33)-ROW($A$29) -> 4 | B33: Carpet - mounting /incl. skirting & laying/ | D33: sqm | E33: =E30 -> 944.8 | F33: 200 | G33: =ROUND(E33*F33,0) -> 188960 | H33: =G33/$B$85 -> 7510.3339
A34: =ROW(A34)-ROW($A$29) -> 5 | B34: Skirting, expansion strips, transitions bars | D34: set | E34: 1 | F34: =ROUND(100*C5,-2) -> 114800 | G34: =ROUND(E34*F34,0) -> 114800 | H34: =G34/$B$85 -> 4562.7981
A35: =ROW(A35)-ROW($A$29) -> 6 | B35: Painting - white colour | D35: sqm | E35: =350*3.5 -> 1225 | F35: 95 | G35: =ROUND(E35*F35,0) -> 116375 | H35: =G35/$B$85 -> 4625.3975
A37: 4 | B37: TOILET REFURBISHMENT | G37: =SUBTOTAL(9,G38:G61) -> 1572098 | H37: =G37/$B$85 -> 62484.022
A38: =ROW(A38)-ROW($A$37) -> 1 | B38: Dismantling of suspended plasterboard ceiling /incl. grid/ | D38: sqm | E38: =15.5+14.1+13.7 -> 43.3 | F38: 230 | G38: =ROUND(E38*F38,0) -> 9959 | H38: =G38/$B$85 -> 395.82671
A39: =ROW(A39)-ROW($A$37) -> 2 | B39: Removal of doors incl. frames | D39: pcs | E39: =5+4 -> 9 | F39: 1000 | G39: =ROUND(E39*F39,0) -> 9000 | H39: =G39/$B$85 -> 357.71065
A40: =ROW(A40)-ROW($A$37) -> 3 | B40: Removal of sanitary installations | D40: pcs | E40: =22 -> 22 | F40: 500 | G40: =ROUND(E40*F40,0) -> 11000 | H40: =G40/$B$85 -> 437.20191
A41: =ROW(A41)-ROW($A$37) -> 4 | B41: Removal of floor tiles | D41: sqm | E41: =E38 -> 43.3 | F41: 150 | G41: =ROUND(E41*F41,0) -> 6495 | H41: =G41/$B$85 -> 258.14785
A42: =ROW(A42)-ROW($A$37) -> 5 | B42: Removal of wall tiles | D42: sqm | E42: =2.5*(11+3.5*4+1.6*4+4.4+5.7+12+8+6.3) -> 169.5 | F42: 250 | G42: =ROUND(E42*F42,0) -> 42375 | H42: =G42/$B$85 -> 1684.221
A43: =ROW(A43)-ROW($A$37) -> 6 | B43: Interior doors 800/2100 /incl. steel frames, painting, door hardware/ | D43: pcs | E43: =E39 -> 9 | F43: 20000 | G43: =ROUND(E43*F43,0) -> 180000 | H43: =G43/$B$85 -> 7154.213
A44: =ROW(A44)-ROW($A$37) -> 7 | B44: Suspended plasterboard ceiling /incl. grid/ | D44: sqm | E44: =E38 -> 43.3 | F44: 1100 | G44: =ROUND(E44*F44,0) -> 47630 | H44: =G44/$B$85 -> 1893.0843
A45: =ROW(A45)-ROW($A$37) -> 8 | B45: Repair of existing plasterboard partitions | D45: sqm | E45: =E42 -> 169.5 | F45: 600 | G45: =ROUND(E45*F45,0) -> 101700 | H45: =G45/$B$85 -> 4042.1304
A46: =ROW(A46)-ROW($A$37) -> 9 | B46: Wall ceramic tiles cladding /incl. material/ | D46: sqm | E46: =E45 -> 169.5 | F46: 1900 | G46: =ROUND(E46*F46,0) -> 322050 | H46: =G46/$B$85 -> 12800.079
A47: =ROW(A47)-ROW($A$37) -> 10 | B47: Water insulation | D47: sqm | E47: =E41 -> 43.3 | F47: 650 | G47: =ROUND(E47*F47,0) -> 28145 | H47: =G47/$B$85 -> 1118.6407
A48: =ROW(A48)-ROW($A$37) -> 11 | B48: Floor ceramic tiles - material only | D48: sqm | E48: =1.1*E49 -> 47.63 | F48: 800 | G48: =ROUND(E48*F48,0) -> 38104 | H48: =G48/$B$85 -> 1514.4674
A49: =ROW(A49)-ROW($A$37) -> 12 | B49: Floor ceramic tiles cladding /incl. skirting & laying/ | D49: sqm | E49: =E47 -> 43.3 | F49: 800 | G49: =ROUND(E49*F49,0) -> 34640 | H49: =G49/$B$85 -> 1376.7886
A50: =ROW(A50)-ROW($A$37) -> 13 | B50: Toilet /incl. all components & installation/ | D50: pcs | E50: 9 | F50: 20000 | G50: =ROUND(E50*F50,0) -> 180000 | H50: =G50/$B$85 -> 7154.213
A51: =ROW(A51)-ROW($A$37) -> 14 | B51: Wash basin /incl. all components & installation/ | D51: pcs | E51: 9 | F51: 15000 | G51: =ROUND(E51*F51,0) -> 135000 | H51: =G51/$B$85 -> 5365.6598
A52: =ROW(A52)-ROW($A$37) -> 15 | B52: Urinal /incl. all components & installation/ | D52: pcs | E52: 3 | F52: 12000 | G52: =ROUND(E52*F52,0) -> 36000 | H52: =G52/$B$85 -> 1430.8426
A53: =ROW(A53)-ROW($A$37) -> 16 | B53: Mirror | D53: pcs | E53: 5 | F53: 5000 | G53: =ROUND(E53*F53,0) -> 25000 | H53: =G53/$B$85 -> 993.6407
A54: =ROW(A54)-ROW($A$37) -> 17 | B54: Sink /incl. all components & installation/ | D54: pcs | E54: 1 | F54: 10000 | G54: =ROUND(E54*F54,0) -> 10000 | H54: =G54/$B$85 -> 397.45628
A55: =ROW(A55)-ROW($A$37) -> 18 | B55: Electrical water heater /incl. fixing/ | D55: pcs | E55: 5 | F55: 10000 | G55: =ROUND(E55*F55,0) -> 50000 | H55: =G55/$B$85 -> 1987.2814
A56: =ROW(A56)-ROW($A$37) -> 19 | B56: Other equipment /bins, towel & soap holders, brushes,…/ | D56: set | E56: 5 | F56: 15000 | G56: =ROUND(E56*F56,0) -> 75000 | H56: =G56/$B$85 -> 2980.9221
A57: =ROW(A57)-ROW($A$37) -> 20 | B57: Adjustment of water outlets and drainage inlets | D57: set | E57: =E40 -> 22 | F57: 2500 | G57: =ROUND(E57*F57,0) -> 55000 | H57: =G57/$B$85 -> 2186.0095
A58: =ROW(A58)-ROW($A$37) -> 21 | B58: Pressure test of piping | D58: set | E58: =3 -> 3 | F58: 5000 | G58: =ROUND(E58*F58,0) -> 15000 | H58: =G58/$B$85 -> 596.18442
A59: =ROW(A59)-ROW($A$37) -> 22 | B59: Aditional construction works | D59: set | E59: 1 | F59: 25000 | G59: =ROUND(E59*F59,0) -> 25000 | H59: =G59/$B$85 -> 993.6407
A60: =ROW(A60)-ROW($A$37) -> 23 | B60: Adjustment of electrical installations | D60: set | E60: =3 -> 3 | F60: 20000 | G60: =ROUND(E60*F60,0) -> 60000 | H60: =G60/$B$85 -> 2384.7377
A61: =ROW(A61)-ROW($A$37) -> 24 | B61: Adjustment of ventilation | D61: set | E61: 3 | F61: 25000 | G61: =ROUND(E61*F61,0) -> 75000 | H61: =G61/$B$85 -> 2980.9221
A63: 5 | B63: REPAIRS OF ACOUSTIC ISOLATION | G63: =SUBTOTAL(9,G64:G66) -> 262000 | H63: =G63/$B$85 -> 10413.355
A64: =ROW(A64)-ROW($A$63) -> 1 | B64: Replacement of seals in glass partitions | D64: set | E64: 1 | F64: 50000 | G64: =ROUND(E64*F64,0) -> 50000 | H64: =G64/$B$85 -> 1987.2814
A65: =ROW(A65)-ROW($A$63) -> 2 | B65: Addition of acoustic insulation above and below the partitions | D65: m | E65: 60 | F65: 1200 | G65: =ROUND(E65*F65,0) -> 72000 | H65: =G65/$B$85 -> 2861.6852
A66: =ROW(A66)-ROW($A$63) -> 3 | B66: Acoustic panels in openspace | D66: pcs | E66: 20 | F66: 7000 | G66: =ROUND(E66*F66,0) -> 140000 | H66: =G66/$B$85 -> 5564.3879
A68: 6 | B68: OTHER | G68: =SUBTOTAL(9,G69:G71) -> 195126 | H68: =G68/$B$85 -> 7755.4054
A69: =ROW(A69)-ROW($A$68) -> 1 | B69: Protecting of existing structure while painting | D69: sqm | E69: =$C$5 -> 1147.8 | F69: 20 | G69: =ROUND(F69*E69,0) -> 22956 | H69: =G69/$B$85 -> 912.40064
A70: =ROW(A70)-ROW($A$68) -> 2 | B70: Regular cleaning | D70: sqm | E70: =$C$5 -> 1147.8 | F70: 60 | G70: =ROUND(F70*E70,0) -> 68868 | H70: =G70/$B$85 -> 2737.2019
A71: =ROW(A71)-ROW($A$68) -> 3 | B71: Final cleaning | D71: sqm | E71: =$C$5 -> 1147.8 | F71: 90 | G71: =ROUND(F71*E71,0) -> 103302 | H71: =G71/$B$85 -> 4105.8029
A73: 7 | B73: SOFT COST | G73: =SUBTOTAL(9,G74) -> 522106 | H73: =G73/$B$85 -> 20751.431
A74: =ROW(A74)-ROW($A$73) -> 1 | B74: Soft cost - site equipment | D74: set | E74: 0.07 | F74: =SUBTOTAL(9,G10:G71) -> 7458653 | G74: =ROUND(F74*E74,0) -> 522106 | H74: =G74/$B$85 -> 20751.431
A76: 8 | B76: CONTINGENCY | G76: =SUBTOTAL(9,G77) -> 798080 | H76: =G76/$B$85 -> 31720.191
A77: 1. | B77: Various unforeseen works | D77: set | E77: 0.1 | F77: =CEILING(SUBTOTAL(9,G10:G75),100) -> 7980800 | G77: =ROUND(E77*F77,-1) -> 798080 | H77: =G77/$B$85 -> 31720.191
B79: TOTAL CONSTRUCTION COST - CZK /VAT excluded/ | F79: Kč | G79: =SUBTOTAL(9,G10:G77) -> 8778839
B80: TOTAL CONSTRUCTION COST - € /VAT excluded/ | F80: € | G80: =G79/$B$85 -> 348920.47
B81: TOTAL CONSTRUCTION COST PER SQM - € /VAT excluded/ | F81: € / m2 | G81: =G80/($C$5) -> 303.99065
A83: Uvažovaný kurz: | F83: Datum:
A84: Exchange rate: | F84: Date:
A85: 1€ = | B85: 25.16 | F85: 45525
B87: Notes:
A88: 1. | B88: This is a rough estimation only, based on spaceplan. The detailed offer based on project documantation has to be elaborated.
A89: 2. | B89: The estimate reflects current market prices as of the date above and does not include inflation.
A90: 3. | B90: Estimate does not include design drawings and project management.
A91: 4. | B91: Estimate does not include moving, furniture, audio-video equipment, IT equipment and cabling, branding and other design features
A92: 5. | B92: Electronical security system is not included in the estimate
A93: 6. | B93: The estimate considers that the replacement of the suspended ceiling will take place at the same time as the replacement of the lighting fixtures and with the maintenance of the existing dimensions of the cassettes, if the lighting fixtures remain, the replacement of the suspended ceiling may be more expensive.
A94: 7. | B94: The estimate considers the replacement of light fixtures while keeping the same size, estimate does not consider modifying the ceiling due different dimensions of the light fixtures.

Sheet Local consultant Advice 2
A1: Project:
A2: Marsh, s.r.o. | J2: Works dealt with by MMC Budget
B3: Offices Fit-out works
A4: Atrium Flora, Vinohradská 2828/151, 130 00 Praha 3
B5: Estimated office area | C5: =1216-14.8-0.13-22.9-1.5-1.47-15.8-11.6 -> 1147.8 | D5: sqm
B7: PRELIMINARY ROUGH COST ESTIMATE
A8: No. | B8: Description | C8: Comments | D8: Unit | E8: Quantity | F8: Material & Work
A9: K/P | C9: Dopl. popis | E9: Výměra | F9: Unit price CZK | G9: Total price CZK | H9: Total price EUR
A10: 1 | B10: SHOWER REFURBISHMENT | G10: =SUBTOTAL(9,G11:G28) -> 164932 | H10: =G10/$B$58 -> 6555.3259
A11: =ROW(A11)-ROW($A$10) -> 1 | B11: Dismantling of suspended plasterboard ceiling /incl. grid/ | D11: sqm | E11: 3.2 | F11: 230 | G11: =ROUND(E11*F11,0) -> 736 | H11: =G11/$B$58 -> 29.252782
A12: =ROW(A12)-ROW($A$10) -> 2 | B12: Removal of doors incl. frames | D12: pcs | E12: 1 | F12: 1000 | G12: =ROUND(E12*F12,0) -> 1000 | H12: =G12/$B$58 -> 39.745628
A13: =ROW(A13)-ROW($A$10) -> 3 | B13: Removal of sanitary installations | D13: pcs | E13: 1 | F13: 500 | G13: =ROUND(E13*F13,0) -> 500 | H13: =G13/$B$58 -> 19.872814
A14: =ROW(A14)-ROW($A$10) -> 4 | B14: Removal of floor tiles | D14: sqm | E14: =E11 -> 3.2 | F14: 150 | G14: =ROUND(E14*F14,0) -> 480 | H14: =G14/$B$58 -> 19.077901
A15: =ROW(A15)-ROW($A$10) -> 5 | B15: Removal of wall tiles | D15: sqm | E15: =6.2*2.5 -> 15.5 | F15: 250 | G15: =ROUND(E15*F15,0) -> 3875 | H15: =G15/$B$58 -> 154.01431
A16: =ROW(A16)-ROW($A$10) -> 6 | B16: Interior doors 800/2100 /incl. steel frames, painting, door hardware/ | D16: pcs | E16: =E12 -> 1 | F16: 20000 | G16: =ROUND(E16*F16,0) -> 20000 | H16: =G16/$B$58 -> 794.91256
A17: =ROW(A17)-ROW($A$10) -> 7 | B17: Suspended plasterboard ceiling /incl. grid/ | D17: sqm | E17: =E11 -> 3.2 | F17: 1100 | G17: =ROUND(E17*F17,0) -> 3520 | H17: =G17/$B$58 -> 139.90461
A18: =ROW(A18)-ROW($A$10) -> 8 | B18: Repair of existing plasterboard partitions | D18: sqm | E18: =E15 -> 15.5 | F18: 600 | G18: =ROUND(E18*F18,0) -> 9300 | H18: =G18/$B$58 -> 369.63434
A19: =ROW(A19)-ROW($A$10) -> 9 | B19: Wall ceramic tiles cladding /incl. material/ | D19: sqm | E19: =E18 -> 15.5 | F19: 1900 | G19: =ROUND(E19*F19,0) -> 29450 | H19: =G19/$B$58 -> 1170.5087
A20: =ROW(A20)-ROW($A$10) -> 10 | B20: Water insulation | D20: sqm | E20: =E14+E15 -> 18.7 | F20: 650 | G20: =ROUND(E20*F20,0) -> 12155 | H20: =G20/$B$58 -> 483.10811
A21: =ROW(A21)-ROW($A$10) -> 11 | B21: Floor ceramic tiles - material only | D21: sqm | E21: =1.1*E22 -> 20.57 | F21: 800 | G21: =ROUND(E21*F21,0) -> 16456 | H21: =G21/$B$58 -> 654.05405
A22: =ROW(A22)-ROW($A$10) -> 12 | B22: Floor ceramic tiles cladding /incl. skirting & laying/ | D22: sqm | E22: =E20 -> 18.7 | F22: 800 | G22: =ROUND(E22*F22,0) -> 14960 | H22: =G22/$B$58 -> 594.59459
A23: =ROW(A23)-ROW($A$10) -> 13 | B23: Shower corner /800x800 mm, incl. water mixer tap/ | D23: pcs | E23: 1 | F23: 30000 | G23: =ROUND(E23*F23,0) -> 30000 | H23: =G23/$B$58 -> 1192.3688
A24: =ROW(A24)-ROW($A$10) -> 14 | B24: Adjustment of water outlets and drainage inlets | D24: set | E24: =E13 -> 1 | F24: 2500 | G24: =ROUND(E24*F24,0) -> 2500 | H24: =G24/$B$58 -> 99.36407
A25: =ROW(A25)-ROW($A$10) -> 15 | B25: Pressure test of piping | D25: set | E25: 1 | F25: 5000 | G25: =ROUND(E25*F25,0) -> 5000 | H25: =G25/$B$58 -> 198.72814
A26: =ROW(A26)-ROW($A$10) -> 16 | B26: Aditional construction works | D26: set | E26: 1 | F26: 5000 | G26: =ROUND(E26*F26,0) -> 5000 | H26: =G26/$B$58 -> 198.72814
A27: =ROW(A27)-ROW($A$10) -> 17 | B27: Adjustment of electrical installations | D27: set | E27: 1 | F27: 5000 | G27: =ROUND(E27*F27,0) -> 5000 | H27: =G27/$B$58 -> 198.72814
A28: =ROW(A28)-ROW($A$10) -> 18 | B28: Adjustment of ventilation | D28: set | E28: 1 | F28: 5000 | G28: =ROUND(E28*F28,0) -> 5000 | H28: =G28/$B$58 -> 198.72814
A30: 2 | B30: BLINDS | G30: =SUBTOTAL(9,G31:G33) -> 259600 | H30: =G30/$B$58 -> 10317.965
A31: =ROW(A31)-ROW($A$30) -> 1 | B31: Repairs of blinds | D31: sqm | E31: =2*(27+59+18+8) -> 224 | F31: 800 | G31: =ROUND(E31*F31,0) -> 179200 | H31: =G31/$B$58 -> 7122.4165
A32: =ROW(A32)-ROW($A$30) -> 2 | B32: Electrical blinds in meeting rooms | D32: sqm | E32: =14*2 -> 28 | F32: 1800 | G32: =ROUND(E32*F32,0) -> 50400 | H32: =G32/$B$58 -> 2003.1797
A33: =ROW(A33)-ROW($A$30) -> 3 | B33: Controls and motors for electrical blinds | D33: pcs | E33: 3 | F33: 10000 | G33: =ROUND(E33*F33,0) -> 30000 | H33: =G33/$B$58 -> 1192.3688
A35: 3 | B35: REST AREA - ROUGH ESTIMATE | G35: =SUBTOTAL(9,G36:G36) -> 1000000 | H35: =G35/$B$58 -> 39745.628
A36: 1. | B36: Rest area - need more specification | D36: set | E36: 1 | F36: 1000000 | G36: =ROUND(E36*F36,0) -> 1000000 | H36: =G36/$B$58 -> 39745.628
A38: 4 | B38: PHONEBOOTHS | G38: =SUBTOTAL(9,G39) -> 1200000 | H38: =G38/$B$58 -> 47694.754
A39: =ROW(A39)-ROW(A38) -> 1 | B39: Phonebooths | D39: pcs | E39: 6 | F39: 200000 | G39: =ROUND(F39*E39,0) -> 1200000 | H39: =G39/$B$58 -> 47694.754
A41: 5 | B41: OTHER | G41: =SUBTOTAL(9,G42:G44) -> 195126 | H41: =G41/$B$58 -> 7755.4054
A42: =ROW(A42)-ROW($A$41) -> 1 | B42: Protecting of existing structure while painting | D42: sqm | E42: =$C$5 -> 1147.8 | F42: 20 | G42: =ROUND(F42*E42,0) -> 22956 | H42: =G42/$B$58 -> 912.40064
A43: =ROW(A43)-ROW($A$41) -> 2 | B43: Regular cleaning | D43: sqm | E43: =$C$5 -> 1147.8 | F43: 60 | G43: =ROUND(F43*E43,0) -> 68868 | H43: =G43/$B$58 -> 2737.2019
A44: =ROW(A44)-ROW($A$41) -> 3 | B44: Final cleaning | D44: sqm | E44: =$C$5 -> 1147.8 | F44: 90 | G44: =ROUND(F44*E44,0) -> 103302 | H44: =G44/$B$58 -> 4105.8029
A46: 6 | B46: SOFT COST | G46: =SUBTOTAL(9,G47) -> 197376 | H46: =G46/$B$58 -> 7844.8331
A47: =ROW(A47)-ROW($A$46) -> 1 | B47: Soft cost - site equipment | D47: set | E47: 0.07 | F47: =SUBTOTAL(9,G10:G44) -> 2819658 | G47: =ROUND(F47*E47,0) -> 197376 | H47: =G47/$B$58 -> 7844.8331
A49: 7 | B49: CONTINGENCY | G49: =SUBTOTAL(9,G50) -> 301710 | H49: =G49/$B$58 -> 11991.653
A50: 1. | B50: Various unforeseen works | D50: set | E50: 0.1 | F50: =CEILING(SUBTOTAL(9,G10:G48),100) -> 3017100 | G50: =ROUND(E50*F50,-1) -> 301710 | H50: =G50/$B$58 -> 11991.653
B52: TOTAL CONSTRUCTION COST - CZK /VAT excluded/ | F52: Kč | G52: =SUBTOTAL(9,G10:G50) -> 3318744
B53: TOTAL CONSTRUCTION COST - € /VAT excluded/ | F53: € | G53: =G52/$B$58 -> 131905.56
B54: TOTAL CONSTRUCTION COST PER SQM - € /VAT excluded/ | F54: € / m2 | G54: =G53/($C$5) -> 114.92034
A56: Uvažovaný kurz: | F56: Datum:
A57: Exchange rate: | F57: Date:
A58: 1€ = | B58: 25.16 | F58: 45525
B60: Notes:
A61: 1. | B61: This is a rough estimation only, based on spaceplan. The detailed offer based on project documantation has to be elaborated.
A62: 2. | B62: The estimate reflects current market prices as of the date above and does not include inflation.
A63: 3. | B63: Estimate does not include design drawings and project management.
A64: 4. | B64: Estimate does not include moving, furniture, audio-video equipment, IT equipment and cabling, branding and other design features
A65: 5. | B65: Electronical security system is not included in the estimate
A66: 6. | B66: The estimate considers that the replacement of the suspended ceiling will take place at the same time as the replacement of the lighting fixtures and with the maintenance of the existing dimensions of the cassettes, if the lighting fixtures remain, the replacement of the suspended ceiling may be more expensive.
A67: 7. | B67: The estimate considers the replacement of light fixtures while keeping the same size, estimate does not consider modifying the ceiling due different dimensions of the light fixtures.

Sheet 2025 FX Rates
A2: MARSH MCLENNAN
A3: FOREIGN EXCHANGE RATE SUMMARY REPORT
A4: 2025 BUDGET
D6: 1st Pass* | F6: 2nd Pass | H6: Variance
C7: CURR | D7: BUDGET | F7: BUDGET | H7: 2nd Pass vs 1st Pass
A8: COUNTRY | B8: CURRENCY | C8: CODE | D8: RATE | F8: RATE | H8: $ | I8: %
A9: ALBANIA | B9: LEK | C9: ALL | D9: 0.01053408 | F9: 0.010755 | H9: =(F9-D9) -> 0.00022092 | I9: =H9/D9 -> 0.020971931
A10: ALGERIA | B10: DINAR | C10: DZD | D10: 0.00746088 | F10: 0.0075002 | H10: =(F10-D10) -> 3.932e-05 | I10: =H10/D10 -> 0.0052701558
A11: ANGOLA | B11: KWANZA | C11: AOA | D11: 0.00119768 | F11: 0.00108685 | H11: =(F11-D11) -> -0.00011083 | I11: =H11/D11 -> -0.092537239
A12: ARGENTINA | B12: PESO | C12: ARS | D12: 0.00071429 | F12: 0.00071429 | H12: =(F12-D12) -> 0 | I12: =H12/D12 -> 0
A13: ARUBA | B13: FLORIN | C13: AWG | D13: 0.55865922 | F13: 0.55865922 | H13: =(F13-D13) -> 0 | I13: =H13/D13 -> 0
A14: AUSTRALIA | B14: DOLLAR | C14: AUD | D14: 0.66 | F14: 0.65 | H14: =(F14-D14) -> -0.01 | I14: =H14/D14 -> -0.015151515
A15: AZERBAIJAN | B15: AZERBAIJAN | C15: AZN | D15: 0.58899753 | F15: 0.58820069 | H15: =(F15-D15) -> -0.00079684 | I15: =H15/D15 -> -0.0013528749
A16: BAHAMAS | B16: DOLLAR | C16: BSD | D16: 1 | F16: 1 | H16: =(F16-D16) -> 0 | I16: =H16/D16 -> 0
A17: BAHRAIN | B17: DINAR | C17: BHD | D17: 2.6525902 | F17: 2.6528014 | H17: =(F17-D17) -> 0.00021111 | I17: =H17/D17 -> 7.9586359e-05
A18: BANGLADESH | B18: TAKA | C18: BDT | D18: 0.00904425 | F18: 0.0083649 | H18: =(F18-D18) -> -0.00067935 | I18: =H18/D18 -> -0.075114023
A19: BARBADOS | B19: DOLLAR | C19: BBD | D19: 0.5 | F19: 0.5 | H19: =(F19-D19) -> 0 | I19: =H19/D19 -> 0
A20: BELARUS | B20: RUBLE | C20: BYR | D20: 3.044e-05 | F20: 3.065e-05 | H20: =(F20-D20) -> 2.1e-07 | I20: =H20/D20 -> 0.0068988173
... A145: ZIMBABWE | B145: DOLLAR | C145: ZWL | D145: 0.00017233 | F145: 2.763e-05 | H145: =(F145-D145) -> -0.0001447 | I145: =H145/D145 -> -0.83966808
A147: *Based on 2024 Budget Rates
