Workbook

Sheet FITOUT
E1: FIT OUT $/M2 | O1: FIT OUT $/SQFT | Y1: LOCATION FACTOR
E2: Activity | H2: Team | K2: Event | O2: Activity | R2: Team | U2: Event | Y2: EMEA | Z2: AMERICA | AA2: APAC
E3: Low | F3: Medium | G3: High | H3: Low | I3: Medium | J3: High | K3: Low | L3: Medium | M3: High | O3: Low | P3: Medium | Q3: High | R3: Low | S3: Medium | T3: High | U3: Low | V3: Medium | W3: High | Y3: =O138 -> 145.42387 | Z3: =O25 -> 213.86534 | AA3: =O133 -> 122.9244
B4: COUNTRY | C4: CITY | D4: REGION
B5: United States | C5: Cincinnati | D5: AMERICAS | E5: 1812.7573 | F5: 2640.9279 | G5: 3159.8936 | H5: 1744.1546 | I5: 2478.8513 | J5: 2933.1367 | K5: 1826.7708 | L5: 2431.3083 | M5: 2969.2193 | O5: 168.4093 | P5: 245.34823 | Q5: 293.56133 | R5: 162.03595 | S5: 230.29095 | T5: 272.4951 | U5: 169.71118 | V5: 225.87409 | W5: 275.84725 | Z5: =O5/$Z$3 -> 0.78745484
B6: United States | C6: Charlotte | D6: AMERICAS | E6: 1693.3113 | F6: 2466.1542 | G6: 2950.4485 | H6: 1671.2387 | I6: 2376.9915 | J6: 2805.8961 | K6: 1972.5798 | L6: 2620.993 | M6: 3225.4336 | O6: 157.31249 | P6: 229.11135 | Q6: 274.10341 | R6: 155.26189 | S6: 220.82794 | T6: 260.67415 | U6: 183.25717 | V6: 243.49624 | W6: 299.65015 | Z6: =O6/$Z$3 -> 0.73556794
B7: United States | C7: Charleston | D7: AMERICAS | E7: 1693.3113 | F7: 2466.1542 | G7: 2950.4485 | H7: 1671.2387 | I7: 2376.9915 | J7: 2805.8961 | K7: 1972.5798 | L7: 2620.993 | M7: 3225.4336 | O7: 157.31249 | P7: 229.11135 | Q7: 274.10341 | R7: 155.26189 | S7: 220.82794 | T7: 260.67415 | U7: 183.25717 | V7: 243.49624 | W7: 299.65015 | Z7: =O7/$Z$3 -> 0.73556794
B8: United States | C8: Chicago | D8: AMERICAS | E8: 2218.4928 | F8: 3234.6057 | G8: 3871.3426 | H8: 2189.4729 | I8: 3117.3779 | J8: 3681.2884 | K8: 2585.6683 | L8: 3438.183 | M8: 4232.8861 | O8: 206.10305 | P8: 300.50225 | Q8: 359.65657 | R8: 203.40703 | S8: 289.61153 | T8: 342.0001 | U8: 240.21449 | V8: 319.41505 | W8: 393.24479 | Z8: =O8/$Z$3 -> 0.96370477
B9: United States | C9: Cleveland | D9: AMERICAS | E9: 1758.2914 | F9: 2556.5694 | G9: 3071.177 | H9: 1711.5122 | I9: 2430.6211 | J9: 2880.7703 | K9: 1940.2859 | L9: 2568.7384 | M9: 3179.7703 | O9: 163.34929 | P9: 237.51113 | Q9: 285.31936 | R9: 159.00339 | S9: 225.81025 | T9: 267.63014 | U9: 180.25699 | V9: 238.64167 | W9: 295.40792 | Z9: =O9/$Z$3 -> 0.76379505
B10: United States | C10: Boston | D10: AMERICAS | E10: 2159.7181 | F10: 3148.6057 | G10: 3768.2819 | H10: 2131.4759 | I10: 3034.5182 | J10: 3583.3207 | K10: 2506.1422 | L10: 3309.3118 | M10: 4058.2223 | O10: 200.64274 | P10: 292.51266 | Q10: 350.082 | R10: 198.01898 | S10: 281.91367 | T10: 332.89868 | U10: 232.82634 | V10: 307.44262 | W10: 377.01812 | Z10: =O10/$Z$3 -> 0.93817325
B11: United States | C11: Baltimore | D11: AMERICAS | E11: 1765.812 | F11: 2572.7882 | G11: 3092.4575 | H11: 1745.5316 | I11: 2479.1447 | J11: 2938.3734 | K11: 2151.8588 | L11: 2859.9547 | M11: 3520.0318 | O11: 164.04797 | P11: 239.0179 | Q11: 287.29636 | R11: 162.16387 | S11: 230.31821 | T11: 272.9816 | U11: 199.9126 | V11: 265.69633 | W11: 327.019 | Z11: =O11/$Z$3 -> 0.76706198
B12: United States | C12: Columbus | D12: AMERICAS | E12: 1717.8081 | F12: 2497.4426 | G12: 3000.0318 | H12: 1672.1208 | I12: 2374.4356 | J12: 2814.0716 | K12: 1895.552 | L12: 2509.3277 | M12: 3106.0885 | O12: 159.58829 | P12: 232.01812 | Q12: 278.70981 | R12: 155.34384 | S12: 220.59049 | T12: 261.43368 | U12: 176.10111 | V12: 233.12227 | W12: 288.56272 | Z12: =O12/$Z$3 -> 0.74620924
B13: United States | C13: Austin | D13: AMERICAS | E13: 1612.2665 | F13: 2322.8329 | G13: 2795.9229 | H13: 1649.271 | I13: 2341.8429 | J13: 2775.3809 | K13: 1784.6753 | L13: 2384.5977 | M13: 2928.0398 | O13: 149.78324 | P13: 215.79648 | Q13: 259.74763 | R13: 153.22104 | S13: 217.56255 | T13: 257.83922 | U13: 165.80041 | V13: 221.53457 | W13: 272.02158 | Z13: =O13/$Z$3 -> 0.70036241
B14: United States | C14: Atlanta | D14: AMERICAS | E14: 1701.2466 | F14: 2518.81 | G14: 3020.0353 | H14: 1412.2452 | I14: 2014.3615 | J14: 2391.2755 | K14: 1877.2511 | L14: 2485.0229 | M14: 3075.9458 | O14: 158.0497 | P14: 234.00321 | Q14: 280.56818 | R14: 131.2008 | S14: 187.13879 | T14: 222.15495 | U14: 174.40092 | V14: 230.8643 | W14: 285.76239 | Z14: =O14/$Z$3 -> 0.73901503
B15: United States | C15: Dallas | D15: AMERICAS | E15: 1620.2795 | F15: 2355 | G15: 2828.6365 | H15: 1577.2248 | I15: 2239.0796 | J15: 2653.3894 | K15: 1787.7837 | L15: 2366.2004 | M15: 2928.5833 | O15: 150.52766 | P15: 218.78488 | Q15: 262.78679 | R15: 146.52778 | S15: 208.01561 | T15: 246.50593 | U15: 166.08919 | V15: 219.82542 | W15: 272.07208 | Z15: =O15/$Z$3 -> 0.70384319
B16: United States | C16: Denver | D16: AMERICAS | E16: 1730.6892 | F16: 2516.2556 | G16: 3022.6688 | H16: 1684.6544 | I16: 2392.3128 | J16: 2835.2939 | K16: 1909.7852 | L16: 2528.2312 | M16: 3129.5326 | O16: 160.78498 | P16: 233.76589 | Q16: 280.81284 | R16: 156.50824 | S16: 222.25132 | T16: vh | U16: 177.42341 | V16: 234.87846 | W16: 290.74072 | Z16: =O16/$Z$3 -> 0.75180476
B17: United States | C17: Detroit | D17: AMERICAS | E17: 1817.177 | F17: 2642.5724 | G17: 3174.6614 | H17: 1768.8081 | I17: 2512.3456 | J17: 2977.7862 | K17: 2005.3531 | L17: 2655.1551 | M17: 3286.9428 | O17: 168.8199 | P17: 245.50101 | Q17: 294.93329 | R17: 164.32631 | S17: 233.40264 | T17: 276.64314 | U17: 186.30188 | V17: 246.66998 | W17: 305.36449 | Z17: =O17/$Z$3 -> 0.78937474
B18: United States | C18: Houston | D18: AMERICAS | E18: 1609.2392 | F18: 2338.8752 | G18: 2809.2327 | H18: 1566.4818 | I18: 2223.7563 | J18: 2635.1989 | K18: 1775.5838 | L18: 2349.9975 | M18: 2908.4883 | O18: 149.502 | P18: 217.28685 | Q18: 260.98414 | R18: 145.52974 | S18: 206.59204 | T18: 244.816 | U18: 164.95579 | V18: 218.32014 | W18: 270.20521 | Z18: =O18/$Z$3 -> 0.69904734
B19: United States | C19: Indianapolis | D19: AMERICAS | E19: 1710.4475 | F19: 2486.6922 | G19: 2987.0965 | H19: 1664.9592 | I19: 2364.2203 | J19: 2801.9448 | K19: 1887.4182 | L19: 2498.5256 | M19: 3092.6922 | O19: 158.90448 | P19: 231.01938 | Q19: 277.50808 | R19: 154.67851 | S19: 219.64146 | T19: 260.30707 | U19: 175.34546 | V19: 232.11874 | W19: 287.31817 | Z19: =O19/$Z$3 -> 0.74301186
B20: United States | C20: Kansas City | D20: AMERICAS | E20: 1796.9354 | F20: 2613.0085 | G20: 3139.089 | H20: 1749.1124 | I20: 2484.2521 | J20: 2944.4366 | K20: 1982.9861 | L20: 2625.4495 | M20: 3250.1024 | O20: 166.9394 | P20: 242.75445 | Q20: 291.62854 | R20: 162.49654 | S20: 230.7927 | T20: 273.54489 | U20: 184.22394 | V20: 243.91026 | W20: 301.94194 | Z20: =O20/$Z$3 -> 0.78058184
B21: United States | C21: Los Angeles | D21: AMERICAS | E21: 2120.8026 | F21: 3086.0234 | G21: 3708.2516 | H21: 2064.2402 | I21: 2933.7355 | J21: 3478.0249 | K21: 2340.8573 | L21: 3100.7379 | M21: 3839.554 | O21: 197.0274 | P21: 286.69862 | Q21: 344.50504 | R21: 191.77263 | S21: 272.55072 | T21: 323.11645 | U21: 217.47099 | V21: 288.06564 | W21: 356.70333 | Z21: =O21/$Z$3 -> 0.92126852
B22: United States | C22: Miami | D22: AMERICAS | E22: 1660.7633 | F22: 2414.1268 | G22: 2899.7817 | H22: 1616.6156 | I22: 2295.2645 | J22: 2720.0875 | K22: 1832.5177 | L22: 2425.6121 | M22: 3002.2645 | O22: 154.2887 | P22: 224.27789 | Q22: 269.39634 | R22: 150.18728 | S22: 213.23532 | T22: 252.70234 | U22: 170.24508 | V22: 225.34491 | W22: 278.91723 | Z22: =O22/$Z$3 -> 0.72142922
B23: United States | C23: Minneapolis | D23: AMERICAS | E23: 1951.5077 | F23: 2838.7658 | G23: 3410.735 | H23: 1899.5142 | I23: 2698.7782 | J23: 3199.1034 | K23: 2153.7882 | L23: 2852.2919 | M23: 3531.4316 | O23: 181.29952 | P23: 263.72783 | Q23: 316.86507 | R23: 176.46921 | S23: 250.72266 | T23: 297.20402 | U23: 200.09184 | V23: 264.98443 | W23: 328.07806 | Z23: =O23/$Z$3 -> 0.84772747
B24: United States | C24: Nashville | D24: AMERICAS | E24: 1655.2432 | F24: 2406.0641 | G24: 2890.0806 | H24: 1611.2447 | I24: 2287.6032 | J24: 2710.9925 | K24: 1826.4177 | L24: 2417.5107 | M24: 2992.2173 | O24: 153.77587 | P24: 223.52885 | Q24: 268.49508 | R24: 149.68831 | S24: 212.52356 | T24: 251.8574 | U24: 169.67838 | V24: 224.59226 | W24: 277.98382 | Z24: =O24/$Z$3 -> 0.71903129
B25: United States | C25: New York | D25: AMERICAS | E25: 2302.0461 | F25: 3357.5815 | G25: 4037.3144 | H25: 2275.5186 | I25: 3235.094 | J25: 3835.7708 | K25: 2619.6763 | L25: 3646.4286 | M25: 4441.179 | O25: 213.86534 | P25: 311.92699 | Q25: 375.07572 | R25: 211.40088 | S25: 300.54762 | T25: 356.35186 | U25: 243.37391 | V25: 338.76155 | W25: 412.59567 | Z25: =O25/$Z$3 -> 1
B26: United States | C26: Newark | D26: AMERICAS | E26: 2130.0035 | F26: 3099.462 | G26: 3724.4207 | H26: 2073.1924 | I26: 2946.5052 | J26: 3493.183 | K26: 2351.0239 | L26: 3114.2407 | M26: 3856.2999 | O26: 197.88219 | P26: 287.9471 | Q26: 346.00719 | R26: 192.60431 | S26: 273.73706 | T26: 324.52468 | U26: 218.41549 | V26: 289.32007 | W26: 358.25906 | Z26: =O26/$Z$3 -> 0.92526535
B27: United States | C27: Oakland | D27: AMERICAS | E27: 2210.9702 | F27: 3217.7156 | G27: 3866.7116 | H27: 2151.9741 | I27: 3058.8767 | J27: 3626.5798 | K27: 2440.4913 | L27: 3233.0627 | M27: 4003.6624 | O27: 205.40418 | P27: 298.93313 | Q27: 359.22634 | R27: 199.92331 | S27: 284.17663 | T27: 336.91755 | U27: 226.72722 | V27: 300.3589 | W27: 371.94938 | Z27: =O27/$Z$3 -> 0.96043697
B28: United States | C28: Orlando | D28: AMERICAS | E28: 1662.6032 | F28: 2416.815 | G28: 2903.0154 | H28: 1618.4068 | I28: 2297.819 | J28: 2723.1188 | K28: 1834.5505 | L28: 2428.3128 | M28: 3005.6136 | O28: 154.45963 | P28: 224.52764 | Q28: 269.69676 | R28: 150.35368 | S28: 213.47263 | T28: 252.98396 | U28: 170.43393 | V28: 225.5958 | W28: 279.22837 | Z28: =O28/$Z$3 -> 0.72222845
... B44: United States | C44: Tulsa | D44: AMERICAS | E44: 1571.9712 | F44: 2289.0962 | G44: 2750.9043 | H44: 1553.9483 | I44: 2205.8792 | J44: 2613.9766 | K44: 1795.7379 | L44: 2493.3093 | M44: 3033.2591 | O44: 146.03972 | P44: 212.66226 | Q44: 255.56529 | R44: 144.36534 | S44: 204.93121 | T44: 242.8444 | U44: 166.82816 | V44: 231.63413 | W44: 281.7967 | Z44: =O44/$Z$3 -> 0.68285828
B45: Saint Kitts and Nevis | C45: Basseterre | D45: AMERICAS | E45: =O45*10.764 -> 1540.2208 | F45: =P45*10.764 -> 2238.0509 | G45: =Q45*10.764 -> 2687.9861 | H45: =R45*10.764 -> 1499.3176 | I45: =S45*10.764 -> 2127.9352 | J45: =T45*10.764 -> 2521.467 | K45: =U45*10.764 -> 1699.3127 | L45: =V45*10.764 -> 2248.7072 | M45: =W45*10.764 -> 2782.8169 | O45: 143.09 | P45: 207.92 | Q45: 249.72 | R45: 139.29 | S45: 197.69 | T45: 234.25 | U45: 157.87 | V45: 208.91 | W45: 258.53 | Z45: =O45/$Z$3 -> 0.66906587
B46: Puerto Rico | C46: San Juan | D46: AMERICAS | E46: =O46*10.764 -> 1684.1354 | F46: =P46*10.764 -> 2448.2718 | G46: =Q46*10.764 -> 2940.9401 | H46: =R46*10.764 -> 1639.3572 | I46: =S46*10.764 -> 2327.715 | J46: =T46*10.764 -> 2758.5979 | K46: =U46*10.764 -> 1858.4046 | L46: =V46*10.764 -> 2460.0046 | M46: =W46*10.764 -> 3044.8127 | O46: 156.46 | P46: 227.45 | Q46: 273.22 | R46: 152.3 | S46: 216.25 | T46: 256.28 | U46: 172.65 | V46: 228.54 | W46: 282.87 | Z46: =O46/$Z$3 -> 0.73158185
B47: Barbados | C47: Bridgetown | D47: AMERICAS | E47: =O47*10.764 -> 1630.3154 | F47: =P47*10.764 -> 2369.6946 | G47: =Q47*10.764 -> 2846.3245 | H47: =R47*10.764 -> 1587.0442 | I47: =S47*10.764 -> 2253.0128 | J47: =T47*10.764 -> 2669.9026 | K47: =U47*10.764 -> 1798.8797 | L47: =V47*10.764 -> 2380.8892 | M47: =W47*10.764 -> 2946.8603 | O47: 151.46 | P47: 220.15 | Q47: 264.43 | R47: 147.44 | S47: 209.31 | T47: 248.04 | U47: 167.12 | V47: 221.19 | W47: 273.77 | Z47: =O47/$Z$3 -> 0.70820265
B48: Saint Lucia | C48: Castries | D48: AMERICAS | E48: =O48*10.764 -> 1630.3154 | F48: =P48*10.764 -> 2369.6946 | G48: =Q48*10.764 -> 2846.3245 | H48: =R48*10.764 -> 1587.0442 | I48: =S48*10.764 -> 2253.0128 | J48: =T48*10.764 -> 2669.9026 | K48: =U48*10.764 -> 1798.8797 | L48: =V48*10.764 -> 2380.8892 | M48: =W48*10.764 -> 2946.8603 | O48: 151.46 | P48: 220.15 | Q48: 264.43 | R48: 147.44 | S48: 209.31 | T48: 248.04 | U48: 167.12 | V48: 221.19 | W48: 273.77 | Z48: =O48/$Z$3 -> 0.70820265
B49: Turks & Caicos Islands | C49: Cockburn Town | D49: AMERICAS | E49: =O49*10.764 -> 2018.0347 | F49: =P49*10.764 -> 2935.881 | G49: =Q49*10.764 -> 3527.5781 | H49: =R49*10.764 -> 1964.2147 | I49: =S49*10.764 -> 2791.1052 | J49: =T49*10.764 -> 3308.6383 | K49: =U49*10.764 -> 2227.2869 | L49: =V49*10.764 -> 2949.8742 | M49: =W49*10.764 -> 3652.4405 | O49: 187.48 | P49: 272.75 | Q49: 327.72 | R49: 182.48 | S49: 259.3 | T49: 307.38 | U49: 206.92 | V49: 274.05 | W49: 339.32 | Z49: =O49/$Z$3 -> 0.87662639
B50: Cayman Islands | C50: George Town | D50: AMERICAS | E50: =O50*10.764 -> 2020.7257 | F50: =P50*10.764 -> 2939.9713 | G50: =Q50*10.764 -> 3532.4219 | H50: =R50*10.764 -> 1966.9057 | I50: =S50*10.764 -> 2794.8726 | J50: =T50*10.764 -> 3313.2668 | K50: =U50*10.764 -> 2230.3008 | L50: =V50*10.764 -> 2953.9645 | M50: =W50*10.764 -> 3657.4996 | O50: 187.73 | P50: 273.13 | Q50: 328.17 | R50: 182.73 | S50: 259.65 | T50: 307.81 | U50: 207.2 | V50: 274.43 | W50: 339.79 | Z50: =O50/$Z$3 -> 0.87779535
B51: Saint Vincent The Grenadines | C51: Kingstontown | D51: AMERICAS | E51: =O51*10.764 -> 1073.6014 | F51: =P51*10.764 -> 1556.4744 | G51: =Q51*10.764 -> 1867.8769 | H51: =R51*10.764 -> 1045.292 | I51: =S51*10.764 -> 1480.2653 | J51: =T51*10.764 -> 1752.7021 | K51: =U51*10.764 -> 1183.7171 | L51: =V51*10.764 -> 1563.9016 | M51: =W51*10.764 -> 1933.5373 | O51: 99.74 | P51: 144.6 | Q51: 173.53 | R51: 97.11 | S51: 137.52 | T51: 162.83 | U51: 109.97 | V51: 145.29 | W51: 179.63 | Z51: =O51/$Z$3 -> 0.46636823
B52: Bahamas | C52: Nassau | D52: AMERICAS | E52: =O52*10.764 -> 2028.1529 | F52: =P52*10.764 -> 2950.7353 | G52: =Q52*10.764 -> 3545.4463 | H52: =R52*10.764 -> 1974.1176 | I52: =S52*10.764 -> 2805.0984 | J52: =T52*10.764 -> 3325.3225 | K52: =U52*10.764 -> 2238.4814 | L52: =V52*10.764 -> 2964.7285 | M52: =W52*10.764 -> 3670.9546 | O52: 188.42 | P52: 274.13 | Q52: 329.38 | R52: 183.4 | S52: 260.6 | T52: 308.93 | U52: 207.96 | V52: 275.43 | W52: 341.04 | Z52: =O52/$Z$3 -> 0.88102168
B53: St. Maarten | C53: Philipsburg | D53: AMERICAS | E53: =O53*10.764 -> 1693.1772 | F53: =P53*10.764 -> 2461.5115 | G53: =Q53*10.764 -> 2956.7632 | H53: =R53*10.764 -> 1648.1837 | I53: =S53*10.764 -> 2340.3089 | J53: =T53*10.764 -> 2773.5599 | K53: =U53*10.764 -> 1868.3075 | L53: =V53*10.764 -> 2473.2443 | M53: =W53*10.764 -> 3061.2816 | O53: 157.3 | P53: 228.68 | Q53: 274.69 | R53: 153.12 | S53: 217.42 | T53: 257.67 | U53: 173.57 | V53: 229.77 | W53: 284.4 | Z53: =O53/$Z$3 -> 0.73550955
B54: Trinidad Tobago | C54: Port of Spain | D54: AMERICAS | E54: =O54*10.764 -> 1777.4593 | F54: =P54*10.764 -> 2584.544 | G54: =Q54*10.764 -> 3104.8758 | H54: =R54*10.764 -> 1730.2054 | I54: =S54*10.764 -> 2457.2059 | J54: =T54*10.764 -> 2912.4155 | K54: =U54*10.764 -> 1961.5237 | L54: =V54*10.764 -> 2596.9226 | M54: =W54*10.764 -> 3214.6686 | O54: 165.13 | P54: 240.11 | Q54: 288.45 | R54: 160.74 | S54: 228.28 | T54: 270.57 | U54: 182.23 | V54: 241.26 | W54: 298.65 | Z54: =O54/$Z$3 -> 0.77212138
B55: British Virgin Islands | C55: Road Town | D55: AMERICAS | E55: =O55*10.764 -> 1844.7343 | F55: =P55*10.764 -> 2682.8194 | G55: =Q55*10.764 -> 3223.0645 | H55: =R55*10.764 -> 1795.6505 | I55: =S55*10.764 -> 2550.6374 | J55: =T55*10.764 -> 3023.177 | K55: =U55*10.764 -> 2035.7953 | L55: =V55*10.764 -> 2695.6285 | M55: =W55*10.764 -> 3337.0553 | O55: 171.38 | P55: 249.24 | Q55: 299.43 | R55: 166.82 | S55: 236.96 | T55: 280.86 | U55: 189.13 | V55: 250.43 | W55: 310.02 | Z55: =O55/$Z$3 -> 0.80134537
B56: Argentina | C56: Buenos Aires | D56: AMERICAS | E56: =O56*10.764 -> 1455.1852 | F56: =P56*10.764 -> 2113.942 | G56: =Q56*10.764 -> 2538.5818 | H56: =R56*10.764 -> 1416.65 | I56: =S56*10.764 -> 2009.9617 | J56: =T56*10.764 -> 2381.4274 | K56: =U56*10.764 -> 1605.343 | L56: =V56*10.764 -> 2123.9525 | M56: =W56*10.764 -> 2628.1382 | O56: 135.19 | P56: 196.39 | Q56: 235.84 | R56: 131.61 | S56: 186.73 | T56: 221.24 | U56: 149.14 | V56: 197.32 | W56: 244.16 | Z56: =O56/$Z$3 -> 0.63212674
B57: Argentina | C57: Cordoba | D57: AMERICAS | E57: 1785.1518 | F57: 2432.3804 | G57: 3420.6234 | H57: 1653.1489 | I57: 2258.441 | J57: 2985.2048 | K57: 1982.6374 | L57: 2501.4945 | M57: 3265.944 | O57: 165.84468 | P57: 225.97369 | Q57: 317.78372 | R57: 153.58131 | S57: 209.81433 | T57: 277.33234 | U57: 184.19155 | V57: 232.39455 | W57: 303.41366 | Z57: =O57/$Z$3 -> 0.7754631
B58: Brazil | C58: Brasilia | D58: AMERICAS | E58: 1069.0142 | F58: 1456.5984 | G58: 2048.3945 | H58: 989.96611 | I58: 1352.4372 | J58: 1787.6499 | K58: 1187.2759 | L58: 1497.9865 | M58: 1955.7669 | O58: 99.313865 | P58: 135.32132 | Q58: 190.30053 | R58: 91.970112 | S58: 125.6445 | T58: 166.07676 | U58: 110.30064 | V58: 139.16637 | W58: 181.69521 | Z58: =O58/$Z$3 -> 0.46437569
B59: Brazil | C59: Rio De Janeiro | D59: AMERICAS | E59: 1069.0142 | F59: 1456.5984 | G59: 2048.3945 | H59: 989.96611 | I59: 1352.4372 | J59: 1787.6499 | K59: 1187.2759 | L59: 1497.9865 | M59: 1955.7669 | O59: 99.313865 | P59: 135.32132 | Q59: 190.30053 | R59: 91.970112 | S59: 125.6445 | T59: 166.07676 | U59: 110.30064 | V59: 139.16637 | W59: 181.69521 | Z59: =O59/$Z$3 -> 0.46437569
B60: Brazil | C60: Sao Paulo | D60: AMERICAS | E60: 1069.0142 | F60: 1456.5984 | G60: 2048.3945 | H60: 989.96611 | I60: 1352.4372 | J60: 1787.6499 | K60: 1187.2759 | L60: 1497.9865 | M60: 1955.7669 | O60: 99.313865 | P60: 135.32132 | Q60: 190.30053 | R60: 91.970112 | S60: 125.6445 | T60: 166.07676 | U60: 110.30064 | V60: 139.16637 | W60: 181.69521 | Z60: =O60/$Z$3 -> 0.46437569
B61: Colombia | C61: Bogota | D61: AMERICAS | E61: =O61*10.764 -> 1080.9209 | F61: =P61*10.764 -> 1567.346 | G61: =Q61*10.764 -> 1880.7937 | H61: =R61*10.764 -> 1052.5039 | I61: =S61*10.764 -> 1490.5987 | J61: =T61*10.764 -> 1764.8654 | K61: =U61*10.764 -> 1191.7901 | L61: =V61*10.764 -> 1574.6656 | M61: =W61*10.764 -> 1946.9923 | O61: 100.42 | P61: 145.61 | Q61: 174.73 | R61: 97.78 | S61: 138.48 | T61: 163.96 | U61: 110.72 | V61: 146.29 | W61: 180.88 | Z61: =O61/$Z$3 -> 0.4695478
B62: Chile | C62: Santiago | D62: AMERICAS | E62: =O62*10.764 -> 954.87444 | F62: =P62*10.764 -> 1383.0664 | G62: =Q62*10.764 -> 1659.163 | H62: =R62*10.764 -> 929.79432 | I62: =S62*10.764 -> 1315.5761 | J62: =T62*10.764 -> 1557.0126 | K62: =U62*10.764 -> 1052.5039 | L62: =V62*10.764 -> 1389.6324 | M62: =W62*10.764 -> 1717.5038 | O62: 88.71 | P62: 128.49 | Q62: 154.14 | R62: 86.38 | S62: 122.22 | T62: 144.65 | U62: 97.78 | V62: 129.1 | W62: 159.56 | Z62: =O62/$Z$3 -> 0.41479372
B63: Costa Rica | C63: San Jose | D63: AMERICAS | E63: =O63*10.764 -> 900.19332 | F63: =P63*10.764 -> 1303.3051 | G63: =Q63*10.764 -> 1563.2557 | H63: =R63*10.764 -> 876.62016 | I63: =S63*10.764 -> 1239.7975 | J63: =T63*10.764 -> 1467.0256 | K63: =U63*10.764 -> 992.11788 | L63: =V63*10.764 -> 1309.5482 | M63: =W63*10.764 -> 1618.0445 | O63: 83.63 | P63: 121.08 | Q63: 145.23 | R63: 81.44 | S63: 115.18 | T63: 136.29 | U63: 92.17 | V63: 121.66 | W63: 150.32 | Z63: =O63/$Z$3 -> 0.39104046
B64: Mexico | C64: Mexico City | D64: AMERICAS | E64: 1115.0525 | F64: 1519.3284 | G64: 2136.6108 | H64: 1032.6001 | I64: 1410.6813 | J64: 1864.637 | K64: 1238.4072 | L64: 1562.4989 | M64: 2039.9941 | O64: 103.59092 | P64: 141.14908 | Q64: 198.49602 | R64: 95.930904 | S64: 131.05552 | T64: 173.22903 | U64: 115.05086 | V64: 145.15972 | W64: 189.52011 | Z64: =O64/$Z$3 -> 0.48437453
B65: Mexico | C65: Guadalajara | D65: AMERICAS | E65: 1115.0525 | F65: 1519.3284 | G65: 2136.6108 | H65: 1032.6001 | I65: 1410.6813 | J65: 1864.637 | K65: 1238.4072 | L65: 1562.4989 | M65: 2039.9941 | O65: 103.59092 | P65: 141.14908 | Q65: 198.49602 | R65: 95.930904 | S65: 131.05552 | T65: 173.22903 | U65: 115.05086 | V65: 145.15972 | W65: 189.52011 | Z65: =O65/$Z$3 -> 0.48437453
B66: Mexico | C66: Monterrey | D66: AMERICAS | E66: 1115.0525 | F66: 1519.3284 | G66: 2136.6108 | H66: 1032.6001 | I66: 1410.6813 | J66: 1864.637 | K66: 1238.4072 | L66: 1562.4989 | M66: 2039.9941 | O66: 103.59092 | P66: 141.14908 | Q66: 198.49602 | R66: 95.930904 | S66: 131.05552 | T66: 173.22903 | U66: 115.05086 | V66: 145.15972 | W66: 189.52011 | Z66: =O66/$Z$3 -> 0.48437453
B67: Mexico | C67: Queretaro | D67: AMERICAS | E67: 1115.0525 | F67: 1519.3284 | G67: 2136.6108 | H67: 1032.6001 | I67: 1410.6813 | J67: 1864.637 | K67: 1238.4072 | L67: 1562.4989 | M67: 2039.9941 | O67: 103.59092 | P67: 141.14908 | Q67: 198.49602 | R67: 95.930904 | S67: 131.05552 | T67: 173.22903 | U67: 115.05086 | V67: 145.15972 | W67: 189.52011 | Z67: =O67/$Z$3 -> 0.48437453
B68: Panama | C68: Panama City | D68: AMERICAS | E68: =O68*10.764 -> 1292.1106 | F68: =P68*10.764 -> 1875.7346 | G68: =Q68*10.764 -> 2251.9364 | H68: =R68*10.764 -> 1257.881 | I68: =S68*10.764 -> 1783.5948 | J68: =T68*10.764 -> 2112.6503 | K68: =U68*10.764 -> 1425.1536 | L68: =V68*10.764 -> 1884.5611 | M68: =W68*10.764 -> 2331.2671 | O68: 120.04 | P68: 174.26 | Q68: 209.21 | R68: 116.86 | S68: 165.7 | T68: 196.27 | U68: 132.4 | V68: 175.08 | W68: 216.58 | Z68: =O68/$Z$3 -> 0.56128777
B69: Austria | C69: Vienna | D69: EMEA | E69: 873.74731 | F69: 1173.392 | G69: 1411.0911 | H69: 771.91801 | I69: 1008.6306 | J69: 1222.5923 | K69: 941.60585 | L69: 1144.7537 | M69: 1626.195 | O69: 81.173121 | P69: 109.0108 | Q69: 131.09359 | R69: 71.712946 | S69: 93.704089 | T69: 113.58162 | U69: 87.477334 | V69: 106.35023 | W69: 151.07723 | Y69: =O69/$Y$3 -> 0.55818291
B70: Belgium | C70: Brussels | D70: EMEA | E70: 913.27347 | F70: 1302.7311 | G70: 1620.4621 | H70: 889.69409 | I70: 1329.3587 | J70: 1563.1098 | K70: 1140.8467 | L70: 1500.9848 | M70: 1928.0522 | O70: 84.845191 | P70: 121.0267 | Q70: 150.54463 | R70: 82.654613 | S70: 123.50046 | T70: 145.21647 | U70: 105.98727 | V70: 139.44492 | W70: 179.12045 | Y70: =O70/$Y$3 -> 0.58343372
B71: Botswana | C71: Gabarone | D71: EMEA | E71: 860.94069 | F71: 1268.7336 | G71: 1716.5762 | H71: 887.75783 | I71: 1222.5156 | J71: 1554.3877 | K71: 1150.266 | L71: 1432.9168 | M71: 1944.1946 | O71: 79.983357 | P71: 117.86825 | Q71: 159.47385 | R71: 82.47473 | S71: 113.57449 | T71: 144.40617 | U71: 106.86234 | V71: 133.12124 | W71: 180.62012 | Y71: =O71/$Y$3 -> 0.55000156
B72: Bulgaria | C72: Sofia | D72: EMEA | E72: 967.29903 | F72: 967.29903 | G72: 967.29903 | H72: 967.29903 | I72: 967.29903 | J72: 967.29903 | K72: 967.29903 | L72: 967.29903 | M72: 967.29903 | O72: 89.8645 | P72: 150.766 | Q72: 188.793 | R72: 90.2 | S72: 151.1125 | T72: 175.164 | U72: 97.4765 | V72: 150.7385 | W72: 172.865 | Y72: =O72/$Y$3 -> 0.61794875
B73: Croatia | C73: Zagreb | D73: EMEA | E73: 1058.3843 | F73: 1058.3843 | G73: 1058.3843 | H73: 1058.3843 | I73: 1058.3843 | J73: 1058.3843 | K73: 1058.3843 | L73: 1058.3843 | M73: 1058.3843 | O73: 98.3223 | P73: 164.9619 | Q73: 206.5742 | R73: 98.6861 | S73: 165.3471 | T73: 191.6584 | U73: 106.6576 | V73: 164.9298 | W73: 191.7654 | Y73: =O73/$Y$3 -> 0.67610838
B74: Czech Republic | C74: Prague | D74: EMEA | E74: 504.76086 | F74: 844.20455 | G74: 1154.8402 | H74: 540.41964 | I74: 871.0993 | J74: 1113.6111 | K74: 649.62989 | L74: 927.69385 | M74: 1298.2304 | O74: 46.893436 | P74: 78.42853 | Q74: 107.28729 | R74: 50.206219 | S74: 80.927115 | T74: 103.45701 | U74: 60.3521 | V74: 86.184877 | W74: 120.60857 | Y74: =O74/$Y$3 -> 0.32246037
B75: Denmark | C75: Copenhagen | D75: EMEA | E75: 1346.7416 | F75: 1835.0192 | G75: 2580.5625 | H75: 1247.1569 | I75: 1703.7971 | J75: 2252.0771 | K75: 1495.7273 | L75: 1887.1598 | M75: 2463.8704 | O75: 125.11537 | P75: 170.47748 | Q75: 239.74015 | R75: 115.86373 | S75: 158.28665 | T75: 209.22311 | U75: 138.95649 | V75: 175.32146 | W75: 228.89919 | Y75: =O75/$Y$3 -> 0.86034959
B76: Ethiopia | C76: Addis Ababa | D76: EMEA | E76: 828.67683 | F76: 1147.6344 | G76: 1833.9745 | H76: 1016.1419 | I76: 1304.4877 | J76: 1843.1821 | K76: 1158.1098 | L76: 1385.1917 | M76: 2090.26 | O76: 76.98597 | P76: 106.61786 | Q76: 170.38042 | R76: 94.401906 | S76: 121.18989 | T76: 171.23582 | U76: 107.59105 | V76: 128.68747 | W76: 194.18993 | Y76: =O76/$Y$3 -> 0.52939018
B77: Finland | C77: Helsinki | D77: EMEA | E77: 1237.1231 | F77: 1685.6572 | G77: 2370.5167 | H77: 1145.6442 | I77: 1565.116 | J77: 2068.7685 | K77: 1373.9821 | L77: 1733.5538 | M77: 2263.3228 | O77: 114.93156 | P77: 156.6014 | Q77: 220.22642 | R77: 106.43296 | S77: 145.40285 | T77: 192.19332 | U77: 127.64607 | V77: 161.05111 | W77: 210.26786 | Y77: =O77/$Y$3 -> 0.79032114
B78: France | C78: Paris | D78: EMEA | E78: 1315.422 | F78: 1792.3444 | G78: 2520.5494 | H78: 1218.1533 | I78: 1664.1739 | J78: 2199.7032 | K78: 1460.943 | L78: 1843.2724 | M78: 2406.5711 | O78: 122.20571 | P78: 166.51289 | Q78: 234.1648 | R78: 113.16922 | S78: 154.60556 | T78: 204.35745 | U78: 135.72494 | V78: 171.24421 | W78: 223.57595 | Y78: =O78/$Y$3 -> 0.84034146
A79: ? | B79: Germany | C79: Berlin | D79: EMEA
B80: Germany | C80: Cologne | D80: EMEA | E80: 1218.5938 | F80: 1429.1247 | G80: 1720.9362 | H80: 1056.8764 | I80: 1265.5227 | J80: 1546.8561 | K80: 1228.1856 | L80: 1438.0752 | M80: 1726.6878 | O80: 113.21015 | P80: 132.76895 | Q80: 159.8789 | R80: 98.186232 | S80: 117.56995 | T80: 143.70646 | U80: 114.10125 | V80: 133.60047 | W80: 160.41324 | Y80: =O80/$Y$3 -> 0.77848392
A81: ? | B81: Germany | C81: Frankfurt | D81: EMEA
A82: ? | B82: Germany | C82: Hamburg | D82: EMEA
A83: ? | B83: Germany | C83: Munich | D83: EMEA
A84: ? | B84: Germany | C84: Stuttgart | D84: EMEA
B85: Ghana | C85: Accra | D85: EMEA | E85: 954.49576 | F85: 1403.1196 | G85: 1891.0942 | H85: 934.80283 | I85: 1306.9535 | J85: 1665.6793 | K85: 1264.8225 | L85: 1580.0541 | M85: 2164.7676 | O85: 88.674836 | P85: 130.35302 | Q85: 175.68697 | R85: 86.845318 | S85: 121.41897 | T85: 154.74541 | U85: 117.5049 | V85: 146.79064 | W85: 201.11186 | Y85: =O85/$Y$3 -> 0.60976808
B86: Hungary | C86: Budapest | D86: EMEA | E86: 971.50637 | F86: 1262.3664 | G86: 1412.3895 | H86: 947.1396 | I86: 1152.0544 | J86: 1234.1369 | K86: 1024.0752 | L86: 1231.2372 | M86: 1475.2084 | O86: 90.255161 | P86: 117.27672 | Q86: 131.21421 | R86: 87.991432 | S86: 107.02849 | T86: 114.65414 | U86: 95.138921 | V86: 114.38474 | W86: 137.05023 | Y86: =O86/$Y$3 -> 0.6206351
B87: Ireland | C87: Dublin | D87: EMEA | E87: 1152.6034 | F87: 1576.491 | G87: 2005.5599 | H87: 1141.8406 | I87: 1532.6268 | J87: 1918.8995 | K87: 1355.8855 | L87: 1678.3696 | M87: 2447.6862 | O87: 107.07948 | P87: 146.45961 | Q87: 186.3211 | R87: 106.0796 | S87: 142.38453 | T87: 178.27014 | U87: 125.96486 | V87: 155.92437 | W87: 227.39564 | Y87: =O87/$Y$3 -> 0.73632673
B88: Israel | C88: Tel Aviv | D88: EMEA | E88: 1170.9677 | F88: 1170.9677 | G88: 1170.9677 | H88: 1170.9677 | I88: 1170.9677 | J88: 1170.9677 | K88: 1170.9677 | L88: 1170.9677 | M88: 1170.9677 | O88: 108.7866 | P88: 146.8246 | Q88: 157.5392 | R88: 98.3788 | S88: 127.9902 | T88: 141.6038 | U88: 107.3254 | V88: 131.8434 | W88: 145.0696 | Y88: =O88/$Y$3 -> 0.74806562
B89: Italy | C89: Rome | D89: EMEA | E89: 686.05942 | F89: 1162.8963 | G89: 1660.5453 | H89: 681.51125 | I89: 947.87421 | J89: 1253.127 | K89: 858.10036 | L89: 1039.1329 | M89: 1443.1224 | O89: 71.145826 | P89: 119.54629 | Q89: 140.7853 | R89: 71.661785 | S89: 114.98585 | T89: 128.94102 | U89: 76.484921 | V89: 105.5874 | W89: 132.36847 | Y89: =O89/$Y$3 -> 0.48923072
B90: Kenya | C90: Nairobi | D90: EMEA | E90: 746.20234 | F90: 1095.9435 | G90: 1467.9148 | H90: 731.07118 | I90: 1020.2901 | J90: 1294.1182 | K90: 1012.6319 | L90: 1257.4742 | M90: 1700.9926 | O90: 69.323902 | P90: 101.81565 | Q90: 136.37263 | R90: 67.918182 | S90: 94.787283 | T90: 120.22654 | U90: 94.075818 | V90: 116.82222 | W90: 158.0261 | Y90: =O90/$Y$3 -> 0.47670235
B91: Luxembourg | C91: Luxembourg | D91: EMEA | E91: 1009.3824 | F91: 1402.82 | G91: 1669.1711 | H91: 972.71954 | I91: 1430.9518 | J91: 1594.3575 | K91: 1228.1883 | L91: 1659.8113 | M91: 1947.8416 | O91: 93.77393 | P91: 130.32518 | Q91: 155.0698 | R91: 90.367867 | S91: 132.93869 | T91: 148.11946 | U91: 114.10149 | V91: 154.20026 | W91: 180.95893 | Y91: =O91/$Y$3 -> 0.64483175
B92: Morocco | C92: Casablanca | D92: EMEA | E92: 1234.5493 | F92: 1682.1503 | G92: 2365.585 | H92: 1143.2607 | I92: 1561.8598 | J92: 2064.4645 | K92: 1371.1236 | L92: 1729.9472 | M92: 2258.6141 | O92: 114.69245 | P92: 156.2756 | Q92: 219.76825 | R92: 106.21153 | S92: 145.10034 | T92: 191.79347 | U92: 127.38051 | V92: 160.71605 | W92: 209.83041 | Y92: =O92/$Y$3 -> 0.78867691
B93: Netherlands | C93: Amsterdam | D93: EMEA | E93: 752.0674 | F93: 1066.1324 | G93: 1396.1473 | H93: 778.28001 | I93: 974.3752 | J93: 1199.1066 | K93: 742.82316 | L93: 906.49325 | M93: 1185.0785 | O93: 69.86878 | P93: 99.046131 | Q93: 129.70527 | R93: 72.303991 | S93: 90.521682 | T93: 111.39974 | U93: 69.009968 | V93: 84.215294 | W93: 110.0965 | Y93: =O93/$Y$3 -> 0.48044917
B94: Nigeria | C94: Abuja | D94: EMEA | E94: 963.3358 | F94: 1403.529 | G94: 1992.835 | H94: 939.43483 | I94: 1316.8858 | J94: 1755.0051 | K94: 1212.2018 | L94: 1535.4781 | M94: 2170.2963 | O94: 89.496096 | P94: 130.39105 | Q94: 185.13893 | R94: 87.275642 | S94: 122.3417 | T94: 163.04398 | U94: 112.61632 | V94: 142.64943 | W94: 201.62548 | Y94: =O94/$Y$3 -> 0.61541543
B95: Norway | C95: Oslo | D95: EMEA | E95: 1248.9141 | F95: 1701.7231 | G95: 2393.11 | H95: 1156.5633 | I95: 1580.033 | J95: 2088.4858 | K95: 1387.0775 | L95: 1750.0762 | M95: 2284.8945 | O95: 116.02697 | P95: 158.09397 | Q95: 222.32539 | R95: 107.44737 | S95: 146.78868 | T95: 194.02511 | U95: 128.86266 | V95: 162.58608 | W95: 212.27192 | Y95: =O95/$Y$3 -> 0.79785366
B96: Poland | C96: Warsaw | D96: EMEA | E96: 1002.5789 | F96: 1381.4179 | G96: 1639.8664 | H96: 952.93868 | I96: 1288.2369 | J96: 1490.6665 | K96: 935.20508 | L96: 1167.1389 | M96: 1435.5877 | O96: 93.141873 | P96: 128.33688 | Q96: 152.34734 | R96: 88.53018 | S96: 119.68015 | T96: 138.48632 | U96: 86.882688 | V96: 108.42987 | W96: 133.36938 | Y96: =O96/$Y$3 -> 0.64048544
... B111: Uganda | C111: Kampala | D111: EMEA | E111: 945.77248 | F111: 1309.8001 | G111: 2093.1231 | H111: 932.79404 | I111: 1261.8556 | J111: 1878.1089 | K111: 1195.1704 | L111: 1454.3398 | M111: 2259.0374 | O111: 87.864423 | P111: 121.68342 | Q111: 194.45592 | R111: 86.658697 | S111: 117.22927 | T111: 174.48061 | U111: 111.03406 | V111: 135.11149 | W111: 209.86973 | Y111: =O111/$Y$3 -> 0.60419532
B112: China | C112: Hong Kong | D112: APAC | E112: 987.4649 | F112: 1487.1148 | G112: 1927.5031 | H112: 974.33343 | I112: 1340.6165 | J112: 1916.1051 | K112: 987.90946 | L112: 1333.4941 | M112: 1889.7378 | O112: 91.738579 | P112: 138.15762 | Q112: 179.07107 | R112: 90.518625 | S112: 124.54746 | T112: 178.01216 | U112: 91.779881 | V112: 123.88578 | W112: 175.56255 | AA112: =O112/$AA$3 -> 0.74630084
B113: Australia | C113: Sydney | D113: APAC | E113: 1240.5316 | F113: 1794.1552 | G113: 2201.2012 | H113: 1138.3512 | I113: 1628.4401 | J113: 2066.7634 | K113: 1029.7734 | L113: 1365.7991 | M113: 1931.4583 | O113: 115.24927 | P113: 166.68263 | Q113: 204.49848 | R113: 105.75639 | S113: 151.28718 | T113: 192.00879 | U113: 95.669169 | V113: 126.88702 | W113: 179.43852 | AA113: =O113/$AA$3 -> 0.93756224
A114: 0.02 | B114: Australia | C114: Brisbane | D114: APAC | E114: 1265.3423 | F114: 1830.0383 | G114: 2245.2253 | H114: 1161.1183 | I114: 1661.0089 | J114: 2108.0986 | K114: 1050.3688 | L114: 1393.1151 | M114: 1970.0874 | O114: 117.55426 | P114: 170.01629 | Q114: 208.58845 | R114: 107.87152 | S114: 154.31292 | T114: 195.84896 | U114: 97.582552 | V114: 129.42476 | W114: 183.02729 | AA114: =O114/$AA$3 -> 0.95631348
A115: 0.04 | B115: Australia | C115: Melborne | D115: APAC | E115: 1290.1529 | F115: 1865.9214 | G115: 2289.2493 | H115: 1183.8853 | I115: 1693.5777 | J115: 2149.4339 | K115: 1070.9643 | L115: 1420.4311 | M115: 2008.7166 | O115: 119.85924 | P115: 173.34994 | Q115: 212.67842 | R115: 109.98665 | S115: 157.33867 | T115: 199.68914 | U115: 99.495936 | V115: 131.9625 | W115: 186.61606 | AA115: =O115/$AA$3 -> 0.97506473
A116: 0.03 | B116: Australia | C116: Perth | D116: APAC | E116: 1277.7476 | F116: 1847.9798 | G116: 2267.2373 | H116: 1172.5018 | I116: 1677.2933 | J116: 2128.7663 | K116: 1060.6666 | L116: 1406.7731 | M116: 1989.402 | O116: 118.70675 | P116: 171.68311 | Q116: 210.63344 | R116: 108.92908 | S116: 155.82579 | T116: 197.76905 | U116: 98.539244 | V116: 130.69363 | W116: 184.82167 | AA116: =O116/$AA$3 -> 0.9656891
B117: China | C117: Beijing | D117: APAC | E117: 812.25928 | F117: 1219.4384 | G117: 1658.157 | H117: 836.66473 | I117: 1313.8717 | J117: 1710.136 | K117: 899.18778 | L117: 1276.6433 | M117: 1940.653 | O117: 75.46143 | P117: 113.28965 | Q117: 154.04798 | R117: 77.728772 | S117: 122.06279 | T117: 158.87699 | U117: 83.53736 | V117: 118.60416 | W117: 180.29274 | AA117: =O117/$AA$3 -> 0.61388489
B118: China | C118: Guangzhou | D118: APAC | E118: 771.93229 | F118: 1160.7156 | G118: 1578.9138 | H118: 805.82636 | I118: 1262.8164 | J118: 1640.0523 | K118: 862.40046 | L118: 1223.1128 | M118: 1856.7166 | O118: 71.714926 | P118: 107.83411 | Q118: 146.68603 | R118: 74.863791 | S118: 117.3196 | T118: 152.36599 | U118: 80.119702 | V118: 113.63101 | W118: 172.49479 | AA118: =O118/$AA$3 -> 0.58340678
B119: China | C119: Shanghai | D119: APAC | E119: 809.38724 | F119: 1216.6628 | G119: 1655.7329 | H119: 823.01586 | I119: 1192.2828 | J119: 1590.3651 | K119: 776.72556 | L119: 1089.2916 | M119: 1730.3081 | O119: 75.194608 | P119: 113.03178 | Q119: 153.82277 | R119: 76.46075 | S119: 110.76681 | T119: 147.74989 | U119: 72.160235 | V119: 101.1986 | W119: 160.75104 | AA119: =O119/$AA$3 -> 0.61171428
B120: India | C120: Bangalore | D120: APAC | E120: 453.5755 | F120: 562.75089 | G120: 758.58852 | H120: 416.57962 | I120: 578.66106 | J120: 702.9544 | K120: 518.40874 | L120: 638.70439 | M120: 986.48251 | O120: 42.138583 | P120: 52.281319 | Q120: 70.475247 | R120: 38.70155 | S120: 53.759423 | T120: 65.306664 | U120: 48.161795 | V120: 59.337637 | W120: 91.647313 | AA120: =O120/$AA$3 -> 0.34280082
A121: -0.01 | B121: India | C121: Chennai | D121: APAC | E121: 449.08465 | F121: 557.1791 | G121: 751.07774 | H121: 412.45507 | I121: 572.93174 | J121: 695.99446 | K121: 513.27598 | L121: 632.38059 | M121: 976.71535 | O121: 41.72137 | P121: 51.763682 | Q121: 69.777473 | R121: 38.318367 | S121: 53.227152 | T121: 64.660064 | U121: 47.684945 | V121: 58.750136 | W121: 90.739913 | AA121: =O121/$AA$3 -> 0.33940675
A122: -0.01 | B122: India | C122: Hyderbad | D122: APAC | E122: 449.08465 | F122: 557.1791 | G122: 751.07774 | H122: 412.45507 | I122: 572.93174 | J122: 695.99446 | K122: 513.27598 | L122: 632.38059 | M122: 976.71535 | O122: 41.72137 | P122: 51.763682 | Q122: 69.777473 | R122: 38.318367 | S122: 53.227152 | T122: 64.660064 | U122: 47.684945 | V122: 58.750136 | W122: 90.739913 | AA122: =O122/$AA$3 -> 0.33940675
A123: -0.02 | B123: India | C123: Kolkata | D123: APAC | E123: 444.68186 | F123: 551.71656 | G123: 743.71423 | H123: 408.41139 | I123: 567.31476 | J123: 689.17098 | K123: 508.24386 | L123: 626.18078 | M123: 967.13971 | O123: 41.312337 | P123: 51.256195 | Q123: 69.09338 | R123: 37.942696 | S123: 52.705317 | T123: 64.026141 | U123: 47.217446 | V123: 58.174154 | W123: 89.850306 | AA123: =O123/$AA$3 -> 0.33607923
A124: 0.08 | B124: India | C124: Mumbai | D124: APAC | E124: 489.86154 | F124: 607.77096 | G124: 819.2756 | H124: 449.90599 | I124: 624.95394 | J124: 759.19076 | K124: 559.88144 | L124: 689.80074 | M124: 1065.4011 | O124: 45.50967 | P124: 56.463825 | Q124: 76.113267 | R124: 41.797674 | S124: 58.060177 | T124: 70.531197 | U124: 52.014738 | V124: 64.084648 | W124: 98.979098 | AA124: =O124/$AA$3 -> 0.37022488
A125: 0.05 | B125: India | C125: New Delhi | D125: APAC | E125: 476.25427 | F125: 590.88843 | G125: 796.51794 | H125: 437.4086 | I125: 607.59411 | J125: 738.10212 | K125: 544.32918 | L125: 670.63961 | M125: 1035.8066 | O125: 44.245513 | P125: 54.895385 | Q125: 73.99901 | R125: 40.636628 | S125: 56.447395 | T125: 68.571997 | U125: 50.569884 | V125: 62.304519 | W125: 96.229678 | AA125: =O125/$AA$3 -> 0.35994086
A126: -0.01 | B126: India | C126: Pune | D126: APAC | E126: 449.08465 | F126: 557.1791 | G126: 751.07774 | H126: 412.45507 | I126: 572.93174 | J126: 695.99446 | K126: 513.27598 | L126: 632.38059 | M126: 976.71535 | O126: 41.72137 | P126: 51.763682 | Q126: 69.777473 | R126: 38.318367 | S126: 53.227152 | T126: 64.660064 | U126: 47.684945 | V126: 58.750136 | W126: 90.739913 | AA126: =O126/$AA$3 -> 0.33940675
B127: Indonesia | C127: Jakarta | D127: APAC | E127: 782.9197 | F127: 998.33313 | G127: 1254.9885 | H127: 705.51675 | I127: 811.559 | J127: 1082.7056 | K127: 994.45205 | L127: 1076.2543 | M127: 1438.4206 | O127: 72.73569 | P127: 92.748273 | Q127: 116.59236 | R127: 65.544714 | S127: 75.396371 | T127: 100.58674 | U127: 92.387708 | V127: 99.987395 | W127: 133.63377 | AA127: =O127/$AA$3 -> 0.59171078
B128: Japan | C128: Tokyo | D128: APAC | E128: 1776.8153 | F128: 2284.4698 | G128: 2721.0351 | H128: 1561.5776 | I128: 2098.6412 | J128: 2413.9909 | K128: 1441.4862 | L128: 1763.3798 | M128: 2482.5079 | O128: 165.0717 | P128: 212.23439 | Q128: 252.79268 | R128: 145.07545 | S128: 194.97033 | T128: 224.26731 | U128: 133.91858 | V128: 163.8235 | W128: 230.63276 | AA128: =O128/$AA$3 -> 1.3428718
B129: Malaysia | C129: Kuala Lumpur | D129: APAC | E129: 775.03335 | F129: 1050.0587 | G129: 1484.977 | H129: 689.89208 | I129: 983.19264 | J129: 1177.3132 | K129: 938.79304 | L129: 1105.201 | M129: 1538.5298 | O129: 72.003024 | P129: 97.553739 | Q129: 137.95901 | R129: 64.093134 | S129: 91.341674 | T129: 109.37608 | U129: 87.216812 | V129: 102.67663 | W129: 142.93423 | AA129: =O129/$AA$3 -> 0.58575048
...

Sheet FURNITURE
A1: a | E1: FURNITURE $/M2 | O1: FURNITURE $/SQFT | Y1: LOCATION FACTOR
E2: Activity | H2: Team | K2: Event | O2: Activity | R2: Team | U2: Event | Y2: EMEA | Z2: AMERICA | AA2: APAC
E3: Low | F3: Medium | G3: High | H3: Low | I3: Medium | J3: High | K3: Low | L3: Medium | M3: High | O3: Low | P3: Medium | Q3: High | R3: Low | S3: Medium | T3: High | U3: Low | V3: Medium | W3: High | Y3: 145.42387 | Z3: 213.86534 | AA3: 153.6541
B4: COUNTRY | C4: CITY | D4: REGION
B5: United States | C5: Cincinnati | D5: AMERICAS | E5: =238.73*$Z5 -> 187.98909 | F5: =315.46*Z5 -> 248.4105 | G5: =365.27*Z5 -> 287.63363 | H5: =191.35*Z5 -> 150.67948 | I5: =307.57*Z5 -> 242.19749 | J5: =368.13*Z5 -> 289.88575 | K5: =179*Z5 -> 140.95442 | L5: =252.87*Z5 -> 199.12371 | M5: =276.8*Z5 -> 217.9675 | O5: =22.18*$O5 -> #NUM! | P5: =29.31*$O5 -> #NUM! | Q5: =33.93*$O5 -> #NUM! | R5: =17.78*$O5 -> #NUM! | S5: =28.57*$O5 -> #NUM! | T5: =34.2*$O5 -> #NUM! | U5: =16.63*$O5 -> #NUM! | V5: =23.49*$O5 -> #NUM! | W5: =25.71*$O5 -> #NUM! | Z5: 0.78745484
B6: United States | C6: Charlotte | D6: AMERICAS | E6: =238.73*$Z6 -> 175.60213 | F6: =315.46*Z6 -> 232.04226 | G6: =365.27*Z6 -> 268.6809 | H6: =191.35*Z6 -> 140.75092 | I6: =307.57*Z6 -> 226.23863 | J6: =368.13*Z6 -> 270.78462 | K6: =179*Z6 -> 131.66666 | L6: =252.87*Z6 -> 186.00306 | M6: =276.8*Z6 -> 203.60521 | O6: =22.18*$O6 -> #NUM! | P6: =29.31*$O6 -> #NUM! | Q6: =33.93*$O6 -> #NUM! | R6: =17.78*$O6 -> #NUM! | S6: =28.57*$O6 -> #NUM! | T6: =34.2*$O6 -> #NUM! | U6: =16.63*$O6 -> #NUM! | V6: =23.49*$O6 -> #NUM! | W6: =25.71*$O6 -> #NUM! | Z6: 0.73556794
B7: United States | C7: Charleston | D7: AMERICAS | E7: =238.73*$Z7 -> 175.60213 | F7: =315.46*Z7 -> 232.04226 | G7: =365.27*Z7 -> 268.6809 | H7: =191.35*Z7 -> 140.75092 | I7: =307.57*Z7 -> 226.23863 | J7: =368.13*Z7 -> 270.78462 | K7: =179*Z7 -> 131.66666 | L7: =252.87*Z7 -> 186.00306 | M7: =276.8*Z7 -> 203.60521 | O7: =22.18*$O7 -> #NUM! | P7: =29.31*$O7 -> #NUM! | Q7: =33.93*$O7 -> #NUM! | R7: =17.78*$O7 -> #NUM! | S7: =28.57*$O7 -> #NUM! | T7: =34.2*$O7 -> #NUM! | U7: =16.63*$O7 -> #NUM! | V7: =23.49*$O7 -> #NUM! | W7: =25.71*$O7 -> #NUM! | Z7: 0.73556794
B8: United States | C8: Chicago | D8: AMERICAS | E8: =238.73*$Z8 -> 230.06524 | F8: =315.46*Z8 -> 304.01031 | G8: =365.27*Z8 -> 352.01244 | H8: =191.35*Z8 -> 184.40491 | I8: =307.57*Z8 -> 296.40668 | J8: =368.13*Z8 -> 354.76864 | K8: =179*Z8 -> 172.50315 | L8: =252.87*Z8 -> 243.69203 | M8: =276.8*Z8 -> 266.75348 | O8: =22.18*$O8 -> #NUM! | P8: =29.31*$O8 -> #NUM! | Q8: =33.93*$O8 -> #NUM! | R8: =17.78*$O8 -> #NUM! | S8: =28.57*$O8 -> #NUM! | T8: =34.2*$O8 -> #NUM! | U8: =16.63*$O8 -> #NUM! | V8: =23.49*$O8 -> #NUM! | W8: =25.71*$O8 -> #NUM! | Z8: 0.96370477
B9: United States | C9: Cleveland | D9: AMERICAS | E9: =238.73*$Z9 -> 182.34079 | F9: =315.46*Z9 -> 240.94679 | G9: =365.27*Z9 -> 278.99142 | H9: =191.35*Z9 -> 146.15218 | I9: =307.57*Z9 -> 234.92044 | J9: =368.13*Z9 -> 281.17587 | K9: =179*Z9 -> 136.71931 | L9: =252.87*Z9 -> 193.14085 | M9: =276.8*Z9 -> 211.41847 | O9: =22.18*$O9 -> #NUM! | P9: =29.31*$O9 -> #NUM! | Q9: =33.93*$O9 -> #NUM! | R9: =17.78*$O9 -> #NUM! | S9: =28.57*$O9 -> #NUM! | T9: =34.2*$O9 -> #NUM! | U9: =16.63*$O9 -> #NUM! | V9: =23.49*$O9 -> #NUM! | W9: =25.71*$O9 -> #NUM! | Z9: 0.76379505
B10: United States | C10: Boston | D10: AMERICAS | E10: =238.73*$Z10 -> 223.9701 | F10: =315.46*Z10 -> 295.95613 | G10: =365.27*Z10 -> 342.68654 | H10: =191.35*Z10 -> 179.51945 | I10: =307.57*Z10 -> 288.55395 | J10: =368.13*Z10 -> 345.36972 | K10: =179*Z10 -> 167.93301 | L10: =252.87*Z10 -> 237.23587 | M10: =276.8*Z10 -> 259.68636 | O10: =22.18*$O10 -> #NUM! | P10: =29.31*$O10 -> #NUM! | Q10: =33.93*$O10 -> #NUM! | R10: =17.78*$O10 -> #NUM! | S10: =28.57*$O10 -> #NUM! | T10: =34.2*$O10 -> #NUM! | U10: =16.63*$O10 -> #NUM! | V10: =23.49*$O10 -> #NUM! | W10: =25.71*$O10 -> #NUM! | Z10: 0.93817325
B11: United States | C11: Baltimore | D11: AMERICAS | E11: =238.73*$Z11 -> 183.12071 | F11: =315.46*Z11 -> 241.97737 | G11: =365.27*Z11 -> 280.18473 | H11: =191.35*Z11 -> 146.77731 | I11: =307.57*Z11 -> 235.92525 | J11: =368.13*Z11 -> 282.37853 | K11: =179*Z11 -> 137.3041 | L11: =252.87*Z11 -> 193.96696 | M11: =276.8*Z11 -> 212.32276 | O11: =22.18*$O11 -> #NUM! | P11: =29.31*$O11 -> #NUM! | Q11: =33.93*$O11 -> #NUM! | R11: =17.78*$O11 -> #NUM! | S11: =28.57*$O11 -> #NUM! | T11: =34.2*$O11 -> #NUM! | U11: =16.63*$O11 -> #NUM! | V11: =23.49*$O11 -> #NUM! | W11: =25.71*$O11 -> #NUM! | Z11: 0.76706198
B12: United States | C12: Columbus | D12: AMERICAS | E12: =238.73*$Z12 -> 178.14253 | F12: =315.46*Z12 -> 235.39917 | G12: =365.27*Z12 -> 272.56785 | H12: =191.35*Z12 -> 142.78714 | I12: =307.57*Z12 -> 229.51158 | J12: =368.13*Z12 -> 274.70201 | K12: =179*Z12 -> 133.57145 | L12: =252.87*Z12 -> 188.69393 | M12: =276.8*Z12 -> 206.55072 | O12: =22.18*$O12 -> #NUM! | P12: =29.31*$O12 -> #NUM! | Q12: =33.93*$O12 -> #NUM! | R12: =17.78*$O12 -> #NUM! | S12: =28.57*$O12 -> #NUM! | T12: =34.2*$O12 -> #NUM! | U12: =16.63*$O12 -> #NUM! | V12: =23.49*$O12 -> #NUM! | W12: =25.71*$O12 -> #NUM! | Z12: 0.74620924
B13: United States | C13: Austin | D13: AMERICAS | E13: =238.73*$Z13 -> 167.19752 | F13: =315.46*Z13 -> 220.93632 | G13: =365.27*Z13 -> 255.82138 | H13: =191.35*Z13 -> 134.01435 | I13: =307.57*Z13 -> 215.41047 | J13: =368.13*Z13 -> 257.82441 | K13: =179*Z13 -> 125.36487 | L13: =252.87*Z13 -> 177.10064 | M13: =276.8*Z13 -> 193.86031 | O13: =22.18*$O13 -> #NUM! | P13: =29.31*$O13 -> #NUM! | Q13: =33.93*$O13 -> #NUM! | R13: =17.78*$O13 -> #NUM! | S13: =28.57*$O13 -> #NUM! | T13: =34.2*$O13 -> #NUM! | U13: =16.63*$O13 -> #NUM! | V13: =23.49*$O13 -> #NUM! | W13: =25.71*$O13 -> #NUM! | Z13: 0.70036241
B14: United States | C14: Atlanta | D14: AMERICAS | E14: =238.73*$Z14 -> 176.42506 | F14: =315.46*Z14 -> 233.12968 | G14: =365.27*Z14 -> 269.94002 | H14: =191.35*Z14 -> 141.41053 | I14: =307.57*Z14 -> 227.29885 | J14: =368.13*Z14 -> 272.0536 | K14: =179*Z14 -> 132.28369 | L14: =252.87*Z14 -> 186.87473 | M14: =276.8*Z14 -> 204.55936 | O14: =22.18*$O14 -> #NUM! | P14: =29.31*$O14 -> #NUM! | Q14: =33.93*$O14 -> #NUM! | R14: =17.78*$O14 -> #NUM! | S14: =28.57*$O14 -> #NUM! | T14: =34.2*$O14 -> #NUM! | U14: =16.63*$O14 -> #NUM! | V14: =23.49*$O14 -> #NUM! | W14: =25.71*$O14 -> #NUM! | Z14: 0.73901503
B15: United States | C15: Dallas | D15: AMERICAS | E15: =238.73*$Z15 -> 168.02849 | F15: =315.46*Z15 -> 222.03437 | G15: =365.27*Z15 -> 257.0928 | H15: =191.35*Z15 -> 134.68039 | I15: =307.57*Z15 -> 216.48105 | J15: =368.13*Z15 -> 259.10579 | K15: =179*Z15 -> 125.98793 | L15: =252.87*Z15 -> 177.98083 | M15: =276.8*Z15 -> 194.8238 | O15: =22.18*$O15 -> #NUM! | P15: =29.31*$O15 -> #NUM! | Q15: =33.93*$O15 -> #NUM! | R15: =17.78*$O15 -> #NUM! | S15: =28.57*$O15 -> #NUM! | T15: =34.2*$O15 -> #NUM! | U15: =16.63*$O15 -> #NUM! | V15: =23.49*$O15 -> #NUM! | W15: =25.71*$O15 -> #NUM! | Z15: 0.70384319
B16: United States | C16: Denver | D16: AMERICAS | E16: =238.73*$Z16 -> 179.47835 | F16: =315.46*Z16 -> 237.16433 | G16: =365.27*Z16 -> 274.61173 | H16: =191.35*Z16 -> 143.85784 | I16: =307.57*Z16 -> 231.23259 | J16: =368.13*Z16 -> 276.76189 | K16: =179*Z16 -> 134.57305 | L16: =252.87*Z16 -> 190.10887 | M16: =276.8*Z16 -> 208.09956 | O16: =22.18*$O16 -> #NUM! | P16: =29.31*$O16 -> #NUM! | Q16: =33.93*$O16 -> #NUM! | R16: =17.78*$O16 -> #NUM! | S16: =28.57*$O16 -> #NUM! | T16: =34.2*$O16 -> #NUM! | U16: =16.63*$O16 -> #NUM! | V16: =23.49*$O16 -> #NUM! | W16: =25.71*$O16 -> #NUM! | Z16: 0.75180476
... B67: Mexico | C67: Queretaro | D67: AMERICAS | E67: =238.73*$Z67 -> 115.63473 | F67: =315.46*Z67 -> 152.80079 | G67: =365.27*Z67 -> 176.92748 | H67: =191.35*Z67 -> 92.685066 | I67: =307.57*Z67 -> 148.97907 | J67: =368.13*Z67 -> 178.3128 | K67: =179*Z67 -> 86.703041 | L67: =252.87*Z67 -> 122.48379 | M67: =276.8*Z67 -> 134.07487 | O67: =22.18*$O67 -> #NUM! | P67: =29.31*$O67 -> #NUM! | Q67: =33.93*$O67 -> #NUM! | R67: =17.78*$O67 -> #NUM! | S67: =28.57*$O67 -> #NUM! | T67: =34.2*$O67 -> #NUM! | U67: =16.63*$O67 -> #NUM! | V67: =23.49*$O67 -> #NUM! | W67: =25.71*$O67 -> #NUM! | Z67: 0.48437453
B68: Panama | C68: Panama City | D68: AMERICAS | E68: =(221.26*$Y68)*1.08 -> 267.83037 | F68: =(310.41*$Y68)*1.08 -> 375.74449 | G68: =(364.87*$Y68)*1.08 -> 441.66713 | H68: =(176.83*$Y68)*1.08 -> 214.04883 | I68: =(308.58*$Y68)*1.08 -> 373.52932 | J68: =(453.13*$Y68)*1.08 -> 548.50392 | K68: =(207.98*$Y68)*1.08 -> 251.75522 | L68: =(233.85*$Y68)*1.08 -> 283.07029 | M68: =(280.64*$Y68)*1.08 -> 339.70856 | O68: =(20.56*$Y68)*1.08 -> 24.887429 | P68: =(28.84*$Y68)*1.08 -> 34.910187 | Q68: =(33.93*$Y68)*1.08 -> 41.07152 | R68: =(16.43*$Y68)*1.08 -> 19.888154 | S68: =(28.67*$Y68)*1.08 -> 34.704406 | T68: =(42.1*$Y68)*1.08 -> 50.961126 | U68: =(19.32*$Y68)*1.08 -> 23.386436 | V68: =(21.73*$Y68)*1.08 -> 26.303688 | W68: =(26.07*$Y68)*1.08 -> 31.557163 | Y68: 1.120813
B69: Austria | C69: Vienna | D69: EMEA | E69: =(221.26*$Y69)*1.08 -> 133.38384 | F69: =(310.41*$Y69)*1.08 -> 187.1268 | G69: =(364.87*$Y69)*1.08 -> 219.95734 | H69: =(176.83*$Y69)*1.08 -> 106.59976 | I69: =(308.58*$Y69)*1.08 -> 186.02361 | J69: =(453.13*$Y69)*1.08 -> 273.16378 | K69: =(207.98*$Y69)*1.08 -> 125.37815 | L69: =(233.85*$Y69)*1.08 -> 140.97356 | M69: =(280.64*$Y69)*1.08 -> 169.18033 | O69: =(20.56*$Y69)*1.08 -> 12.39434 | P69: =(28.84*$Y69)*1.08 -> 17.385835 | Q69: =(33.93*$Y69)*1.08 -> 20.454278 | R69: =(16.43*$Y69)*1.08 -> 9.9046209 | S69: =(28.67*$Y69)*1.08 -> 17.283352 | T69: =(42.1*$Y69)*1.08 -> 25.379461 | U69: =(19.32*$Y69)*1.08 -> 11.646821 | V69: =(21.73*$Y69)*1.08 -> 13.09966 | W69: =(26.07*$Y69)*1.08 -> 15.715975 | Y69: 0.55818291
B70: Belgium | C70: Brussels | D70: EMEA | E70: =(221.26*$Y70)*1.08 -> 139.41779 | F70: =(310.41*$Y70)*1.08 -> 195.59195 | G70: =(364.87*$Y70)*1.08 -> 229.90766 | H70: =(176.83*$Y70)*1.08 -> 111.42207 | I70: =(308.58*$Y70)*1.08 -> 194.43885 | J70: =(453.13*$Y70)*1.08 -> 285.52103 | K70: =(207.98*$Y70)*1.08 -> 131.04995 | L70: =(233.85*$Y70)*1.08 -> 147.35085 | M70: =(280.64*$Y70)*1.08 -> 176.83363 | O70: =(20.56*$Y70)*1.08 -> 12.955029 | P70: =(28.84*$Y70)*1.08 -> 18.172327 | Q70: =(33.93*$Y70)*1.08 -> 21.379578 | R70: =(16.43*$Y70)*1.08 -> 10.352681 | S70: =(28.67*$Y70)*1.08 -> 18.065208 | T70: =(42.1*$Y70)*1.08 -> 26.527564 | U70: =(19.32*$Y70)*1.08 -> 12.173695 | V70: =(21.73*$Y70)*1.08 -> 13.692256 | W70: =(26.07*$Y70)*1.08 -> 16.426926 | Y70: 0.58343372
B71: Botswana | C71: Gabarone | D71: EMEA | E71: =(221.26*$Y71)*1.08 -> 131.42881 | F71: =(310.41*$Y71)*1.08 -> 184.38406 | G71: =(364.87*$Y71)*1.08 -> 216.73339 | H71: =(176.83*$Y71)*1.08 -> 105.03732 | I71: =(308.58*$Y71)*1.08 -> 183.29704 | J71: =(453.13*$Y71)*1.08 -> 269.15998 | K71: =(207.98*$Y71)*1.08 -> 123.54047 | L71: =(233.85*$Y71)*1.08 -> 138.90729 | M71: =(280.64*$Y71)*1.08 -> 166.70063 | O71: =(20.56*$Y71)*1.08 -> 12.212675 | P71: =(28.84*$Y71)*1.08 -> 17.131008 | Q71: =(33.93*$Y71)*1.08 -> 20.154477 | R71: =(16.43*$Y71)*1.08 -> 9.7594476 | S71: =(28.67*$Y71)*1.08 -> 17.030028 | T71: =(42.1*$Y71)*1.08 -> 25.007471 | U71: =(19.32*$Y71)*1.08 -> 11.476112 | V71: =(21.73*$Y71)*1.08 -> 12.907657 | W71: =(26.07*$Y71)*1.08 -> 15.485624 | Y71: 0.55000156
B72: Bulgaria | C72: Sofia | D72: EMEA | E72: =(221.26*$Y72)*1.08 -> 147.66553 | F72: =(310.41*$Y72)*1.08 -> 207.16287 | G72: =(364.87*$Y72)*1.08 -> 243.50864 | H72: =(176.83*$Y72)*1.08 -> 118.01363 | I72: =(308.58*$Y72)*1.08 -> 205.94155 | J72: =(453.13*$Y72)*1.08 -> 302.412 | K72: =(207.98*$Y72)*1.08 -> 138.80266 | L72: =(233.85*$Y72)*1.08 -> 156.0679 | M72: =(280.64*$Y72)*1.08 -> 187.29483 | O72: =(20.56*$Y72)*1.08 -> 13.721428 | P72: =(28.84*$Y72)*1.08 -> 19.247373 | Q72: =(33.93*$Y72)*1.08 -> 22.644361 | R72: =(16.43*$Y72)*1.08 -> 10.96513 | S72: =(28.67*$Y72)*1.08 -> 19.133918 | T72: =(42.1*$Y72)*1.08 -> 28.096894 | U72: =(19.32*$Y72)*1.08 -> 12.893871 | V72: =(21.73*$Y72)*1.08 -> 14.502268 | W72: =(26.07*$Y72)*1.08 -> 17.398718 | Y72: 0.61794875
B73: Croatia | C73: Zagreb | D73: EMEA | E73: =(221.26*$Y73)*1.08 -> 161.5634 | F73: =(310.41*$Y73)*1.08 -> 226.66047 | G73: =(364.87*$Y73)*1.08 -> 266.427 | H73: =(176.83*$Y73)*1.08 -> 129.12075 | I73: =(308.58*$Y73)*1.08 -> 225.32421 | J73: =(453.13*$Y73)*1.08 -> 330.87419 | K73: =(207.98*$Y73)*1.08 -> 151.86638 | L73: =(233.85*$Y73)*1.08 -> 170.75658 | M73: =(280.64*$Y73)*1.08 -> 204.9225 | O73: =(20.56*$Y73)*1.08 -> 15.012851 | P73: =(28.84*$Y73)*1.08 -> 21.058883 | Q73: =(33.93*$Y73)*1.08 -> 24.775586 | R73: =(16.43*$Y73)*1.08 -> 11.997138 | S73: =(28.67*$Y73)*1.08 -> 20.93475 | T73: =(42.1*$Y73)*1.08 -> 30.741296 | U73: =(19.32*$Y73)*1.08 -> 14.107407 | V73: =(21.73*$Y73)*1.08 -> 15.867182 | W73: =(26.07*$Y73)*1.08 -> 19.036237 | Y73: 0.67610838
B74: Czech Republic | C74: Prague | D74: EMEA | E74: =(221.26*$Y74)*1.08 -> 77.055389 | F74: =(310.41*$Y74)*1.08 -> 108.10252 | G74: =(364.87*$Y74)*1.08 -> 127.06861 | H74: =(176.83*$Y74)*1.08 -> 61.582321 | I74: =(308.58*$Y74)*1.08 -> 107.46521 | J74: =(453.13*$Y74)*1.08 -> 157.80579 | K74: =(207.98*$Y74)*1.08 -> 72.430533 | L74: =(233.85*$Y74)*1.08 -> 81.439947 | M74: =(280.64*$Y74)*1.08 -> 97.734901 | O74: =(20.56*$Y74)*1.08 -> 7.1601681 | P74: =(28.84*$Y74)*1.08 -> 10.043738 | Q74: =(33.93*$Y74)*1.08 -> 11.816367 | R74: =(16.43*$Y74)*1.08 -> 5.7218658 | S74: =(28.67*$Y74)*1.08 -> 9.984534 | T74: =(42.1*$Y74)*1.08 -> 14.661628 | U74: =(19.32*$Y74)*1.08 -> 6.7283292 | V74: =(21.73*$Y74)*1.08 -> 7.567629 | W74: =(26.07*$Y74)*1.08 -> 9.0790653 | Y74: 0.32246037
B75: Denmark | C75: Copenhagen | D75: EMEA | E75: =(221.26*$Y75)*1.08 -> 205.58983 | F75: =(310.41*$Y75)*1.08 -> 288.42601 | G75: =(364.87*$Y75)*1.08 -> 339.02902 | H75: =(176.83*$Y75)*1.08 -> 164.30647 | I75: =(308.58*$Y75)*1.08 -> 286.72561 | J75: =(453.13*$Y75)*1.08 -> 421.03823 | K75: =(207.98*$Y75)*1.08 -> 193.25035 | L75: =(233.85*$Y75)*1.08 -> 217.28817 | M75: =(280.64*$Y75)*1.08 -> 260.76439 | O75: =(20.56*$Y75)*1.08 -> 19.103891 | P75: =(28.84*$Y75)*1.08 -> 26.797481 | Q75: =(33.93*$Y75)*1.08 -> 31.526995 | R75: =(16.43*$Y75)*1.08 -> 15.266387 | S75: =(28.67*$Y75)*1.08 -> 26.639521 | T75: =(42.1*$Y75)*1.08 -> 39.118375 | U75: =(19.32*$Y75)*1.08 -> 17.95171 | V75: =(21.73*$Y75)*1.08 -> 20.191028 | W75: =(26.07*$Y75)*1.08 -> 24.223659 | Y75: 0.86034959
B76: Ethiopia | C76: Addis Ababa | D76: EMEA | E76: =(221.26*$Y76)*1.08 -> 126.5035 | F76: =(310.41*$Y76)*1.08 -> 177.47425 | G76: =(364.87*$Y76)*1.08 -> 208.61128 | H76: =(176.83*$Y76)*1.08 -> 101.10103 | I76: =(308.58*$Y76)*1.08 -> 176.42796 | J76: =(453.13*$Y76)*1.08 -> 259.07318 | K76: =(207.98*$Y76)*1.08 -> 118.91077 | L76: =(233.85*$Y76)*1.08 -> 133.70172 | M76: =(280.64*$Y76)*1.08 -> 160.4535 | O76: =(20.56*$Y76)*1.08 -> 11.755003 | P76: =(28.84*$Y76)*1.08 -> 16.489022 | Q76: =(33.93*$Y76)*1.08 -> 19.399185 | R76: =(16.43*$Y76)*1.08 -> 9.3937111 | S76: =(28.67*$Y76)*1.08 -> 16.391826 | T76: =(42.1*$Y76)*1.08 -> 24.070313 | U76: =(19.32*$Y76)*1.08 -> 11.046044 | V76: =(21.73*$Y76)*1.08 -> 12.42394 | W76: =(26.07*$Y76)*1.08 -> 14.905298 | Y76: 0.52939018
B77: Finland | C77: Helsinki | D77: EMEA | E77: =(221.26*$Y77)*1.08 -> 188.85577 | F77: =(310.41*$Y77)*1.08 -> 264.94947 | G77: =(364.87*$Y77)*1.08 -> 311.43363 | H77: =(176.83*$Y77)*1.08 -> 150.93269 | I77: =(308.58*$Y77)*1.08 -> 263.38748 | J77: =(453.13*$Y77)*1.08 -> 386.76767 | K77: =(207.98*$Y77)*1.08 -> 177.52067 | L77: =(233.85*$Y77)*1.08 -> 199.60193 | M77: =(280.64*$Y77)*1.08 -> 239.53938 | O77: =(20.56*$Y77)*1.08 -> 17.548923 | P77: =(28.84*$Y77)*1.08 -> 24.616291 | Q77: =(33.93*$Y77)*1.08 -> 28.960844 | R77: =(16.43*$Y77)*1.08 -> 14.023774 | S77: =(28.67*$Y77)*1.08 -> 24.471188 | T77: =(42.1*$Y77)*1.08 -> 35.934322 | U77: =(19.32*$Y77)*1.08 -> 16.490525 | V77: =(21.73*$Y77)*1.08 -> 18.547573 | W77: =(26.07*$Y77)*1.08 -> 22.251966 | Y77: 0.79032114
B78: France | C78: Paris | D78: EMEA | E78: =(221.26*$Y78)*1.08 -> 200.80867 | F78: =(310.41*$Y78)*1.08 -> 281.71843 | G78: =(364.87*$Y78)*1.08 -> 331.14462 | H78: =(176.83*$Y78)*1.08 -> 160.48539 | I78: =(308.58*$Y78)*1.08 -> 280.05757 | J78: =(453.13*$Y78)*1.08 -> 411.24664 | K78: =(207.98*$Y78)*1.08 -> 188.75615 | L78: =(233.85*$Y78)*1.08 -> 212.23496 | M78: =(280.64*$Y78)*1.08 -> 254.7001 | O78: =(20.56*$Y78)*1.08 -> 18.659614 | P78: =(28.84*$Y78)*1.08 -> 26.174284 | Q78: =(33.93*$Y78)*1.08 -> 30.793809 | R78: =(16.43*$Y78)*1.08 -> 14.911355 | S78: =(28.67*$Y78)*1.08 -> 26.019997 | T78: =(42.1*$Y78)*1.08 -> 38.208646 | U78: =(19.32*$Y78)*1.08 -> 17.534229 | V78: =(21.73*$Y78)*1.08 -> 19.72147 | W78: =(26.07*$Y78)*1.08 -> 23.660318 | Y78: 0.84034146
A79: ? | B79: Germany | C79: Berlin | D79: EMEA
B80: Germany | C80: Cologne | D80: EMEA | E80: =(221.26*$Y80)*1.08 -> 186.02714 | F80: =(310.41*$Y80)*1.08 -> 260.98113 | G80: =(364.87*$Y80)*1.08 -> 306.76906 | H80: =(176.83*$Y80)*1.08 -> 148.67206 | I80: =(308.58*$Y80)*1.08 -> 259.44253 | J80: =(453.13*$Y80)*1.08 -> 380.97477 | K80: =(207.98*$Y80)*1.08 -> 174.86181 | L80: =(233.85*$Y80)*1.08 -> 196.61234 | M80: =(280.64*$Y80)*1.08 -> 235.95162 | O80: =(20.56*$Y80)*1.08 -> 17.28608 | P80: =(28.84*$Y80)*1.08 -> 24.247594 | Q80: =(33.93*$Y80)*1.08 -> 28.527076 | R80: =(16.43*$Y80)*1.08 -> 13.81373 | S80: =(28.67*$Y80)*1.08 -> 24.104665 | T80: =(42.1*$Y80)*1.08 -> 35.396107 | U80: =(19.32*$Y80)*1.08 -> 16.243534 | V80: =(21.73*$Y80)*1.08 -> 18.269772 | W80: =(26.07*$Y80)*1.08 -> 21.918682 | Y80: 0.77848392
A81: ? | B81: Germany | C81: Frankfurt | D81: EMEA
A82: ? | B82: Germany | C82: Hamburg | D82: EMEA
A83: ? | B83: Germany | C83: Munich | D83: EMEA
A84: ? | B84: Germany | C84: Stuttgart | D84: EMEA
B85: Ghana | C85: Accra | D85: EMEA | E85: =(221.26*$Y85)*1.08 -> 145.71067 | F85: =(310.41*$Y85)*1.08 -> 204.42036 | G85: =(364.87*$Y85)*1.08 -> 240.28497 | H85: =(176.83*$Y85)*1.08 -> 116.45131 | I85: =(308.58*$Y85)*1.08 -> 203.21521 | J85: =(453.13*$Y85)*1.08 -> 298.40855 | K85: =(207.98*$Y85)*1.08 -> 136.96513 | L85: =(233.85*$Y85)*1.08 -> 154.00181 | M85: =(280.64*$Y85)*1.08 -> 184.81534 | O85: =(20.56*$Y85)*1.08 -> 13.539778 | P85: =(28.84*$Y85)*1.08 -> 18.992568 | Q85: =(33.93*$Y85)*1.08 -> 22.344585 | R85: =(16.43*$Y85)*1.08 -> 10.819969 | S85: =(28.67*$Y85)*1.08 -> 18.880615 | T85: =(42.1*$Y85)*1.08 -> 27.724935 | U85: =(19.32*$Y85)*1.08 -> 12.723177 | V85: =(21.73*$Y85)*1.08 -> 14.310281 | W85: =(26.07*$Y85)*1.08 -> 17.168386 | Y85: 0.60976808
B86: Hungary | C86: Budapest | D86: EMEA | E86: =(221.26*$Y86)*1.08 -> 148.30746 | F86: =(310.41*$Y86)*1.08 -> 208.06345 | G86: =(364.87*$Y86)*1.08 -> 244.56722 | H86: =(176.83*$Y86)*1.08 -> 118.52666 | I86: =(308.58*$Y86)*1.08 -> 206.83683 | J86: =(453.13*$Y86)*1.08 -> 303.72666 | K86: =(207.98*$Y86)*1.08 -> 139.40606 | L86: =(233.85*$Y86)*1.08 -> 156.74636 | M86: =(280.64*$Y86)*1.08 -> 188.10904 | O86: =(20.56*$Y86)*1.08 -> 13.781078 | P86: =(28.84*$Y86)*1.08 -> 19.331046 | Q86: =(33.93*$Y86)*1.08 -> 22.742801 | R86: =(16.43*$Y86)*1.08 -> 11.012798 | S86: =(28.67*$Y86)*1.08 -> 19.217097 | T86: =(42.1*$Y86)*1.08 -> 28.219037 | U86: =(19.32*$Y86)*1.08 -> 12.949924 | V86: =(21.73*$Y86)*1.08 -> 14.565313 | W86: =(26.07*$Y86)*1.08 -> 17.474354 | Y86: 0.6206351
B87: Ireland | C87: Dublin | D87: EMEA | E87: =(221.26*$Y87)*1.08 -> 175.95322 | F87: =(310.41*$Y87)*1.08 -> 246.84823 | G87: =(364.87*$Y87)*1.08 -> 290.15662 | H87: =(176.83*$Y87)*1.08 -> 140.62103 | I87: =(308.58*$Y87)*1.08 -> 245.39296 | J87: =(453.13*$Y87)*1.08 -> 360.34387 | K87: =(207.98*$Y87)*1.08 -> 165.39253 | L87: =(233.85*$Y87)*1.08 -> 185.96521 | M87: =(280.64*$Y87)*1.08 -> 223.17415 | O87: =(20.56*$Y87)*1.08 -> 16.349988 | P87: =(28.84*$Y87)*1.08 -> 22.934516 | Q87: =(33.93*$Y87)*1.08 -> 26.982251 | R87: =(16.43*$Y87)*1.08 -> 13.065676 | S87: =(28.67*$Y87)*1.08 -> 22.799326 | T87: =(42.1*$Y87)*1.08 -> 33.479304 | U87: =(19.32*$Y87)*1.08 -> 15.363899 | V87: =(21.73*$Y87)*1.08 -> 17.28041 | W87: =(26.07*$Y87)*1.08 -> 20.731721 | Y87: 0.73632673
B88: Israel | C88: Tel Aviv | D88: EMEA | E88: =(221.26*$Y88)*1.08 -> 178.75836 | F88: =(310.41*$Y88)*1.08 -> 250.78361 | G88: =(364.87*$Y88)*1.08 -> 294.78244 | H88: =(176.83*$Y88)*1.08 -> 142.86288 | I88: =(308.58*$Y88)*1.08 -> 249.30514 | J88: =(453.13*$Y88)*1.08 -> 366.08865 | K88: =(207.98*$Y88)*1.08 -> 168.0293 | L88: =(233.85*$Y88)*1.08 -> 188.92996 | M88: =(280.64*$Y88)*1.08 -> 226.73211 | O88: =(20.56*$Y88)*1.08 -> 16.610647 | P88: =(28.84*$Y88)*1.08 -> 23.300149 | Q88: =(33.93*$Y88)*1.08 -> 27.412416 | R88: =(16.43*$Y88)*1.08 -> 13.273976 | S88: =(28.67*$Y88)*1.08 -> 23.162805 | T88: =(42.1*$Y88)*1.08 -> 34.013048 | U88: =(19.32*$Y88)*1.08 -> 15.608838 | V88: =(21.73*$Y88)*1.08 -> 17.555903 | W88: =(26.07*$Y88)*1.08 -> 21.062236 | Y88: 0.74806562
B89: Italy | C89: Rome | D89: EMEA | E89: =(221.26*$Y89)*1.08 -> 116.90696 | F89: =(310.41*$Y89)*1.08 -> 164.01108 | G89: =(364.87*$Y89)*1.08 -> 192.78606 | H89: =(176.83*$Y89)*1.08 -> 93.431521 | I89: =(308.58*$Y89)*1.08 -> 163.04416 | J89: =(453.13*$Y89)*1.08 -> 239.41992 | K89: =(207.98*$Y89)*1.08 -> 109.89022 | L89: =(233.85*$Y89)*1.08 -> 123.55913 | M89: =(280.64*$Y89)*1.08 -> 148.28152 | O89: =(20.56*$Y89)*1.08 -> 10.86327 | P89: =(28.84*$Y89)*1.08 -> 15.238167 | Q89: =(33.93*$Y89)*1.08 -> 17.927566 | R89: =(16.43*$Y89)*1.08 -> 8.6811055 | S89: =(28.67*$Y89)*1.08 -> 15.148344 | T89: =(42.1*$Y89)*1.08 -> 22.244342 | U89: =(19.32*$Y89)*1.08 -> 10.208092 | V89: =(21.73*$Y89)*1.08 -> 11.481462 | W89: =(26.07*$Y89)*1.08 -> 13.774584 | Y89: 0.48923072
B90: Kenya | C90: Nairobi | D90: EMEA | E90: =(221.26*$Y90)*1.08 -> 113.91317 | F90: =(310.41*$Y90)*1.08 -> 159.81103 | G90: =(364.87*$Y90)*1.08 -> 187.84914 | H90: =(176.83*$Y90)*1.08 -> 91.038899 | I90: =(308.58*$Y90)*1.08 -> 158.86888 | J90: =(453.13*$Y90)*1.08 -> 233.28879 | K90: =(207.98*$Y90)*1.08 -> 107.07612 | L90: =(233.85*$Y90)*1.08 -> 120.39499 | M90: =(280.64*$Y90)*1.08 -> 144.48429 | O90: =(20.56*$Y90)*1.08 -> 10.58508 | P90: =(28.84*$Y90)*1.08 -> 14.847943 | Q90: =(33.93*$Y90)*1.08 -> 17.468472 | R90: =(16.43*$Y90)*1.08 -> 8.4587972 | S90: =(28.67*$Y90)*1.08 -> 14.760421 | T90: =(42.1*$Y90)*1.08 -> 21.674702 | U90: =(19.32*$Y90)*1.08 -> 9.9466805 | V90: =(21.73*$Y90)*1.08 -> 11.187441 | W90: =(26.07*$Y90)*1.08 -> 13.421841 | Y90: 0.47670235
B91: Luxembourg | C91: Luxembourg | D91: EMEA | E91: =(221.26*$Y91)*1.08 -> 154.08951 | F91: =(310.41*$Y91)*1.08 -> 216.1752 | G91: =(364.87*$Y91)*1.08 -> 254.10214 | H91: =(176.83*$Y91)*1.08 -> 123.14765 | I91: =(308.58*$Y91)*1.08 -> 214.90075 | J91: =(453.13*$Y91)*1.08 -> 315.56802 | K91: =(207.98*$Y91)*1.08 -> 144.84108 | L91: =(233.85*$Y91)*1.08 -> 162.85742 | M91: =(280.64*$Y91)*1.08 -> 195.44283 | O91: =(20.56*$Y91)*1.08 -> 14.31836 | P91: =(28.84*$Y91)*1.08 -> 20.084703 | Q91: =(33.93*$Y91)*1.08 -> 23.629472 | R91: =(16.43*$Y91)*1.08 -> 11.442152 | S91: =(28.67*$Y91)*1.08 -> 19.966312 | T91: =(42.1*$Y91)*1.08 -> 29.31921 | U91: =(19.32*$Y91)*1.08 -> 13.454801 | V91: =(21.73*$Y91)*1.08 -> 15.133169 | W91: =(26.07*$Y91)*1.08 -> 18.155625 | Y91: 0.64483175
B92: Morocco | C92: Casablanca | D92: EMEA | E92: =(221.26*$Y92)*1.08 -> 188.46287 | F92: =(310.41*$Y92)*1.08 -> 264.39826 | G92: =(364.87*$Y92)*1.08 -> 310.78571 | H92: =(176.83*$Y92)*1.08 -> 150.61868 | I92: =(308.58*$Y92)*1.08 -> 262.83951 | J92: =(453.13*$Y92)*1.08 -> 385.96302 | K92: =(207.98*$Y92)*1.08 -> 177.15135 | L92: =(233.85*$Y92)*1.08 -> 199.18666 | M92: =(280.64*$Y92)*1.08 -> 239.04103 | O92: =(20.56*$Y92)*1.08 -> 17.512413 | P92: =(28.84*$Y92)*1.08 -> 24.565077 | Q92: =(33.93*$Y92)*1.08 -> 28.900592 | R92: =(16.43*$Y92)*1.08 -> 13.994599 | S92: =(28.67*$Y92)*1.08 -> 24.420276 | T92: =(42.1*$Y92)*1.08 -> 35.859562 | U92: =(19.32*$Y92)*1.08 -> 16.456217 | V92: =(21.73*$Y92)*1.08 -> 18.508985 | W92: =(26.07*$Y92)*1.08 -> 22.205672 | Y92: 0.78867691
B93: Netherlands | C93: Amsterdam | D93: EMEA | E93: =(221.26*$Y93)*1.08 -> 114.80852 | F93: =(310.41*$Y93)*1.08 -> 161.06713 | G93: =(364.87*$Y93)*1.08 -> 189.32561 | H93: =(176.83*$Y93)*1.08 -> 91.754453 | I93: =(308.58*$Y93)*1.08 -> 160.11757 | J93: =(453.13*$Y93)*1.08 -> 235.12241 | K93: =(207.98*$Y93)*1.08 -> 107.91772 | L93: =(233.85*$Y93)*1.08 -> 121.34128 | M93: =(280.64*$Y93)*1.08 -> 145.61992 | O93: =(20.56*$Y93)*1.08 -> 10.668278 | P93: =(28.84*$Y93)*1.08 -> 14.964646 | Q93: =(33.93*$Y93)*1.08 -> 17.605772 | R93: =(16.43*$Y93)*1.08 -> 8.5252823 | S93: =(28.67*$Y93)*1.08 -> 14.876436 | T93: =(42.1*$Y93)*1.08 -> 21.845063 | U93: =(19.32*$Y93)*1.08 -> 10.02486 | V93: =(21.73*$Y93)*1.08 -> 11.275373 | W93: =(26.07*$Y93)*1.08 -> 13.527335 | Y93: 0.48044917
B94: Nigeria | C94: Abuja | D94: EMEA | E94: =(221.26*$Y94)*1.08 -> 147.06016 | F94: =(310.41*$Y94)*1.08 -> 206.31359 | G94: =(364.87*$Y94)*1.08 -> 242.51036 | H94: =(176.83*$Y94)*1.08 -> 117.52982 | I94: =(308.58*$Y94)*1.08 -> 205.09729 | J94: =(453.13*$Y94)*1.08 -> 301.17225 | K94: =(207.98*$Y94)*1.08 -> 138.23363 | L94: =(233.85*$Y94)*1.08 -> 155.42809 | M94: =(280.64*$Y94)*1.08 -> 186.527 | O94: =(20.56*$Y94)*1.08 -> 13.665177 | P94: =(28.84*$Y94)*1.08 -> 19.168468 | Q94: =(33.93*$Y94)*1.08 -> 22.551529 | R94: =(16.43*$Y94)*1.08 -> 10.920178 | S94: =(28.67*$Y94)*1.08 -> 19.055477 | T94: =(42.1*$Y94)*1.08 -> 27.981709 | U94: =(19.32*$Y94)*1.08 -> 12.841012 | V94: =(21.73*$Y94)*1.08 -> 14.442816 | W94: =(26.07*$Y94)*1.08 -> 17.327391 | Y94: 0.61541543
B95: Norway | C95: Oslo | D95: EMEA | E95: =(221.26*$Y95)*1.08 -> 190.65575 | F95: =(310.41*$Y95)*1.08 -> 267.47469 | G95: =(364.87*$Y95)*1.08 -> 314.40189 | H95: =(176.83*$Y95)*1.08 -> 152.37122 | I95: =(308.58*$Y95)*1.08 -> 265.89782 | J95: =(453.13*$Y95)*1.08 -> 390.45394 | K95: =(207.98*$Y95)*1.08 -> 179.21261 | L95: =(233.85*$Y95)*1.08 -> 201.50432 | M95: =(280.64*$Y95)*1.08 -> 241.82242 | O95: =(20.56*$Y95)*1.08 -> 17.716181 | P95: =(28.84*$Y95)*1.08 -> 24.850907 | Q95: =(33.93*$Y95)*1.08 -> 29.236869 | R95: =(16.43*$Y95)*1.08 -> 14.157434 | S95: =(28.67*$Y95)*1.08 -> 24.704422 | T95: =(42.1*$Y95)*1.08 -> 36.27681 | U95: =(19.32*$Y95)*1.08 -> 16.647695 | V95: =(21.73*$Y95)*1.08 -> 18.724349 | W95: =(26.07*$Y95)*1.08 -> 22.464048 | Y95: 0.79785366
B96: Poland | C96: Warsaw | D96: EMEA | E96: =(221.26*$Y96)*1.08 -> 153.05091 | F96: =(310.41*$Y96)*1.08 -> 214.71813 | G96: =(364.87*$Y96)*1.08 -> 252.38944 | H96: =(176.83*$Y96)*1.08 -> 122.3176 | I96: =(308.58*$Y96)*1.08 -> 213.45228 | J96: =(453.13*$Y96)*1.08 -> 313.44102 | K96: =(207.98*$Y96)*1.08 -> 143.86481 | L96: =(233.85*$Y96)*1.08 -> 161.75972 | M96: =(280.64*$Y96)*1.08 -> 194.1255 | O96: =(20.56*$Y96)*1.08 -> 14.221851 | P96: =(28.84*$Y96)*1.08 -> 19.949328 | Q96: =(33.93*$Y96)*1.08 -> 23.470205 | R96: =(16.43*$Y96)*1.08 -> 11.36503 | S96: =(28.67*$Y96)*1.08 -> 19.831735 | T96: =(42.1*$Y96)*1.08 -> 29.121592 | U96: =(19.32*$Y96)*1.08 -> 13.364113 | V96: =(21.73*$Y96)*1.08 -> 15.031168 | W96: =(26.07*$Y96)*1.08 -> 18.033252 | Y96: 0.64048544
... B108: Turkey | C108: Istanbul | D108: EMEA | E108: =(221.26*$Y108)*1.08 -> 166.64019 | F108: =(310.41*$Y108)*1.08 -> 233.78279 | G108: =(364.87*$Y108)*1.08 -> 274.7989 | H108: =(176.83*$Y108)*1.08 -> 133.17809 | I108: =(308.58*$Y108)*1.08 -> 232.40454 | J108: =(453.13*$Y108)*1.08 -> 341.27121 | K108: =(207.98*$Y108)*1.08 -> 156.63846 | L108: =(233.85*$Y108)*1.08 -> 176.12225 | M108: =(280.64*$Y108)*1.08 -> 211.36176 | O108: =(20.56*$Y108)*1.08 -> 15.484599 | P108: =(28.84*$Y108)*1.08 -> 21.720614 | Q108: =(33.93*$Y108)*1.08 -> 25.554106 | R108: =(16.43*$Y108)*1.08 -> 12.374122 | S108: =(28.67*$Y108)*1.08 -> 21.59258 | T108: =(42.1*$Y108)*1.08 -> 31.707276 | U108: =(19.32*$Y108)*1.08 -> 14.550702 | V108: =(21.73*$Y108)*1.08 -> 16.365775 | W108: =(26.07*$Y108)*1.08 -> 19.634411 | Y108: 0.69735366
B109: UAE | C109: Abu Dhabi | D109: EMEA | E109: =(146.93*$AA109) -> 133.24317 | F109: =(202.05*$AA109) -> 183.22862 | G109: =(212.49*$AA109) -> 192.69612 | H109: =(109.98*$AA109) -> 99.735136 | I109: =(202.95*$AA109) -> 184.04479 | J109: =(217.97*$AA109) -> 197.66564 | K109: =(95.04*$AA109) -> 86.186827 | L109: =(131.26*$AA109) -> 119.03286 | M109: =(135.02*$AA109) -> 122.44261 | O109: =(13.65*$AA109) -> 12.378474 | P109: =(18.77*$AA109) -> 17.021536 | Q109: =(19.74*$AA109) -> 17.901178 | R109: =(10.22*$AA109) -> 9.2679859 | S109: =(18.85*$AA109) -> 17.094084 | T109: =(20.25*$AA109) -> 18.363671 | U109: =(8.83*$AA109) -> 8.0074672 | V109: =(12.19*$AA109) -> 11.054476 | W109: =(12.54*$AA109) -> 11.371873 | AA109: 0.90684793
B110: UAE | C110: Dubai | D110: EMEA | E110: =(146.93*$AA110) -> 133.24317 | F110: =(202.05*$AA110) -> 183.22862 | G110: =(212.49*$AA110) -> 192.69612 | H110: =(109.98*$AA110) -> 99.735136 | I110: =(202.95*$AA110) -> 184.04479 | J110: =(217.97*$AA110) -> 197.66564 | K110: =(95.04*$AA110) -> 86.186827 | L110: =(131.26*$AA110) -> 119.03286 | M110: =(135.02*$AA110) -> 122.44261 | O110: =(13.65*$AA110) -> 12.378474 | P110: =(18.77*$AA110) -> 17.021536 | Q110: =(19.74*$AA110) -> 17.901178 | R110: =(10.22*$AA110) -> 9.2679859 | S110: =(18.85*$AA110) -> 17.094084 | T110: =(20.25*$AA110) -> 18.363671 | U110: =(8.83*$AA110) -> 8.0074672 | V110: =(12.19*$AA110) -> 11.054476 | W110: =(12.54*$AA110) -> 11.371873 | AA110: 0.90684793
B111: Uganda | C111: Kampala | D111: EMEA | E111: =(221.26*$Y111)*1.08 -> 144.379 | F111: =(310.41*$Y111)*1.08 -> 202.55213 | G111: =(364.87*$Y111)*1.08 -> 238.08896 | H111: =(176.83*$Y111)*1.08 -> 115.38705 | I111: =(308.58*$Y111)*1.08 -> 201.358 | J111: =(453.13*$Y111)*1.08 -> 295.68135 | K111: =(207.98*$Y111)*1.08 -> 135.71339 | L111: =(233.85*$Y111)*1.08 -> 152.59436 | M111: =(280.64*$Y111)*1.08 -> 183.12628 | O111: =(20.56*$Y111)*1.08 -> 13.416036 | P111: =(28.84*$Y111)*1.08 -> 18.818992 | Q111: =(33.93*$Y111)*1.08 -> 22.140375 | R111: =(16.43*$Y111)*1.08 -> 10.721083 | S111: =(28.67*$Y111)*1.08 -> 18.708062 | T111: =(42.1*$Y111)*1.08 -> 27.471553 | U111: =(19.32*$Y111)*1.08 -> 12.606898 | V111: =(21.73*$Y111)*1.08 -> 14.179497 | W111: =(26.07*$Y111)*1.08 -> 17.011482 | Y111: 0.60419532
B112: China | C112: Hong Kong | D112: APAC | E112: =(146.93*$AA112) -> 95.5045 | F112: =(202.05*$AA112) -> 131.3325 | G112: =(212.49*$AA112) -> 138.1185 | H112: =(109.98*$AA112) -> 71.487 | I112: =(202.95*$AA112) -> 131.9175 | J112: =(217.97*$AA112) -> 141.6805 | K112: =(95.04*$AA112) -> 61.776 | L112: =(131.26*$AA112) -> 85.319 | M112: =(135.02*$AA112) -> 87.763 | O112: =(13.65*$AA112) -> 8.8725 | P112: =(18.77*$AA112) -> 12.2005 | Q112: =(19.74*$AA112) -> 12.831 | R112: =(10.22*$AA112) -> 6.643 | S112: =(18.85*$AA112) -> 12.2525 | T112: =(20.25*$AA112) -> 13.1625 | U112: =(8.83*$AA112) -> 5.7395 | V112: =(12.19*$AA112) -> 7.9235 | W112: =(12.54*$AA112) -> 8.151 | AA112: 0.65
B113: Australia | C113: Sydney | D113: APAC | E113: =(146.93*$AA113) -> 110.20482 | F113: =(202.05*$AA113) -> 151.54756 | G113: =(212.49*$AA113) -> 159.37808 | H113: =(109.98*$AA113) -> 82.490476 | I113: =(202.95*$AA113) -> 152.2226 | J113: =(217.97*$AA113) -> 163.48835 | K113: =(95.04*$AA113) -> 71.284732 | L113: =(131.26*$AA113) -> 98.451535 | M113: =(135.02*$AA113) -> 101.27172 | O113: =(13.65*$AA113) -> 10.23818 | P113: =(18.77*$AA113) -> 14.078435 | Q113: =(19.74*$AA113) -> 14.805983 | R113: =(10.22*$AA113) -> 7.6655089 | S113: =(18.85*$AA113) -> 14.138439 | T113: =(20.25*$AA113) -> 15.188508 | U113: =(8.83*$AA113) -> 6.6229396 | V113: =(12.19*$AA113) -> 9.1431069 | W113: =(12.54*$AA113) -> 9.4056244 | AA113: 0.75004979
A114: 0.02 | B114: Australia | C114: Brisbane | D114: APAC | E114: =E113*1.02 -> 112.40891 | F114: =F113*1.02 -> 154.57851 | G114: =G113*1.02 -> 162.56564 | H114: =H113*1.02 -> 84.140285 | I114: =I113*1.02 -> 155.26706 | J114: =J113*1.02 -> 166.75812 | K114: =K113*1.02 -> 72.710427 | L114: =L113*1.02 -> 100.42057 | M114: =M113*1.02 -> 103.29716 | O114: =(13.65*$AA114) -> 10.5105 | P114: =(18.77*$AA114) -> 14.4529 | Q114: =(19.74*$AA114) -> 15.1998 | R114: =(10.22*$AA114) -> 7.8694 | S114: =(18.85*$AA114) -> 14.5145 | T114: =(20.25*$AA114) -> 15.5925 | U114: =(8.83*$AA114) -> 6.7991 | V114: =(12.19*$AA114) -> 9.3863 | W114: =(12.54*$AA114) -> 9.6558 | AA114: 0.77
A115: 0.04 | B115: Australia | C115: Melborne | D115: APAC | E115: =E113*1.04 -> 114.61301 | F115: =F113*1.04 -> 157.60946 | G115: =G113*1.04 -> 165.7532 | H115: =H113*1.04 -> 85.790095 | I115: =I113*1.04 -> 158.31151 | J115: =J113*1.04 -> 170.02789 | K115: =K113*1.04 -> 74.136121 | L115: =L113*1.04 -> 102.3896 | M115: =M113*1.04 -> 105.32259 | O115: =(13.65*$AA115) -> 10.647 | P115: =(18.77*$AA115) -> 14.6406 | Q115: =(19.74*$AA115) -> 15.3972 | R115: =(10.22*$AA115) -> 7.9716 | S115: =(18.85*$AA115) -> 14.703 | T115: =(20.25*$AA115) -> 15.795 | U115: =(8.83*$AA115) -> 6.8874 | V115: =(12.19*$AA115) -> 9.5082 | W115: =(12.54*$AA115) -> 9.7812 | AA115: 0.78
A116: 0.03 | B116: Australia | C116: Perth | D116: APAC | E116: =E113*1.03 -> 113.51096 | F116: =F113*1.03 -> 156.09399 | G116: =G113*1.03 -> 164.15942 | H116: =H113*1.03 -> 84.96519 | I116: =I113*1.03 -> 156.78928 | J116: =J113*1.03 -> 168.393 | K116: =K113*1.03 -> 73.423274 | L116: =L113*1.03 -> 101.40508 | M116: =M113*1.03 -> 104.30987 | O116: =(13.65*$AA116) -> 10.5105 | P116: =(18.77*$AA116) -> 14.4529 | Q116: =(19.74*$AA116) -> 15.1998 | R116: =(10.22*$AA116) -> 7.8694 | S116: =(18.85*$AA116) -> 14.5145 | T116: =(20.25*$AA116) -> 15.5925 | U116: =(8.83*$AA116) -> 6.7991 | V116: =(12.19*$AA116) -> 9.3863 | W116: =(12.54*$AA116) -> 9.6558 | AA116: 0.77
B117: China | C117: Beijing | D117: APAC | E117: =(146.93*$AA117) -> 91.0966 | F117: =(202.05*$AA117) -> 125.271 | G117: =(212.49*$AA117) -> 131.7438 | H117: =(109.98*$AA117) -> 68.1876 | I117: =(202.95*$AA117) -> 125.829 | J117: =(217.97*$AA117) -> 135.1414 | K117: =(95.04*$AA117) -> 58.9248 | L117: =(131.26*$AA117) -> 81.3812 | M117: =(135.02*$AA117) -> 83.7124 | O117: =(13.65*$AA117) -> 8.463 | P117: =(18.77*$AA117) -> 11.6374 | Q117: =(19.74*$AA117) -> 12.2388 | R117: =(10.22*$AA117) -> 6.3364 | S117: =(18.85*$AA117) -> 11.687 | T117: =(20.25*$AA117) -> 12.555 | U117: =(8.83*$AA117) -> 5.4746 | V117: =(12.19*$AA117) -> 7.5578 | W117: =(12.54*$AA117) -> 7.7748 | AA117: 0.62
B118: China | C118: Guangzhou | D118: APAC | E118: =(146.93*$AA118) -> 88.158 | F118: =(202.05*$AA118) -> 121.23 | G118: =(212.49*$AA118) -> 127.494 | H118: =(109.98*$AA118) -> 65.988 | I118: =(202.95*$AA118) -> 121.77 | J118: =(217.97*$AA118) -> 130.782 | K118: =(95.04*$AA118) -> 57.024 | L118: =(131.26*$AA118) -> 78.756 | M118: =(135.02*$AA118) -> 81.012 | O118: =(13.65*$AA118) -> 8.19 | P118: =(18.77*$AA118) -> 11.262 | Q118: =(19.74*$AA118) -> 11.844 | R118: =(10.22*$AA118) -> 6.132 | S118: =(18.85*$AA118) -> 11.31 | T118: =(20.25*$AA118) -> 12.15 | U118: =(8.83*$AA118) -> 5.298 | V118: =(12.19*$AA118) -> 7.314 | W118: =(12.54*$AA118) -> 7.524 | AA118: 0.6
B119: China | C119: Shanghai | D119: APAC | E119: =(146.93*$AA119) -> 91.0966 | F119: =(202.05*$AA119) -> 125.271 | G119: =(212.49*$AA119) -> 131.7438 | H119: =(109.98*$AA119) -> 68.1876 | I119: =(202.95*$AA119) -> 125.829 | J119: =(217.97*$AA119) -> 135.1414 | K119: =(95.04*$AA119) -> 58.9248 | L119: =(131.26*$AA119) -> 81.3812 | M119: =(135.02*$AA119) -> 83.7124 | O119: =(13.65*$AA119) -> 8.463 | P119: =(18.77*$AA119) -> 11.6374 | Q119: =(19.74*$AA119) -> 12.2388 | R119: =(10.22*$AA119) -> 6.3364 | S119: =(18.85*$AA119) -> 11.687 | T119: =(20.25*$AA119) -> 12.555 | U119: =(8.83*$AA119) -> 5.4746 | V119: =(12.19*$AA119) -> 7.5578 | W119: =(12.54*$AA119) -> 7.7748 | AA119: 0.62
B120: India | C120: Bangalore | D120: APAC | E120: =(146.93*$AA120) -> 39.6711 | F120: =(202.05*$AA120) -> 54.5535 | G120: =(212.49*$AA120) -> 57.3723 | H120: =(109.98*$AA120) -> 29.6946 | I120: =(202.95*$AA120) -> 54.7965 | J120: =(217.97*$AA120) -> 58.8519 | K120: =(95.04*$AA120) -> 25.6608 | L120: =(131.26*$AA120) -> 35.4402 | M120: =(135.02*$AA120) -> 36.4554 | O120: =(13.65*$AA120) -> 3.6855 | P120: =(18.77*$AA120) -> 5.0679 | Q120: =(19.74*$AA120) -> 5.3298 | R120: =(10.22*$AA120) -> 2.7594 | S120: =(18.85*$AA120) -> 5.0895 | T120: =(20.25*$AA120) -> 5.4675 | U120: =(8.83*$AA120) -> 2.3841 | V120: =(12.19*$AA120) -> 3.2913 | W120: =(12.54*$AA120) -> 3.3858 | AA120: 0.27
A121: -0.01 | B121: India | C121: Chennai | D121: APAC | E121: =E120/1.01 -> 39.278317 | F121: =F120/1.01 -> 54.013366 | G121: =G120/1.01 -> 56.804257 | H121: =H120/1.01 -> 29.400594 | I121: =I120/1.01 -> 54.25396 | J121: =J120/1.01 -> 58.269208 | K121: =K120/1.01 -> 25.406733 | L121: =L120/1.01 -> 35.089307 | M121: =M120/1.01 -> 36.094455 | O121: =(13.65*$AA121) -> 3.6855 | P121: =(18.77*$AA121) -> 5.0679 | Q121: =(19.74*$AA121) -> 5.3298 | R121: =(10.22*$AA121) -> 2.7594 | S121: =(18.85*$AA121) -> 5.0895 | T121: =(20.25*$AA121) -> 5.4675 | U121: =(8.83*$AA121) -> 2.3841 | V121: =(12.19*$AA121) -> 3.2913 | W121: =(12.54*$AA121) -> 3.3858 | AA121: 0.27
A122: -0.01 | B122: India | C122: Hyderbad | D122: APAC | E122: =E120/1.01 -> 39.278317 | F122: =F120/1.01 -> 54.013366 | G122: =G120/1.01 -> 56.804257 | H122: =H120/1.01 -> 29.400594 | I122: =I120/1.01 -> 54.25396 | J122: =J120/1.01 -> 58.269208 | K122: =K120/1.01 -> 25.406733 | L122: =L120/1.01 -> 35.089307 | M122: =M120/1.01 -> 36.094455 | O122: =(13.65*$AA122) -> 3.6855 | P122: =(18.77*$AA122) -> 5.0679 | Q122: =(19.74*$AA122) -> 5.3298 | R122: =(10.22*$AA122) -> 2.7594 | S122: =(18.85*$AA122) -> 5.0895 | T122: =(20.25*$AA122) -> 5.4675 | U122: =(8.83*$AA122) -> 2.3841 | V122: =(12.19*$AA122) -> 3.2913 | W122: =(12.54*$AA122) -> 3.3858 | AA122: 0.27
A123: -0.02 | B123: India | C123: Kolkata | D123: APAC | E123: =E120/1.02 -> 38.893235 | F123: =F120/1.02 -> 53.483824 | G123: =G120/1.02 -> 56.247353 | H123: =H120/1.02 -> 29.112353 | I123: =I120/1.02 -> 53.722059 | J123: =J120/1.02 -> 57.697941 | K123: =K120/1.02 -> 25.157647 | L123: =L120/1.02 -> 34.745294 | M123: =M120/1.02 -> 35.740588 | O123: =(13.65*$AA123) -> 3.6855 | P123: =(18.77*$AA123) -> 5.0679 | Q123: =(19.74*$AA123) -> 5.3298 | R123: =(10.22*$AA123) -> 2.7594 | S123: =(18.85*$AA123) -> 5.0895 | T123: =(20.25*$AA123) -> 5.4675 | U123: =(8.83*$AA123) -> 2.3841 | V123: =(12.19*$AA123) -> 3.2913 | W123: =(12.54*$AA123) -> 3.3858 | AA123: 0.27
A124: 0.08 | B124: India | C124: Mumbai | D124: APAC | E124: =E120*1.08 -> 42.844788 | F124: =F120*1.08 -> 58.91778 | G124: =G120*1.08 -> 61.962084 | H124: =H120*1.08 -> 32.070168 | I124: =I120*1.08 -> 59.18022 | J124: =J120*1.08 -> 63.560052 | K124: =K120*1.08 -> 27.713664 | L124: =L120*1.08 -> 38.275416 | M124: =M120*1.08 -> 39.371832 | O124: =(13.65*$AA124) -> 4.095 | P124: =(18.77*$AA124) -> 5.631 | Q124: =(19.74*$AA124) -> 5.922 | R124: =(10.22*$AA124) -> 3.066 | S124: =(18.85*$AA124) -> 5.655 | T124: =(20.25*$AA124) -> 6.075 | U124: =(8.83*$AA124) -> 2.649 | V124: =(12.19*$AA124) -> 3.657 | W124: =(12.54*$AA124) -> 3.762 | AA124: 0.3
A125: 0.05 | B125: India | C125: New Delhi | D125: APAC | E125: =E120*1.05 -> 41.654655 | F125: =F120*1.05 -> 57.281175 | G125: =G120*1.05 -> 60.240915 | H125: =H120*1.05 -> 31.17933 | I125: =I120*1.05 -> 57.536325 | J125: =J120*1.05 -> 61.794495 | K125: =K120*1.05 -> 26.94384 | L125: =L120*1.05 -> 37.21221 | M125: =M120*1.05 -> 38.27817 | O125: =(13.65*$AA125) -> 3.9585 | P125: =(18.77*$AA125) -> 5.4433 | Q125: =(19.74*$AA125) -> 5.7246 | R125: =(10.22*$AA125) -> 2.9638 | S125: =(18.85*$AA125) -> 5.4665 | T125: =(20.25*$AA125) -> 5.8725 | U125: =(8.83*$AA125) -> 2.5607 | V125: =(12.19*$AA125) -> 3.5351 | W125: =(12.54*$AA125) -> 3.6366 | AA125: 0.29
A126: -0.01 | B126: India | C126: Pune | D126: APAC | E126: =E120/1.01 -> 39.278317 | F126: =F120/1.01 -> 54.013366 | G126: =G120/1.01 -> 56.804257 | H126: =H120/1.01 -> 29.400594 | I126: =I120/1.01 -> 54.25396 | J126: =J120/1.01 -> 58.269208 | K126: =K120/1.01 -> 25.406733 | L126: =L120/1.01 -> 35.089307 | M126: =M120/1.01 -> 36.094455 | O126: =(13.65*$AA126) -> 3.6855 | P126: =(18.77*$AA126) -> 5.0679 | Q126: =(19.74*$AA126) -> 5.3298 | R126: =(10.22*$AA126) -> 2.7594 | S126: =(18.85*$AA126) -> 5.0895 | T126: =(20.25*$AA126) -> 5.4675 | U126: =(8.83*$AA126) -> 2.3841 | V126: =(12.19*$AA126) -> 3.2913 | W126: =(12.54*$AA126) -> 3.3858 | AA126: 0.27
B127: Indonesia | C127: Jakarta | D127: APAC | E127: =(146.93*$AA127) -> 69.0571 | F127: =(202.05*$AA127) -> 94.9635 | G127: =(212.49*$AA127) -> 99.8703 | H127: =(109.98*$AA127) -> 51.6906 | I127: =(202.95*$AA127) -> 95.3865 | J127: =(217.97*$AA127) -> 102.4459 | K127: =(95.04*$AA127) -> 44.6688 | L127: =(131.26*$AA127) -> 61.6922 | M127: =(135.02*$AA127) -> 63.4594 | O127: =(13.65*$AA127) -> 6.4155 | P127: =(18.77*$AA127) -> 8.8219 | Q127: =(19.74*$AA127) -> 9.2778 | R127: =(10.22*$AA127) -> 4.8034 | S127: =(18.85*$AA127) -> 8.8595 | T127: =(20.25*$AA127) -> 9.5175 | U127: =(8.83*$AA127) -> 4.1501 | V127: =(12.19*$AA127) -> 5.7293 | W127: =(12.54*$AA127) -> 5.8938 | AA127: 0.47
B128: Japan | C128: Tokyo | D128: APAC | E128: =(146.93*$AA128) -> 157.84652 | F128: =(202.05*$AA128) -> 217.0618 | G128: =(212.49*$AA128) -> 228.27746 | H128: =(109.98*$AA128) -> 118.15123 | I128: =(202.95*$AA128) -> 218.02867 | J128: =(217.97*$AA128) -> 234.16461 | K128: =(95.04*$AA128) -> 102.10123 | L128: =(131.26*$AA128) -> 141.01228 | M128: =(135.02*$AA128) -> 145.05164 | O128: =(13.65*$AA128) -> 14.66416 | P128: =(18.77*$AA128) -> 20.164563 | Q128: =(19.74*$AA128) -> 21.206631 | R128: =(10.22*$AA128) -> 10.97932 | S128: =(18.85*$AA128) -> 20.250507 | T128: =(20.25*$AA128) -> 21.754523 | U128: =(8.83*$AA128) -> 9.4860464 | V128: =(12.19*$AA128) -> 13.095686 | W128: =(12.54*$AA128) -> 13.47169 | AA128: 1.0742974
B129: Malaysia | C129: Kuala Lumpur | D129: APAC | E129: =(146.93*$AA129) -> 68.851455 | F129: =(202.05*$AA129) -> 94.680708 | G129: =(212.49*$AA129) -> 99.572896 | H129: =(109.98*$AA129) -> 51.53667 | I129: =(202.95*$AA129) -> 95.102448 | J129: =(217.97*$AA129) -> 102.14083 | K129: =(95.04*$AA129) -> 44.535781 | L129: =(131.26*$AA129) -> 61.508487 | M129: =(135.02*$AA129) -> 63.270424 | O129: =(13.65*$AA129) -> 6.3963953 | P129: =(18.77*$AA129) -> 8.7956292 | Q129: =(19.74*$AA129) -> 9.2501716 | R129: =(10.22*$AA129) -> 4.7890959 | S129: =(18.85*$AA129) -> 8.8331173 | T129: =(20.25*$AA129) -> 9.4891578 | U129: =(8.83*$AA129) -> 4.1377414 | V129: =(12.19*$AA129) -> 5.7122387 | W129: =(12.54*$AA129) -> 5.8762488 | AA129: 0.46860039
B130: New Zealand | C130: Auckland | D130: APAC | E130: =(146.93*$AA130) -> 93.153411 | F130: =(202.05*$AA130) -> 128.09941 | G130: =(212.49*$AA130) -> 134.71836 | H130: =(109.98*$AA130) -> 69.727163 | I130: =(202.95*$AA130) -> 128.67001 | J130: =(217.97*$AA130) -> 138.19267 | K130: =(95.04*$AA130) -> 60.255225 | L130: =(131.26*$AA130) -> 83.218653 | M130: =(135.02*$AA130) -> 85.602488 | O130: =(13.65*$AA130) -> 8.6540806 | P130: =(18.77*$AA130) -> 11.900153 | Q130: =(19.74*$AA130) -> 12.515132 | R130: =(10.22*$AA130) -> 6.4794655 | S130: =(18.85*$AA130) -> 11.950873 | T130: =(20.25*$AA130) -> 12.838471 | U130: =(8.83*$AA130) -> 5.5982074 | V130: =(12.19*$AA130) -> 7.7284426 | W130: =(12.54*$AA130) -> 7.9503421 | AA130: 0.63399858
B131: Pakistan | C131: Karachi | D131: APAC | E131: =(146.93*$AA131) -> 51.4255 | F131: =(202.05*$AA131) -> 70.7175 | G131: =(212.49*$AA131) -> 74.3715 | H131: =(109.98*$AA131) -> 38.493 | I131: =(202.95*$AA131) -> 71.0325 | J131: =(217.97*$AA131) -> 76.2895 | K131: =(95.04*$AA131) -> 33.264 | L131: =(131.26*$AA131) -> 45.941 | M131: =(135.02*$AA131) -> 47.257 | O131: =(13.65*$AA131) -> 4.7775 | P131: =(18.77*$AA131) -> 6.5695 | Q131: =(19.74*$AA131) -> 6.909 | R131: =(10.22*$AA131) -> 3.577 | S131: =(18.85*$AA131) -> 6.5975 | T131: =(20.25*$AA131) -> 7.0875 | U131: =(8.83*$AA131) -> 3.0905 | V131: =(12.19*$AA131) -> 4.2665 | W131: =(12.54*$AA131) -> 4.389 | AA131: 0.35
B132: Philippines | C132: Manila | D132: APAC | E132: =(146.93*$AA132) -> 73.465 | F132: =(202.05*$AA132) -> 101.025 | G132: =(212.49*$AA132) -> 106.245 | H132: =(109.98*$AA132) -> 54.99 | I132: =(202.95*$AA132) -> 101.475 | J132: =(217.97*$AA132) -> 108.985 | K132: =(95.04*$AA132) -> 47.52 | L132: =(131.26*$AA132) -> 65.63 | M132: =(135.02*$AA132) -> 67.51 | O132: =(13.65*$AA132) -> 6.825 | P132: =(18.77*$AA132) -> 9.385 | Q132: =(19.74*$AA132) -> 9.87 | R132: =(10.22*$AA132) -> 5.11 | S132: =(18.85*$AA132) -> 9.425 | T132: =(20.25*$AA132) -> 10.125 | U132: =(8.83*$AA132) -> 4.415 | V132: =(12.19*$AA132) -> 6.095 | W132: =(12.54*$AA132) -> 6.27 | AA132: 0.5
B133: Singapore | C133: Singapore | D133: APAC | E133: =(146.93*$AA133) -> 132.237 | F133: =(202.05*$AA133) -> 181.845 | G133: =(212.49*$AA133) -> 191.241 | H133: =(109.98*$AA133) -> 98.982 | I133: =(202.95*$AA133) -> 182.655 | J133: =(217.97*$AA133) -> 196.173 | K133: =(95.04*$AA133) -> 85.536 | L133: =(131.26*$AA133) -> 118.134 | M133: =(135.02*$AA133) -> 121.518 | O133: =(13.65*$AA133) -> 12.285 | P133: =(18.77*$AA133) -> 16.893 | Q133: =(19.74*$AA133) -> 17.766 | R133: =(10.22*$AA133) -> 9.198 | S133: =(18.85*$AA133) -> 16.965 | T133: =(20.25*$AA133) -> 18.225 | U133: =(8.83*$AA133) -> 7.947 | V133: =(12.19*$AA133) -> 10.971 | W133: =(12.54*$AA133) -> 11.286 | AA133: 0.9
B134: South Korea | C134: Seoul | D134: APAC | E134: =(146.93*$AA134) -> 88.158 | F134: =(202.05*$AA134) -> 121.23 | G134: =(212.49*$AA134) -> 127.494 | H134: =(109.98*$AA134) -> 65.988 | I134: =(202.95*$AA134) -> 121.77 | J134: =(217.97*$AA134) -> 130.782 | K134: =(95.04*$AA134) -> 57.024 | L134: =(131.26*$AA134) -> 78.756 | M134: =(135.02*$AA134) -> 81.012 | O134: =(13.65*$AA134) -> 8.19 | P134: =(18.77*$AA134) -> 11.262 | Q134: =(19.74*$AA134) -> 11.844 | R134: =(10.22*$AA134) -> 6.132 | S134: =(18.85*$AA134) -> 11.31 | T134: =(20.25*$AA134) -> 12.15 | U134: =(8.83*$AA134) -> 5.298 | V134: =(12.19*$AA134) -> 7.314 | W134: =(12.54*$AA134) -> 7.524 | AA134: 0.6
B135: Taiwan | C135: Taipei | D135: APAC | E135: =(146.93*$AA135) -> 76.4036 | F135: =(202.05*$AA135) -> 105.066 | G135: =(212.49*$AA135) -> 110.4948 | H135: =(109.98*$AA135) -> 57.1896 | I135: =(202.95*$AA135) -> 105.534 | J135: =(217.97*$AA135) -> 113.3444 | K135: =(95.04*$AA135) -> 49.4208 | L135: =(131.26*$AA135) -> 68.2552 | M135: =(135.02*$AA135) -> 70.2104 | O135: =(13.65*$AA135) -> 7.098 | P135: =(18.77*$AA135) -> 9.7604 | Q135: =(19.74*$AA135) -> 10.2648 | R135: =(10.22*$AA135) -> 5.3144 | S135: =(18.85*$AA135) -> 9.802 | T135: =(20.25*$AA135) -> 10.53 | U135: =(8.83*$AA135) -> 4.5916 | V135: =(12.19*$AA135) -> 6.3388 | W135: =(12.54*$AA135) -> 6.5208 | AA135: 0.52
B136: Thailand | C136: Bangkok | D136: APAC | E136: =(146.93*$AA136) -> 46.22931 | F136: =(202.05*$AA136) -> 63.571988 | G136: =(212.49*$AA136) -> 66.856777 | H136: =(109.98*$AA136) -> 34.60355 | I136: =(202.95*$AA136) -> 63.855159 | J136: =(217.97*$AA136) -> 68.580976 | K136: =(95.04*$AA136) -> 29.902904 | L136: =(131.26*$AA136) -> 41.298981 | M136: =(135.02*$AA136) -> 42.482008 | O136: =(13.65*$AA136) -> 4.2947668 | P136: =(18.77*$AA136) -> 5.9056977 | Q136: =(19.74*$AA136) -> 6.2108935 | R136: =(10.22*$AA136) -> 3.215569 | S136: =(18.85*$AA136) -> 5.9308685 | T136: =(20.25*$AA136) -> 6.3713574 | U136: =(8.83*$AA136) -> 2.7782264 | V136: =(12.19*$AA136) -> 3.8353998 | W136: =(12.54*$AA136) -> 3.945522 | AA136: 0.31463493
B137: Vietnam | C137: Hanoi | D137: APAC | E137: =(146.93*$AA137) -> 54.380652 | F137: =(202.05*$AA137) -> 74.781262 | G137: =(212.49*$AA137) -> 78.645238 | H137: =(109.98*$AA137) -> 40.70499 | I137: =(202.95*$AA137) -> 75.114363 | J137: =(217.97*$AA137) -> 80.673455 | K137: =(95.04*$AA137) -> 35.175507 | L137: =(131.26*$AA137) -> 48.580987 | M137: =(135.02*$AA137) -> 49.972611 | O137: =(13.65*$AA137) -> 5.0520377 | P137: =(18.77*$AA137) -> 6.9470145 | Q137: =(19.74*$AA137) -> 7.3060238 | R137: =(10.22*$AA137) -> 3.7825513 | S137: =(18.85*$AA137) -> 6.9766236 | T137: =(20.25*$AA137) -> 7.4947813 | U137: =(8.83*$AA137) -> 3.2680947 | V137: =(12.19*$AA137) -> 4.5116733 | W137: =(12.54*$AA137) -> 4.6412127 | AA137: 0.37011266
B138: United Kingdom | C138: London | D138: EMEA | E138: =(221.26*$Y138)*1.08 -> 238.9608 | F138: =(310.41*$Y138)*1.08 -> 335.2428 | G138: =(364.87*$Y138)*1.08 -> 394.0596 | H138: =(176.83*$Y138)*1.08 -> 190.9764 | I138: =(308.58*$Y138)*1.08 -> 333.2664 | J138: =(453.13*$Y138)*1.08 -> 489.3804 | K138: =(207.98*$Y138)*1.08 -> 224.6184 | L138: =(233.85*$Y138)*1.08 -> 252.558 | M138: =(280.64*$Y138)*1.08 -> 303.0912 | O138: =(20.56*$Y138)*1.08 -> 22.2048 | P138: =(28.84*$Y138)*1.08 -> 31.1472 | Q138: =(33.93*$Y138)*1.08 -> 36.6444 | R138: =(16.43*$Y138)*1.08 -> 17.7444 | S138: =(28.67*$Y138)*1.08 -> 30.9636 | T138: =(42.1*$Y138)*1.08 -> 45.468 | U138: =(19.32*$Y138)*1.08 -> 20.8656 | V138: =(21.73*$Y138)*1.08 -> 23.4684 | W138: =(26.07*$Y138)*1.08 -> 28.1556 | Y138: 1
B139: Zimbabwe | C139: Harare | D139: EMEA | E139: =(221.26*$Y139)*1.08 -> 144.379 | F139: =(310.41*$Y139)*1.08 -> 202.55213 | G139: =(364.87*$Y139)*1.08 -> 238.08896 | H139: =(176.83*$Y139)*1.08 -> 115.38705 | I139: =(308.58*$Y139)*1.08 -> 201.358 | J139: =(453.13*$Y139)*1.08 -> 295.68135 | K139: =(207.98*$Y139)*1.08 -> 135.71339 | L139: =(233.85*$Y139)*1.08 -> 152.59436 | M139: =(280.64*$Y139)*1.08 -> 183.12628 | O139: =(20.56*$Y139)*1.08 -> 13.416036 | P139: =(28.84*$Y139)*1.08 -> 18.818992 | Q139: =(33.93*$Y139)*1.08 -> 22.140375 | R139: =(16.43*$Y139)*1.08 -> 10.721083 | S139: =(28.67*$Y139)*1.08 -> 18.708062 | T139: =(42.1*$Y139)*1.08 -> 27.471553 | U139: =(19.32*$Y139)*1.08 -> 12.606898 | V139: =(21.73*$Y139)*1.08 -> 14.179497 | W139: =(26.07*$Y139)*1.08 -> 17.011482 | Y139: 0.60419532

Sheet TECH
A1: a | E1: TECH $/M2 | O1: TECH $/SQFT | Y1: LOCATION FACTOR | AA1: INFLATION 2022 -2023
E2: Activity | H2: Team | K2: Event | O2: Activity | R2: Team | U2: Event | Y2: BASED OFF LONDON
E3: Low | F3: Medium | G3: High | H3: Low | I3: Medium | J3: High | K3: Low | L3: Medium | M3: High | O3: Low | P3: Medium | Q3: High | R3: Low | S3: Medium | T3: High | U3: Low | V3: Medium | W3: High
B4: COUNTRY | C4: CITY | D4: REGION
B5: United States | C5: Cincinnati | D5: AMERICAS | E5: =(331.44*$Y5)*$AA5 -> 412.61379 | F5: =(339.03*$Y5)*$AA5 -> 422.06268 | G5: =(371.99*$Y5)*$AA5 -> 463.09499 | H5: =(331.44*$Y5)*$AA5 -> 412.61379 | I5: =(339.03*$Y5)*$AA5 -> 422.06268 | J5: =(371.99*$Y5)*$AA5 -> 463.09499 | K5: =(331.44*$Y5)*$AA5 -> 412.61379 | L5: =(339.03*$Y5)*$AA5 -> 422.06268 | M5: =(371.99*$Y5)*$AA5 -> 463.09499 | O5: =(30.8*$Y5)*$AA5 -> 38.343304 | P5: =(31.5*$Y5)*$AA5 -> 39.214743 | Q5: =(34.6*$Y5)*$AA5 -> 43.073972 | R5: =(30.8*$Y5)*$AA5 -> 38.343304 | S5: =(31.5*$Y5)*$AA5 -> 39.214743 | T5: =(34.6*$Y5)*$AA5 -> 43.073972 | U5: =(30.8*$Y5)*$AA5 -> 38.343304 | V5: =(31.5*$Y5)*$AA5 -> 39.214743 | W5: =(34.6*$Y5)*$AA5 -> 43.073972 | Y5: 1.1580581 | AA5: 1.075
B6: United States | C6: Charlotte | D6: AMERICAS | E6: =(331.44*$Y6)*$AA6 -> 385.42588 | F6: =(339.03*$Y6)*$AA6 -> 394.25216 | G6: =(371.99*$Y6)*$AA6 -> 432.58078 | H6: =(331.44*$Y6)*$AA6 -> 385.42588 | I6: =(339.03*$Y6)*$AA6 -> 394.25216 | J6: =(371.99*$Y6)*$AA6 -> 432.58078 | K6: =(331.44*$Y6)*$AA6 -> 385.42588 | L6: =(339.03*$Y6)*$AA6 -> 394.25216 | M6: =(371.99*$Y6)*$AA6 -> 432.58078 | O6: =(30.8*$Y6)*$AA6 -> 35.816791 | P6: =(31.5*$Y6)*$AA6 -> 36.630809 | Q6: =(34.6*$Y6)*$AA6 -> 40.235745 | R6: =(30.8*$Y6)*$AA6 -> 35.816791 | S6: =(31.5*$Y6)*$AA6 -> 36.630809 | T6: =(34.6*$Y6)*$AA6 -> 40.235745 | U6: =(30.8*$Y6)*$AA6 -> 35.816791 | V6: =(31.5*$Y6)*$AA6 -> 36.630809 | W6: =(34.6*$Y6)*$AA6 -> 40.235745 | Y6: 1.0817515 | AA6: 1.075
B7: United States | C7: Charleston | D7: AMERICAS | E7: =(331.44*$Y7)*$AA7 -> 385.42588 | F7: =(339.03*$Y7)*$AA7 -> 394.25216 | G7: =(371.99*$Y7)*$AA7 -> 432.58078 | H7: =(331.44*$Y7)*$AA7 -> 385.42588 | I7: =(339.03*$Y7)*$AA7 -> 394.25216 | J7: =(371.99*$Y7)*$AA7 -> 432.58078 | K7: =(331.44*$Y7)*$AA7 -> 385.42588 | L7: =(339.03*$Y7)*$AA7 -> 394.25216 | M7: =(371.99*$Y7)*$AA7 -> 432.58078 | O7: =(30.8*$Y7)*$AA7 -> 35.816791 | P7: =(31.5*$Y7)*$AA7 -> 36.630809 | Q7: =(34.6*$Y7)*$AA7 -> 40.235745 | R7: =(30.8*$Y7)*$AA7 -> 35.816791 | S7: =(31.5*$Y7)*$AA7 -> 36.630809 | T7: =(34.6*$Y7)*$AA7 -> 40.235745 | U7: =(30.8*$Y7)*$AA7 -> 35.816791 | V7: =(31.5*$Y7)*$AA7 -> 36.630809 | W7: =(34.6*$Y7)*$AA7 -> 40.235745 | Y7: 1.0817515 | AA7: 1.075
B8: United States | C8: Chicago | D8: AMERICAS | E8: =(331.44*$Y8)*$AA8 -> 504.96594 | F8: =(339.03*$Y8)*$AA8 -> 516.5297 | G8: =(371.99*$Y8)*$AA8 -> 566.74596 | H8: =(331.44*$Y8)*$AA8 -> 504.96594 | I8: =(339.03*$Y8)*$AA8 -> 516.5297 | J8: =(371.99*$Y8)*$AA8 -> 566.74596 | K8: =(331.44*$Y8)*$AA8 -> 504.96594 | L8: =(339.03*$Y8)*$AA8 -> 516.5297 | M8: =(371.99*$Y8)*$AA8 -> 566.74596 | O8: =(30.8*$Y8)*$AA8 -> 46.925389 | P8: =(31.5*$Y8)*$AA8 -> 47.991876 | Q8: =(34.6*$Y8)*$AA8 -> 52.714886 | R8: =(30.8*$Y8)*$AA8 -> 46.925389 | S8: =(31.5*$Y8)*$AA8 -> 47.991876 | T8: =(34.6*$Y8)*$AA8 -> 52.714886 | U8: =(30.8*$Y8)*$AA8 -> 46.925389 | V8: =(31.5*$Y8)*$AA8 -> 47.991876 | W8: =(34.6*$Y8)*$AA8 -> 52.714886 | Y8: 1.4172573 | AA8: 1.075
B9: United States | C9: Cleveland | D9: AMERICAS | E9: =(331.44*$Y9)*$AA9 -> 400.21644 | F9: =(339.03*$Y9)*$AA9 -> 409.38142 | G9: =(371.99*$Y9)*$AA9 -> 449.18088 | H9: =(331.44*$Y9)*$AA9 -> 400.21644 | I9: =(339.03*$Y9)*$AA9 -> 409.38142 | J9: =(371.99*$Y9)*$AA9 -> 449.18088 | K9: =(331.44*$Y9)*$AA9 -> 400.21644 | L9: =(339.03*$Y9)*$AA9 -> 409.38142 | M9: =(371.99*$Y9)*$AA9 -> 449.18088 | O9: =(30.8*$Y9)*$AA9 -> 37.191245 | P9: =(31.5*$Y9)*$AA9 -> 38.0365 | Q9: =(34.6*$Y9)*$AA9 -> 41.779775 | R9: =(30.8*$Y9)*$AA9 -> 37.191245 | S9: =(31.5*$Y9)*$AA9 -> 38.0365 | T9: =(34.6*$Y9)*$AA9 -> 41.779775 | U9: =(30.8*$Y9)*$AA9 -> 37.191245 | V9: =(31.5*$Y9)*$AA9 -> 38.0365 | W9: =(34.6*$Y9)*$AA9 -> 41.779775 | Y9: 1.1232632 | AA9: 1.075
B10: United States | C10: Boston | D10: AMERICAS | E10: =(331.44*$Y10)*$AA10 -> 491.58783 | F10: =(339.03*$Y10)*$AA10 -> 502.84523 | G10: =(371.99*$Y10)*$AA10 -> 551.73111 | H10: =(331.44*$Y10)*$AA10 -> 491.58783 | I10: =(339.03*$Y10)*$AA10 -> 502.84523 | J10: =(371.99*$Y10)*$AA10 -> 551.73111 | K10: =(331.44*$Y10)*$AA10 -> 491.58783 | L10: =(339.03*$Y10)*$AA10 -> 502.84523 | M10: =(371.99*$Y10)*$AA10 -> 551.73111 | O10: =(30.8*$Y10)*$AA10 -> 45.682191 | P10: =(31.5*$Y10)*$AA10 -> 46.720422 | Q10: =(34.6*$Y10)*$AA10 -> 51.318305 | R10: =(30.8*$Y10)*$AA10 -> 45.682191 | S10: =(31.5*$Y10)*$AA10 -> 46.720422 | T10: =(34.6*$Y10)*$AA10 -> 51.318305 | U10: =(30.8*$Y10)*$AA10 -> 45.682191 | V10: =(31.5*$Y10)*$AA10 -> 46.720422 | W10: =(34.6*$Y10)*$AA10 -> 51.318305 | Y10: 1.3797098 | AA10: 1.075
B11: United States | C11: Baltimore | D11: AMERICAS | E11: =(331.44*$Y11)*$AA11 -> 401.92826 | F11: =(339.03*$Y11)*$AA11 -> 411.13244 | G11: =(371.99*$Y11)*$AA11 -> 451.10214 | H11: =(331.44*$Y11)*$AA11 -> 401.92826 | I11: =(339.03*$Y11)*$AA11 -> 411.13244 | J11: =(371.99*$Y11)*$AA11 -> 451.10214 | K11: =(331.44*$Y11)*$AA11 -> 401.92826 | L11: =(339.03*$Y11)*$AA11 -> 411.13244 | M11: =(371.99*$Y11)*$AA11 -> 451.10214 | O11: =(30.8*$Y11)*$AA11 -> 37.350321 | P11: =(31.5*$Y11)*$AA11 -> 38.199192 | Q11: =(34.6*$Y11)*$AA11 -> 41.958477 | R11: =(30.8*$Y11)*$AA11 -> 37.350321 | S11: =(31.5*$Y11)*$AA11 -> 38.199192 | T11: =(34.6*$Y11)*$AA11 -> 41.958477 | U11: =(30.8*$Y11)*$AA11 -> 37.350321 | V11: =(31.5*$Y11)*$AA11 -> 38.199192 | W11: =(34.6*$Y11)*$AA11 -> 41.958477 | Y11: 1.1280677 | AA11: 1.075
B12: United States | C12: Columbus | D12: AMERICAS | E12: =(331.44*$Y12)*$AA12 -> 391.00175 | F12: =(339.03*$Y12)*$AA12 -> 399.95572 | G12: =(371.99*$Y12)*$AA12 -> 438.83883 | H12: =(331.44*$Y12)*$AA12 -> 391.00175 | I12: =(339.03*$Y12)*$AA12 -> 399.95572 | J12: =(371.99*$Y12)*$AA12 -> 438.83883 | K12: =(331.44*$Y12)*$AA12 -> 391.00175 | L12: =(339.03*$Y12)*$AA12 -> 399.95572 | M12: =(371.99*$Y12)*$AA12 -> 438.83883 | O12: =(30.8*$Y12)*$AA12 -> 36.334944 | P12: =(31.5*$Y12)*$AA12 -> 37.160739 | Q12: =(34.6*$Y12)*$AA12 -> 40.817827 | R12: =(30.8*$Y12)*$AA12 -> 36.334944 | S12: =(31.5*$Y12)*$AA12 -> 37.160739 | T12: =(34.6*$Y12)*$AA12 -> 40.817827 | U12: =(30.8*$Y12)*$AA12 -> 36.334944 | V12: =(31.5*$Y12)*$AA12 -> 37.160739 | W12: =(34.6*$Y12)*$AA12 -> 40.817827 | Y12: 1.0974009 | AA12: 1.075
B13: United States | C13: Austin | D13: AMERICAS | E13: =(331.44*$Y13)*$AA13 -> 366.97874 | F13: =(339.03*$Y13)*$AA13 -> 375.38258 | G13: =(371.99*$Y13)*$AA13 -> 411.87673 | H13: =(331.44*$Y13)*$AA13 -> 366.97874 | I13: =(339.03*$Y13)*$AA13 -> 375.38258 | J13: =(371.99*$Y13)*$AA13 -> 411.87673 | K13: =(331.44*$Y13)*$AA13 -> 366.97874 | L13: =(339.03*$Y13)*$AA13 -> 375.38258 | M13: =(371.99*$Y13)*$AA13 -> 411.87673 | O13: =(30.8*$Y13)*$AA13 -> 34.102538 | P13: =(31.5*$Y13)*$AA13 -> 34.877596 | Q13: =(34.6*$Y13)*$AA13 -> 38.309994 | R13: =(30.8*$Y13)*$AA13 -> 34.102538 | S13: =(31.5*$Y13)*$AA13 -> 34.877596 | T13: =(34.6*$Y13)*$AA13 -> 38.309994 | U13: =(30.8*$Y13)*$AA13 -> 34.102538 | V13: =(31.5*$Y13)*$AA13 -> 34.877596 | W13: =(34.6*$Y13)*$AA13 -> 38.309994 | Y13: 1.029977 | AA13: 1.075
B14: United States | C14: Atlanta | D14: AMERICAS | E14: =(331.44*$Y14)*$AA14 -> 387.2321 | F14: =(339.03*$Y14)*$AA14 -> 396.09974 | G14: =(371.99*$Y14)*$AA14 -> 434.60798 | H14: =(331.44*$Y14)*$AA14 -> 387.2321 | I14: =(339.03*$Y14)*$AA14 -> 396.09974 | J14: =(371.99*$Y14)*$AA14 -> 434.60798 | K14: =(331.44*$Y14)*$AA14 -> 387.2321 | L14: =(339.03*$Y14)*$AA14 -> 396.09974 | M14: =(371.99*$Y14)*$AA14 -> 434.60798 | O14: =(30.8*$Y14)*$AA14 -> 35.984639 | P14: =(31.5*$Y14)*$AA14 -> 36.802471 | Q14: =(34.6*$Y14)*$AA14 -> 40.424302 | R14: =(30.8*$Y14)*$AA14 -> 35.984639 | S14: =(31.5*$Y14)*$AA14 -> 36.802471 | T14: =(34.6*$Y14)*$AA14 -> 40.424302 | U14: =(30.8*$Y14)*$AA14 -> 35.984639 | V14: =(31.5*$Y14)*$AA14 -> 36.802471 | W14: =(34.6*$Y14)*$AA14 -> 40.424302 | Y14: 1.0868209 | AA14: 1.075
B15: United States | C15: Dallas | D15: AMERICAS | E15: =(331.44*$Y15)*$AA15 -> 368.80262 | F15: =(339.03*$Y15)*$AA15 -> 377.24822 | G15: =(371.99*$Y15)*$AA15 -> 413.92374 | H15: =(331.44*$Y15)*$AA15 -> 368.80262 | I15: =(339.03*$Y15)*$AA15 -> 377.24822 | J15: =(371.99*$Y15)*$AA15 -> 413.92374 | K15: =(331.44*$Y15)*$AA15 -> 368.80262 | L15: =(339.03*$Y15)*$AA15 -> 377.24822 | M15: =(371.99*$Y15)*$AA15 -> 413.92374 | O15: =(30.8*$Y15)*$AA15 -> 34.272027 | P15: =(31.5*$Y15)*$AA15 -> 35.050937 | Q15: =(34.6*$Y15)*$AA15 -> 38.500394 | R15: =(30.8*$Y15)*$AA15 -> 34.272027 | S15: =(31.5*$Y15)*$AA15 -> 35.050937 | T15: =(34.6*$Y15)*$AA15 -> 38.500394 | U15: =(30.8*$Y15)*$AA15 -> 34.272027 | V15: =(31.5*$Y15)*$AA15 -> 35.050937 | W15: =(34.6*$Y15)*$AA15 -> 38.500394 | Y15: 1.035096 | AA15: 1.075
B16: United States | C16: Denver | D16: AMERICAS | E16: =(331.44*$Y16)*$AA16 -> 393.93372 | F16: =(339.03*$Y16)*$AA16 -> 402.95483 | G16: =(371.99*$Y16)*$AA16 -> 442.12951 | H16: =(331.44*$Y16)*$AA16 -> 393.93372 | I16: =(339.03*$Y16)*$AA16 -> 402.95483 | J16: =(371.99*$Y16)*$AA16 -> 442.12951 | K16: =(331.44*$Y16)*$AA16 -> 393.93372 | L16: =(339.03*$Y16)*$AA16 -> 402.95483 | M16: =(371.99*$Y16)*$AA16 -> 442.12951 | O16: =(30.8*$Y16)*$AA16 -> 36.607406 | P16: =(31.5*$Y16)*$AA16 -> 37.439392 | Q16: =(34.6*$Y16)*$AA16 -> 41.123904 | R16: =(30.8*$Y16)*$AA16 -> 36.607406 | S16: =(31.5*$Y16)*$AA16 -> 37.439392 | T16: =(34.6*$Y16)*$AA16 -> 41.123904 | U16: =(30.8*$Y16)*$AA16 -> 36.607406 | V16: =(31.5*$Y16)*$AA16 -> 37.439392 | W16: =(34.6*$Y16)*$AA16 -> 41.123904 | Y16: 1.1056299 | AA16: 1.075
... B78: France | C78: Paris | D78: EMEA | E78: =(331.44*$Y78)*$AA78 -> 292.44891 | F78: =(339.03*$Y78)*$AA78 -> 299.14601 | G78: =(371.99*$Y78)*$AA78 -> 328.22855 | H78: =(331.44*$Y78)*$AA78 -> 292.44891 | I78: =(339.03*$Y78)*$AA78 -> 299.14601 | J78: =(371.99*$Y78)*$AA78 -> 328.22855 | K78: =(331.44*$Y78)*$AA78 -> 292.44891 | L78: =(339.03*$Y78)*$AA78 -> 299.14601 | M78: =(371.99*$Y78)*$AA78 -> 328.22855 | O78: =(30.8*$Y78)*$AA78 -> 27.176643 | P78: =(31.5*$Y78)*$AA78 -> 27.794294 | Q78: =(34.6*$Y78)*$AA78 -> 30.529605 | R78: =(30.8*$Y78)*$AA78 -> 27.176643 | S78: =(31.5*$Y78)*$AA78 -> 27.794294 | T78: =(34.6*$Y78)*$AA78 -> 30.529605 | U78: =(30.8*$Y78)*$AA78 -> 27.176643 | V78: =(31.5*$Y78)*$AA78 -> 27.794294 | W78: =(34.6*$Y78)*$AA78 -> 30.529605 | Y78: 0.84034146 | AA78: 1.05
A79: ? | B79: Germany | C79: Berlin | D79: EMEA | E79: =(331.44*$Y79)*$AA79 -> 0 | F79: =(339.03*$Y79)*$AA79 -> 0 | G79: =(371.99*$Y79)*$AA79 -> 0 | H79: =(331.44*$Y79)*$AA79 -> 0 | I79: =(339.03*$Y79)*$AA79 -> 0 | J79: =(371.99*$Y79)*$AA79 -> 0 | K79: =(331.44*$Y79)*$AA79 -> 0 | L79: =(339.03*$Y79)*$AA79 -> 0 | M79: =(371.99*$Y79)*$AA79 -> 0 | O79: =(30.8*$Y79)*$AA79 -> 0 | P79: =(31.5*$Y79)*$AA79 -> 0 | Q79: =(34.6*$Y79)*$AA79 -> 0 | R79: =(30.8*$Y79)*$AA79 -> 0 | S79: =(31.5*$Y79)*$AA79 -> 0 | T79: =(34.6*$Y79)*$AA79 -> 0 | U79: =(30.8*$Y79)*$AA79 -> 0 | V79: =(31.5*$Y79)*$AA79 -> 0 | W79: =(34.6*$Y79)*$AA79 -> 0 | AA79: 1.075
B80: Germany | C80: Cologne | D80: EMEA | E80: =(331.44*$Y80)*$AA80 -> 277.37226 | F80: =(339.03*$Y80)*$AA80 -> 283.72411 | G80: =(371.99*$Y80)*$AA80 -> 311.30735 | H80: =(331.44*$Y80)*$AA80 -> 277.37226 | I80: =(339.03*$Y80)*$AA80 -> 283.72411 | J80: =(371.99*$Y80)*$AA80 -> 311.30735 | K80: =(331.44*$Y80)*$AA80 -> 277.37226 | L80: =(339.03*$Y80)*$AA80 -> 283.72411 | M80: =(371.99*$Y80)*$AA80 -> 311.30735 | O80: =(30.8*$Y80)*$AA80 -> 25.775602 | P80: =(31.5*$Y80)*$AA80 -> 26.361412 | Q80: =(34.6*$Y80)*$AA80 -> 28.955709 | R80: =(30.8*$Y80)*$AA80 -> 25.775602 | S80: =(31.5*$Y80)*$AA80 -> 26.361412 | T80: =(34.6*$Y80)*$AA80 -> 28.955709 | U80: =(30.8*$Y80)*$AA80 -> 25.775602 | V80: =(31.5*$Y80)*$AA80 -> 26.361412 | W80: =(34.6*$Y80)*$AA80 -> 28.955709 | Y80: 0.77848392 | AA80: 1.075
A81: ? | B81: Germany | C81: Frankfurt | D81: EMEA | E81: =(331.44*$Y81)*$AA81 -> 0 | F81: =(339.03*$Y81)*$AA81 -> 0 | G81: =(371.99*$Y81)*$AA81 -> 0 | H81: =(331.44*$Y81)*$AA81 -> 0 | I81: =(339.03*$Y81)*$AA81 -> 0 | J81: =(371.99*$Y81)*$AA81 -> 0 | K81: =(331.44*$Y81)*$AA81 -> 0 | L81: =(339.03*$Y81)*$AA81 -> 0 | M81: =(371.99*$Y81)*$AA81 -> 0 | O81: =(30.8*$Y81)*$AA81 -> 0 | P81: =(31.5*$Y81)*$AA81 -> 0 | Q81: =(34.6*$Y81)*$AA81 -> 0 | R81: =(30.8*$Y81)*$AA81 -> 0 | S81: =(31.5*$Y81)*$AA81 -> 0 | T81: =(34.6*$Y81)*$AA81 -> 0 | U81: =(30.8*$Y81)*$AA81 -> 0 | V81: =(31.5*$Y81)*$AA81 -> 0 | W81: =(34.6*$Y81)*$AA81 -> 0 | AA81: 1.075
A82: ? | B82: Germany | C82: Hamburg | D82: EMEA | E82: =(331.44*$Y82)*$AA82 -> 0 | F82: =(339.03*$Y82)*$AA82 -> 0 | G82: =(371.99*$Y82)*$AA82 -> 0 | H82: =(331.44*$Y82)*$AA82 -> 0 | I82: =(339.03*$Y82)*$AA82 -> 0 | J82: =(371.99*$Y82)*$AA82 -> 0 | K82: =(331.44*$Y82)*$AA82 -> 0 | L82: =(339.03*$Y82)*$AA82 -> 0 | M82: =(371.99*$Y82)*$AA82 -> 0 | O82: =(30.8*$Y82)*$AA82 -> 0 | P82: =(31.5*$Y82)*$AA82 -> 0 | Q82: =(34.6*$Y82)*$AA82 -> 0 | R82: =(30.8*$Y82)*$AA82 -> 0 | S82: =(31.5*$Y82)*$AA82 -> 0 | T82: =(34.6*$Y82)*$AA82 -> 0 | U82: =(30.8*$Y82)*$AA82 -> 0 | V82: =(31.5*$Y82)*$AA82 -> 0 | W82: =(34.6*$Y82)*$AA82 -> 0 | AA82: 1.075
A83: ? | B83: Germany | C83: Munich | D83: EMEA | E83: =(331.44*$Y83)*$AA83 -> 0 | F83: =(339.03*$Y83)*$AA83 -> 0 | G83: =(371.99*$Y83)*$AA83 -> 0 | H83: =(331.44*$Y83)*$AA83 -> 0 | I83: =(339.03*$Y83)*$AA83 -> 0 | J83: =(371.99*$Y83)*$AA83 -> 0 | K83: =(331.44*$Y83)*$AA83 -> 0 | L83: =(339.03*$Y83)*$AA83 -> 0 | M83: =(371.99*$Y83)*$AA83 -> 0 | O83: =(30.8*$Y83)*$AA83 -> 0 | P83: =(31.5*$Y83)*$AA83 -> 0 | Q83: =(34.6*$Y83)*$AA83 -> 0 | R83: =(30.8*$Y83)*$AA83 -> 0 | S83: =(31.5*$Y83)*$AA83 -> 0 | T83: =(34.6*$Y83)*$AA83 -> 0 | U83: =(30.8*$Y83)*$AA83 -> 0 | V83: =(31.5*$Y83)*$AA83 -> 0 | W83: =(34.6*$Y83)*$AA83 -> 0 | AA83: 1.075
A84: ? | B84: Germany | C84: Stuttgart | D84: EMEA | E84: =(331.44*$Y84)*$AA84 -> 0 | F84: =(339.03*$Y84)*$AA84 -> 0 | G84: =(371.99*$Y84)*$AA84 -> 0 | H84: =(331.44*$Y84)*$AA84 -> 0 | I84: =(339.03*$Y84)*$AA84 -> 0 | J84: =(371.99*$Y84)*$AA84 -> 0 | K84: =(331.44*$Y84)*$AA84 -> 0 | L84: =(339.03*$Y84)*$AA84 -> 0 | M84: =(371.99*$Y84)*$AA84 -> 0 | O84: =(30.8*$Y84)*$AA84 -> 0 | P84: =(31.5*$Y84)*$AA84 -> 0 | Q84: =(34.6*$Y84)*$AA84 -> 0 | R84: =(30.8*$Y84)*$AA84 -> 0 | S84: =(31.5*$Y84)*$AA84 -> 0 | T84: =(34.6*$Y84)*$AA84 -> 0 | U84: =(30.8*$Y84)*$AA84 -> 0 | V84: =(31.5*$Y84)*$AA84 -> 0 | W84: =(34.6*$Y84)*$AA84 -> 0 | AA84: 1.075
B85: Ghana | C85: Accra | D85: EMEA | E85: =(331.44*$Y85)*$AA85 -> 210.18559 | F85: =(339.03*$Y85)*$AA85 -> 214.99886 | G85: =(371.99*$Y85)*$AA85 -> 235.90073 | H85: =(331.44*$Y85)*$AA85 -> 210.18559 | I85: =(339.03*$Y85)*$AA85 -> 214.99886 | J85: =(371.99*$Y85)*$AA85 -> 235.90073 | K85: =(331.44*$Y85)*$AA85 -> 210.18559 | L85: =(339.03*$Y85)*$AA85 -> 214.99886 | M85: =(371.99*$Y85)*$AA85 -> 235.90073 | O85: =(30.8*$Y85)*$AA85 -> 19.532091 | P85: =(31.5*$Y85)*$AA85 -> 19.976002 | Q85: =(34.6*$Y85)*$AA85 -> 21.941895 | R85: =(30.8*$Y85)*$AA85 -> 19.532091 | S85: =(31.5*$Y85)*$AA85 -> 19.976002 | T85: =(34.6*$Y85)*$AA85 -> 21.941895 | U85: =(30.8*$Y85)*$AA85 -> 19.532091 | V85: =(31.5*$Y85)*$AA85 -> 19.976002 | W85: =(34.6*$Y85)*$AA85 -> 21.941895 | Y85: 0.60976808 | AA85: 1.04
B86: Hungary | C86: Budapest | D86: EMEA | E86: =(331.44*$Y86)*$AA86 -> 215.98846 | F86: =(339.03*$Y86)*$AA86 -> 220.93462 | G86: =(371.99*$Y86)*$AA86 -> 242.41356 | H86: =(331.44*$Y86)*$AA86 -> 215.98846 | I86: =(339.03*$Y86)*$AA86 -> 220.93462 | J86: =(371.99*$Y86)*$AA86 -> 242.41356 | K86: =(331.44*$Y86)*$AA86 -> 215.98846 | L86: =(339.03*$Y86)*$AA86 -> 220.93462 | M86: =(371.99*$Y86)*$AA86 -> 242.41356 | O86: =(30.8*$Y86)*$AA86 -> 20.071339 | P86: =(31.5*$Y86)*$AA86 -> 20.527506 | Q86: =(34.6*$Y86)*$AA86 -> 22.547673 | R86: =(30.8*$Y86)*$AA86 -> 20.071339 | S86: =(31.5*$Y86)*$AA86 -> 20.527506 | T86: =(34.6*$Y86)*$AA86 -> 22.547673 | U86: =(30.8*$Y86)*$AA86 -> 20.071339 | V86: =(31.5*$Y86)*$AA86 -> 20.527506 | W86: =(34.6*$Y86)*$AA86 -> 22.547673 | Y86: 0.6206351 | AA86: 1.05
B87: Ireland | C87: Dublin | D87: EMEA | E87: =(331.44*$Y87)*$AA87 -> 261.1315 | F87: =(339.03*$Y87)*$AA87 -> 267.11143 | G87: =(371.99*$Y87)*$AA87 -> 293.07961 | H87: =(331.44*$Y87)*$AA87 -> 261.1315 | I87: =(339.03*$Y87)*$AA87 -> 267.11143 | J87: =(371.99*$Y87)*$AA87 -> 293.07961 | K87: =(331.44*$Y87)*$AA87 -> 261.1315 | L87: =(339.03*$Y87)*$AA87 -> 267.11143 | M87: =(371.99*$Y87)*$AA87 -> 293.07961 | O87: =(30.8*$Y87)*$AA87 -> 24.266384 | P87: =(31.5*$Y87)*$AA87 -> 24.817892 | Q87: =(34.6*$Y87)*$AA87 -> 27.260288 | R87: =(30.8*$Y87)*$AA87 -> 24.266384 | S87: =(31.5*$Y87)*$AA87 -> 24.817892 | T87: =(34.6*$Y87)*$AA87 -> 27.260288 | U87: =(30.8*$Y87)*$AA87 -> 24.266384 | V87: =(31.5*$Y87)*$AA87 -> 24.817892 | W87: =(34.6*$Y87)*$AA87 -> 27.260288 | Y87: 0.73632673 | AA87: 1.07
B88: Israel | C88: Tel Aviv | D88: EMEA | E88: =(331.44*$Y88)*$AA88 -> 269.26161 | F88: =(339.03*$Y88)*$AA88 -> 275.42772 | G88: =(371.99*$Y88)*$AA88 -> 302.2044 | H88: =(331.44*$Y88)*$AA88 -> 269.26161 | I88: =(339.03*$Y88)*$AA88 -> 275.42772 | J88: =(371.99*$Y88)*$AA88 -> 302.2044 | K88: =(331.44*$Y88)*$AA88 -> 269.26161 | L88: =(339.03*$Y88)*$AA88 -> 275.42772 | M88: =(371.99*$Y88)*$AA88 -> 302.2044 | O88: =(30.8*$Y88)*$AA88 -> 25.021897 | P88: =(31.5*$Y88)*$AA88 -> 25.590577 | Q88: =(34.6*$Y88)*$AA88 -> 28.109015 | R88: =(30.8*$Y88)*$AA88 -> 25.021897 | S88: =(31.5*$Y88)*$AA88 -> 25.590577 | T88: =(34.6*$Y88)*$AA88 -> 28.109015 | U88: =(30.8*$Y88)*$AA88 -> 25.021897 | V88: =(31.5*$Y88)*$AA88 -> 25.590577 | W88: =(34.6*$Y88)*$AA88 -> 28.109015 | Y88: 0.74806562 | AA88: 1.086
B89: Italy | C89: Rome | D89: EMEA | E89: =(331.44*$Y89)*$AA89 -> 174.31193 | F89: =(339.03*$Y89)*$AA89 -> 178.30368 | G89: =(371.99*$Y89)*$AA89 -> 195.6381 | H89: =(331.44*$Y89)*$AA89 -> 174.31193 | I89: =(339.03*$Y89)*$AA89 -> 178.30368 | J89: =(371.99*$Y89)*$AA89 -> 195.6381 | K89: =(331.44*$Y89)*$AA89 -> 174.31193 | L89: =(339.03*$Y89)*$AA89 -> 178.30368 | M89: =(371.99*$Y89)*$AA89 -> 195.6381 | O89: =(30.8*$Y89)*$AA89 -> 16.198429 | P89: =(31.5*$Y89)*$AA89 -> 16.566575 | Q89: =(34.6*$Y89)*$AA89 -> 18.196936 | R89: =(30.8*$Y89)*$AA89 -> 16.198429 | S89: =(31.5*$Y89)*$AA89 -> 16.566575 | T89: =(34.6*$Y89)*$AA89 -> 18.196936 | U89: =(30.8*$Y89)*$AA89 -> 16.198429 | V89: =(31.5*$Y89)*$AA89 -> 16.566575 | W89: =(34.6*$Y89)*$AA89 -> 18.196936 | Y89: 0.48923072 | AA89: 1.075
B90: Kenya | C90: Nairobi | D90: EMEA | E90: =(331.44*$Y90)*$AA90 -> 164.31816 | F90: =(339.03*$Y90)*$AA90 -> 168.08105 | G90: =(371.99*$Y90)*$AA90 -> 184.42165 | H90: =(331.44*$Y90)*$AA90 -> 164.31816 | I90: =(339.03*$Y90)*$AA90 -> 168.08105 | J90: =(371.99*$Y90)*$AA90 -> 184.42165 | K90: =(331.44*$Y90)*$AA90 -> 164.31816 | L90: =(339.03*$Y90)*$AA90 -> 168.08105 | M90: =(371.99*$Y90)*$AA90 -> 184.42165 | O90: =(30.8*$Y90)*$AA90 -> 15.26973 | P90: =(31.5*$Y90)*$AA90 -> 15.616769 | Q90: =(34.6*$Y90)*$AA90 -> 17.153657 | R90: =(30.8*$Y90)*$AA90 -> 15.26973 | S90: =(31.5*$Y90)*$AA90 -> 15.616769 | T90: =(34.6*$Y90)*$AA90 -> 17.153657 | U90: =(30.8*$Y90)*$AA90 -> 15.26973 | V90: =(31.5*$Y90)*$AA90 -> 15.616769 | W90: =(34.6*$Y90)*$AA90 -> 17.153657 | Y90: 0.47670235 | AA90: 1.04
B91: Luxembourg | C91: Luxembourg | D91: EMEA | E91: =(331.44*$Y91)*$AA91 -> 224.40919 | F91: =(339.03*$Y91)*$AA91 -> 229.54817 | G91: =(371.99*$Y91)*$AA91 -> 251.86451 | H91: =(331.44*$Y91)*$AA91 -> 224.40919 | I91: =(339.03*$Y91)*$AA91 -> 229.54817 | J91: =(371.99*$Y91)*$AA91 -> 251.86451 | K91: =(331.44*$Y91)*$AA91 -> 224.40919 | L91: =(339.03*$Y91)*$AA91 -> 229.54817 | M91: =(371.99*$Y91)*$AA91 -> 251.86451 | O91: =(30.8*$Y91)*$AA91 -> 20.853859 | P91: =(31.5*$Y91)*$AA91 -> 21.32781 | Q91: =(34.6*$Y91)*$AA91 -> 23.426737 | R91: =(30.8*$Y91)*$AA91 -> 20.853859 | S91: =(31.5*$Y91)*$AA91 -> 21.32781 | T91: =(34.6*$Y91)*$AA91 -> 23.426737 | U91: =(30.8*$Y91)*$AA91 -> 20.853859 | V91: =(31.5*$Y91)*$AA91 -> 21.32781 | W91: =(34.6*$Y91)*$AA91 -> 23.426737 | Y91: 0.64483175 | AA91: 1.05
B92: Morocco | C92: Casablanca | D92: EMEA | E92: =(331.44*$Y92)*$AA92 -> 271.85504 | F92: =(339.03*$Y92)*$AA92 -> 278.08054 | G92: =(371.99*$Y92)*$AA92 -> 305.11512 | H92: =(331.44*$Y92)*$AA92 -> 271.85504 | I92: =(339.03*$Y92)*$AA92 -> 278.08054 | J92: =(371.99*$Y92)*$AA92 -> 305.11512 | K92: =(331.44*$Y92)*$AA92 -> 271.85504 | L92: =(339.03*$Y92)*$AA92 -> 278.08054 | M92: =(371.99*$Y92)*$AA92 -> 305.11512 | O92: =(30.8*$Y92)*$AA92 -> 25.262899 | P92: =(31.5*$Y92)*$AA92 -> 25.837056 | Q92: =(34.6*$Y92)*$AA92 -> 28.37975 | R92: =(30.8*$Y92)*$AA92 -> 25.262899 | S92: =(31.5*$Y92)*$AA92 -> 25.837056 | T92: =(34.6*$Y92)*$AA92 -> 28.37975 | U92: =(30.8*$Y92)*$AA92 -> 25.262899 | V92: =(31.5*$Y92)*$AA92 -> 25.837056 | W92: =(34.6*$Y92)*$AA92 -> 28.37975 | Y92: 0.78867691 | AA92: 1.04
B93: Netherlands | C93: Amsterdam | D93: EMEA | E93: =(331.44*$Y93)*$AA93 -> 167.99828 | F93: =(339.03*$Y93)*$AA93 -> 171.84545 | G93: =(371.99*$Y93)*$AA93 -> 188.55201 | H93: =(331.44*$Y93)*$AA93 -> 167.99828 | I93: =(339.03*$Y93)*$AA93 -> 171.84545 | J93: =(371.99*$Y93)*$AA93 -> 188.55201 | K93: =(331.44*$Y93)*$AA93 -> 167.99828 | L93: =(339.03*$Y93)*$AA93 -> 171.84545 | M93: =(371.99*$Y93)*$AA93 -> 188.55201 | O93: =(30.8*$Y93)*$AA93 -> 15.611715 | P93: =(31.5*$Y93)*$AA93 -> 15.966527 | Q93: =(34.6*$Y93)*$AA93 -> 17.537836 | R93: =(30.8*$Y93)*$AA93 -> 15.611715 | S93: =(31.5*$Y93)*$AA93 -> 15.966527 | T93: =(34.6*$Y93)*$AA93 -> 17.537836 | U93: =(30.8*$Y93)*$AA93 -> 15.611715 | V93: =(31.5*$Y93)*$AA93 -> 15.966527 | W93: =(34.6*$Y93)*$AA93 -> 17.537836 | Y93: 0.48044917 | AA93: 1.055
B94: Nigeria | C94: Abuja | D94: EMEA | E94: =(331.44*$Y94)*$AA94 -> 212.13222 | F94: =(339.03*$Y94)*$AA94 -> 216.99007 | G94: =(371.99*$Y94)*$AA94 -> 238.08552 | H94: =(331.44*$Y94)*$AA94 -> 212.13222 | I94: =(339.03*$Y94)*$AA94 -> 216.99007 | J94: =(371.99*$Y94)*$AA94 -> 238.08552 | K94: =(331.44*$Y94)*$AA94 -> 212.13222 | L94: =(339.03*$Y94)*$AA94 -> 216.99007 | M94: =(371.99*$Y94)*$AA94 -> 238.08552 | O94: =(30.8*$Y94)*$AA94 -> 19.712987 | P94: =(31.5*$Y94)*$AA94 -> 20.16101 | Q94: =(34.6*$Y94)*$AA94 -> 22.145109 | R94: =(30.8*$Y94)*$AA94 -> 19.712987 | S94: =(31.5*$Y94)*$AA94 -> 20.16101 | T94: =(34.6*$Y94)*$AA94 -> 22.145109 | U94: =(30.8*$Y94)*$AA94 -> 19.712987 | V94: =(31.5*$Y94)*$AA94 -> 20.16101 | W94: =(34.6*$Y94)*$AA94 -> 22.145109 | Y94: 0.61541543 | AA94: 1.04
B95: Norway | C95: Oslo | D95: EMEA | E95: =(331.44*$Y95)*$AA95 -> 277.66265 | F95: =(339.03*$Y95)*$AA95 -> 284.02114 | G95: =(371.99*$Y95)*$AA95 -> 311.63326 | H95: =(331.44*$Y95)*$AA95 -> 277.66265 | I95: =(339.03*$Y95)*$AA95 -> 284.02114 | J95: =(371.99*$Y95)*$AA95 -> 311.63326 | K95: =(331.44*$Y95)*$AA95 -> 277.66265 | L95: =(339.03*$Y95)*$AA95 -> 284.02114 | M95: =(371.99*$Y95)*$AA95 -> 311.63326 | O95: =(30.8*$Y95)*$AA95 -> 25.802587 | P95: =(31.5*$Y95)*$AA95 -> 26.38901 | Q95: =(34.6*$Y95)*$AA95 -> 28.986023 | R95: =(30.8*$Y95)*$AA95 -> 25.802587 | S95: =(31.5*$Y95)*$AA95 -> 26.38901 | T95: =(34.6*$Y95)*$AA95 -> 28.986023 | U95: =(30.8*$Y95)*$AA95 -> 25.802587 | V95: =(31.5*$Y95)*$AA95 -> 26.38901 | W95: =(34.6*$Y95)*$AA95 -> 28.986023 | Y95: 0.79785366 | AA95: 1.05
B96: Poland | C96: Warsaw | D96: EMEA | E96: =(331.44*$Y96)*$AA96 -> 228.20368 | F96: =(339.03*$Y96)*$AA96 -> 233.42956 | G96: =(371.99*$Y96)*$AA96 -> 256.12324 | H96: =(331.44*$Y96)*$AA96 -> 228.20368 | I96: =(339.03*$Y96)*$AA96 -> 233.42956 | J96: =(371.99*$Y96)*$AA96 -> 256.12324 | K96: =(331.44*$Y96)*$AA96 -> 228.20368 | L96: =(339.03*$Y96)*$AA96 -> 233.42956 | M96: =(371.99*$Y96)*$AA96 -> 256.12324 | O96: =(30.8*$Y96)*$AA96 -> 21.206473 | P96: =(31.5*$Y96)*$AA96 -> 21.688438 | Q96: =(34.6*$Y96)*$AA96 -> 23.822856 | R96: =(30.8*$Y96)*$AA96 -> 21.206473 | S96: =(31.5*$Y96)*$AA96 -> 21.688438 | T96: =(34.6*$Y96)*$AA96 -> 23.822856 | U96: =(30.8*$Y96)*$AA96 -> 21.206473 | V96: =(31.5*$Y96)*$AA96 -> 21.688438 | W96: =(34.6*$Y96)*$AA96 -> 23.822856 | Y96: 0.64048544 | AA96: 1.075
... B113: Australia | C113: Sydney | D113: APAC | E113: =(331.44*$Y113)*$AA113 -> 276.50051 | F113: =(339.03*$Y113)*$AA113 -> 282.83239 | G113: =(371.99*$Y113)*$AA113 -> 310.32894 | H113: =(331.44*$Y113)*$AA113 -> 276.50051 | I113: =(339.03*$Y113)*$AA113 -> 282.83239 | J113: =(371.99*$Y113)*$AA113 -> 310.32894 | K113: =(331.44*$Y113)*$AA113 -> 276.50051 | L113: =(339.03*$Y113)*$AA113 -> 282.83239 | M113: =(371.99*$Y113)*$AA113 -> 310.32894 | O113: =(30.8*$Y113)*$AA113 -> 25.694592 | P113: =(31.5*$Y113)*$AA113 -> 26.27856 | Q113: =(34.6*$Y113)*$AA113 -> 28.864704 | R113: =(30.8*$Y113)*$AA113 -> 25.694592 | S113: =(31.5*$Y113)*$AA113 -> 26.27856 | T113: =(34.6*$Y113)*$AA113 -> 28.864704 | U113: =(30.8*$Y113)*$AA113 -> 25.694592 | V113: =(31.5*$Y113)*$AA113 -> 26.27856 | W113: =(34.6*$Y113)*$AA113 -> 28.864704 | Y113: 0.79 | AA113: 1.056
A114: 0.02 | B114: Australia | C114: Brisbane | D114: APAC | E114: =E113*1.02 -> 282.03052 | F114: =F113*1.02 -> 288.48903 | G114: =G113*1.02 -> 316.53552 | H114: =H113*1.02 -> 282.03052 | I114: =I113*1.02 -> 288.48903 | J114: =J113*1.02 -> 316.53552 | K114: =K113*1.02 -> 282.03052 | L114: =L113*1.02 -> 288.48903 | M114: =M113*1.02 -> 316.53552 | O114: =O113*1.02 -> 26.208484 | P114: =P113*1.02 -> 26.804131 | Q114: =Q113*1.02 -> 29.441998 | R114: =R113*1.02 -> 26.208484 | S114: =S113*1.02 -> 26.804131 | T114: =T113*1.02 -> 29.441998 | U114: =U113*1.02 -> 26.208484 | V114: =V113*1.02 -> 26.804131 | W114: =W113*1.02 -> 29.441998 | AA114: 1.056
A115: 0.04 | B115: Australia | C115: Melborne | D115: APAC | E115: =E113*1.04 -> 287.56053 | F115: =F113*1.04 -> 294.14568 | G115: =G113*1.04 -> 322.7421 | H115: =H113*1.04 -> 287.56053 | I115: =I113*1.04 -> 294.14568 | J115: =J113*1.04 -> 322.7421 | K115: =K113*1.04 -> 287.56053 | L115: =L113*1.04 -> 294.14568 | M115: =M113*1.04 -> 322.7421 | O115: =O113*1.04 -> 26.722376 | P115: =P113*1.04 -> 27.329702 | Q115: =Q113*1.04 -> 30.019292 | R115: =R113*1.04 -> 26.722376 | S115: =S113*1.04 -> 27.329702 | T115: =T113*1.04 -> 30.019292 | U115: =U113*1.04 -> 26.722376 | V115: =V113*1.04 -> 27.329702 | W115: =W113*1.04 -> 30.019292 | AA115: 1.056
A116: 0.03 | B116: Australia | C116: Perth | D116: APAC | E116: =E113*1.03 -> 284.79552 | F116: =F113*1.03 -> 291.31736 | G116: =G113*1.03 -> 319.63881 | H116: =H113*1.03 -> 284.79552 | I116: =I113*1.03 -> 291.31736 | J116: =J113*1.03 -> 319.63881 | K116: =K113*1.03 -> 284.79552 | L116: =L113*1.03 -> 291.31736 | M116: =M113*1.03 -> 319.63881 | O116: =O113*1.03 -> 26.46543 | P116: =P113*1.03 -> 27.066917 | Q116: =Q113*1.03 -> 29.730645 | R116: =R113*1.03 -> 26.46543 | S116: =S113*1.03 -> 27.066917 | T116: =T113*1.03 -> 29.730645 | U116: =U113*1.03 -> 26.46543 | V116: =V113*1.03 -> 27.066917 | W116: =W113*1.03 -> 29.730645 | AA116: 1.056
B117: China | C117: Beijing | D117: APAC | E117: =(331.44*$Y117)*$AA117 -> 196.0799 | F117: =(339.03*$Y117)*$AA117 -> 200.57015 | G117: =(371.99*$Y117)*$AA117 -> 220.06928 | H117: =(331.44*$Y117)*$AA117 -> 196.0799 | I117: =(339.03*$Y117)*$AA117 -> 200.57015 | J117: =(371.99*$Y117)*$AA117 -> 220.06928 | K117: =(331.44*$Y117)*$AA117 -> 196.0799 | L117: =(339.03*$Y117)*$AA117 -> 200.57015 | M117: =(371.99*$Y117)*$AA117 -> 220.06928 | O117: =(30.8*$Y117)*$AA117 -> 18.22128 | P117: =(31.5*$Y117)*$AA117 -> 18.6354 | Q117: =(34.6*$Y117)*$AA117 -> 20.46936 | R117: =(30.8*$Y117)*$AA117 -> 18.22128 | S117: =(31.5*$Y117)*$AA117 -> 18.6354 | T117: =(34.6*$Y117)*$AA117 -> 20.46936 | U117: =(30.8*$Y117)*$AA117 -> 18.22128 | V117: =(31.5*$Y117)*$AA117 -> 18.6354 | W117: =(34.6*$Y117)*$AA117 -> 20.46936 | Y117: 0.58 | AA117: 1.02
B118: China | C118: Guangzhou | D118: APAC | E118: =(331.44*$Y118)*$AA118 -> 192.69922 | F118: =(339.03*$Y118)*$AA118 -> 197.11204 | G118: =(371.99*$Y118)*$AA118 -> 216.27499 | H118: =(331.44*$Y118)*$AA118 -> 192.69922 | I118: =(339.03*$Y118)*$AA118 -> 197.11204 | J118: =(371.99*$Y118)*$AA118 -> 216.27499 | K118: =(331.44*$Y118)*$AA118 -> 192.69922 | L118: =(339.03*$Y118)*$AA118 -> 197.11204 | M118: =(371.99*$Y118)*$AA118 -> 216.27499 | O118: =(30.8*$Y118)*$AA118 -> 17.90712 | P118: =(31.5*$Y118)*$AA118 -> 18.3141 | Q118: =(34.6*$Y118)*$AA118 -> 20.11644 | R118: =(30.8*$Y118)*$AA118 -> 17.90712 | S118: =(31.5*$Y118)*$AA118 -> 18.3141 | T118: =(34.6*$Y118)*$AA118 -> 20.11644 | U118: =(30.8*$Y118)*$AA118 -> 17.90712 | V118: =(31.5*$Y118)*$AA118 -> 18.3141 | W118: =(34.6*$Y118)*$AA118 -> 20.11644 | Y118: 0.57 | AA118: 1.02
B119: China | C119: Shanghai | D119: APAC | E119: =(331.44*$Y119)*$AA119 -> 189.31853 | F119: =(339.03*$Y119)*$AA119 -> 193.65394 | G119: =(371.99*$Y119)*$AA119 -> 212.48069 | H119: =(331.44*$Y119)*$AA119 -> 189.31853 | I119: =(339.03*$Y119)*$AA119 -> 193.65394 | J119: =(371.99*$Y119)*$AA119 -> 212.48069 | K119: =(331.44*$Y119)*$AA119 -> 189.31853 | L119: =(339.03*$Y119)*$AA119 -> 193.65394 | M119: =(371.99*$Y119)*$AA119 -> 212.48069 | O119: =(30.8*$Y119)*$AA119 -> 17.59296 | P119: =(31.5*$Y119)*$AA119 -> 17.9928 | Q119: =(34.6*$Y119)*$AA119 -> 19.76352 | R119: =(30.8*$Y119)*$AA119 -> 17.59296 | S119: =(31.5*$Y119)*$AA119 -> 17.9928 | T119: =(34.6*$Y119)*$AA119 -> 19.76352 | U119: =(30.8*$Y119)*$AA119 -> 17.59296 | V119: =(31.5*$Y119)*$AA119 -> 17.9928 | W119: =(34.6*$Y119)*$AA119 -> 19.76352 | Y119: 0.56 | AA119: 1.02
B120: India | C120: Bangalore | D120: APAC | E120: =(331.44*$Y120)*$AA120 -> 99.399807 | F120: =(339.03*$Y120)*$AA120 -> 101.67607 | G120: =(371.99*$Y120)*$AA120 -> 111.56087 | H120: =(331.44*$Y120)*$AA120 -> 99.399807 | I120: =(339.03*$Y120)*$AA120 -> 101.67607 | J120: =(371.99*$Y120)*$AA120 -> 111.56087 | K120: =(331.44*$Y120)*$AA120 -> 99.399807 | L120: =(339.03*$Y120)*$AA120 -> 101.67607 | M120: =(371.99*$Y120)*$AA120 -> 111.56087 | O120: =(30.8*$Y120)*$AA120 -> 9.2370084 | P120: =(31.5*$Y120)*$AA120 -> 9.4469404 | Q120: =(34.6*$Y120)*$AA120 -> 10.376639 | R120: =(30.8*$Y120)*$AA120 -> 9.2370084 | S120: =(31.5*$Y120)*$AA120 -> 9.4469404 | T120: =(34.6*$Y120)*$AA120 -> 10.376639 | U120: =(30.8*$Y120)*$AA120 -> 9.2370084 | V120: =(31.5*$Y120)*$AA120 -> 9.4469404 | W120: =(34.6*$Y120)*$AA120 -> 10.376639 | Y120: 0.28976123 | AA120: 1.035
A121: -0.01 | B121: India | C121: Chennai | D121: APAC | E121: =E120/1.01 -> 98.41565 | F121: =F120/1.01 -> 100.66938 | G121: =G120/1.01 -> 110.45631 | H121: =H120/1.01 -> 98.41565 | I121: =I120/1.01 -> 100.66938 | J121: =J120/1.01 -> 110.45631 | K121: =K120/1.01 -> 98.41565 | L121: =L120/1.01 -> 100.66938 | M121: =M120/1.01 -> 110.45631 | O121: =O120/1.01 -> 9.1455528 | P121: =P120/1.01 -> 9.3534063 | Q121: =Q120/1.01 -> 10.2739 | R121: =R120/1.01 -> 9.1455528 | S121: =S120/1.01 -> 9.3534063 | T121: =T120/1.01 -> 10.2739 | U121: =U120/1.01 -> 9.1455528 | V121: =V120/1.01 -> 9.3534063 | W121: =W120/1.01 -> 10.2739 | AA121: 1.035
A122: -0.01 | B122: India | C122: Hyderbad | D122: APAC | E122: =E120/1.01 -> 98.41565 | F122: =F120/1.01 -> 100.66938 | G122: =G120/1.01 -> 110.45631 | H122: =H120/1.01 -> 98.41565 | I122: =I120/1.01 -> 100.66938 | J122: =J120/1.01 -> 110.45631 | K122: =K120/1.01 -> 98.41565 | L122: =L120/1.01 -> 100.66938 | M122: =M120/1.01 -> 110.45631 | O122: =O120/1.01 -> 9.1455528 | P122: =P120/1.01 -> 9.3534063 | Q122: =Q120/1.01 -> 10.2739 | R122: =R120/1.01 -> 9.1455528 | S122: =S120/1.01 -> 9.3534063 | T122: =T120/1.01 -> 10.2739 | U122: =U120/1.01 -> 9.1455528 | V122: =V120/1.01 -> 9.3534063 | W122: =W120/1.01 -> 10.2739 | AA122: 1.035
A123: -0.02 | B123: India | C123: Kolkata | D123: APAC | E123: =E120/1.02 -> 97.450791 | F123: =F120/1.02 -> 99.682421 | G123: =G120/1.02 -> 109.3734 | H123: =H120/1.02 -> 97.450791 | I123: =I120/1.02 -> 99.682421 | J123: =J120/1.02 -> 109.3734 | K123: =K120/1.02 -> 97.450791 | L123: =L120/1.02 -> 99.682421 | M123: =M120/1.02 -> 109.3734 | O123: =O120/1.02 -> 9.0558905 | P123: =P120/1.02 -> 9.2617062 | Q123: =Q120/1.02 -> 10.173176 | R123: =R120/1.02 -> 9.0558905 | S123: =S120/1.02 -> 9.2617062 | T123: =T120/1.02 -> 10.173176 | U123: =U120/1.02 -> 9.0558905 | V123: =V120/1.02 -> 9.2617062 | W123: =W120/1.02 -> 10.173176 | AA123: 1.035
A124: 0.08 | B124: India | C124: Mumbai | D124: APAC | E124: =E120*1.08 -> 107.35179 | F124: =F120*1.08 -> 109.81016 | G124: =G120*1.08 -> 120.48574 | H124: =H120*1.08 -> 107.35179 | I124: =I120*1.08 -> 109.81016 | J124: =J120*1.08 -> 120.48574 | K124: =K120*1.08 -> 107.35179 | L124: =L120*1.08 -> 109.81016 | M124: =M120*1.08 -> 120.48574 | O124: =O120*1.08 -> 9.975969 | P124: =P120*1.08 -> 10.202696 | Q124: =Q120*1.08 -> 11.20677 | R124: =R120*1.08 -> 9.975969 | S124: =S120*1.08 -> 10.202696 | T124: =T120*1.08 -> 11.20677 | U124: =U120*1.08 -> 9.975969 | V124: =V120*1.08 -> 10.202696 | W124: =W120*1.08 -> 11.20677 | AA124: 1.035
A125: 0.05 | B125: India | C125: New Delhi | D125: APAC | E125: =E120*1.05 -> 104.3698 | F125: =F120*1.05 -> 106.75987 | G125: =G120*1.05 -> 117.13891 | H125: =H120*1.05 -> 104.3698 | I125: =I120*1.05 -> 106.75987 | J125: =J120*1.05 -> 117.13891 | K125: =K120*1.05 -> 104.3698 | L125: =L120*1.05 -> 106.75987 | M125: =M120*1.05 -> 117.13891 | O125: =O120*1.05 -> 9.6988588 | P125: =P120*1.05 -> 9.9192874 | Q125: =Q120*1.05 -> 10.895471 | R125: =R120*1.05 -> 9.6988588 | S125: =S120*1.05 -> 9.9192874 | T125: =T120*1.05 -> 10.895471 | U125: =U120*1.05 -> 9.6988588 | V125: =V120*1.05 -> 9.9192874 | W125: =W120*1.05 -> 10.895471 | AA125: 1.035
A126: -0.01 | B126: India | C126: Pune | D126: APAC | E126: =E120/1.01 -> 98.41565 | F126: =F120/1.01 -> 100.66938 | G126: =G120/1.01 -> 110.45631 | H126: =H120/1.01 -> 98.41565 | I126: =I120/1.01 -> 100.66938 | J126: =J120/1.01 -> 110.45631 | K126: =K120/1.01 -> 98.41565 | L126: =L120/1.01 -> 100.66938 | M126: =M120/1.01 -> 110.45631 | O126: =O120/1.01 -> 9.1455528 | P126: =P120/1.01 -> 9.3534063 | Q126: =Q120/1.01 -> 10.2739 | R126: =R120/1.01 -> 9.1455528 | S126: =S120/1.01 -> 9.3534063 | T126: =T120/1.01 -> 10.2739 | U126: =U120/1.01 -> 9.1455528 | V126: =V120/1.01 -> 9.3534063 | W126: =W120/1.01 -> 10.2739 | AA126: 1.035
B127: Indonesia | C127: Jakarta | D127: APAC | E127: =(331.44*$Y127)*$AA127 -> 167.04576 | F127: =(339.03*$Y127)*$AA127 -> 170.87112 | G127: =(371.99*$Y127)*$AA127 -> 187.48296 | H127: =(331.44*$Y127)*$AA127 -> 167.04576 | I127: =(339.03*$Y127)*$AA127 -> 170.87112 | J127: =(371.99*$Y127)*$AA127 -> 187.48296 | K127: =(331.44*$Y127)*$AA127 -> 167.04576 | L127: =(339.03*$Y127)*$AA127 -> 170.87112 | M127: =(371.99*$Y127)*$AA127 -> 187.48296 | O127: =(30.8*$Y127)*$AA127 -> 15.5232 | P127: =(31.5*$Y127)*$AA127 -> 15.876 | Q127: =(34.6*$Y127)*$AA127 -> 17.4384 | R127: =(30.8*$Y127)*$AA127 -> 15.5232 | S127: =(31.5*$Y127)*$AA127 -> 15.876 | T127: =(34.6*$Y127)*$AA127 -> 17.4384 | U127: =(30.8*$Y127)*$AA127 -> 15.5232 | V127: =(31.5*$Y127)*$AA127 -> 15.876 | W127: =(34.6*$Y127)*$AA127 -> 17.4384 | Y127: 0.48 | AA127: 1.05
B128: Japan | C128: Tokyo | D128: APAC | E128: =(331.44*$Y128)*$AA128 -> 378.09763 | F128: =(339.03*$Y128)*$AA128 -> 386.75609 | G128: =(371.99*$Y128)*$AA128 -> 424.35596 | H128: =(331.44*$Y128)*$AA128 -> 378.09763 | I128: =(339.03*$Y128)*$AA128 -> 386.75609 | J128: =(371.99*$Y128)*$AA128 -> 424.35596 | K128: =(331.44*$Y128)*$AA128 -> 378.09763 | L128: =(339.03*$Y128)*$AA128 -> 386.75609 | M128: =(371.99*$Y128)*$AA128 -> 424.35596 | O128: =(30.8*$Y128)*$AA128 -> 35.135792 | P128: =(31.5*$Y128)*$AA128 -> 35.934333 | Q128: =(34.6*$Y128)*$AA128 -> 39.470728 | R128: =(30.8*$Y128)*$AA128 -> 35.135792 | S128: =(31.5*$Y128)*$AA128 -> 35.934333 | T128: =(34.6*$Y128)*$AA128 -> 39.470728 | U128: =(30.8*$Y128)*$AA128 -> 35.135792 | V128: =(31.5*$Y128)*$AA128 -> 35.934333 | W128: =(34.6*$Y128)*$AA128 -> 39.470728 | Y128: 1.135097 | AA128: 1.005
B129: Malaysia | C129: Kuala Lumpur | D129: APAC | E129: =(331.44*$Y129)*$AA129 -> 167.38486 | F129: =(339.03*$Y129)*$AA129 -> 171.21798 | G129: =(371.99*$Y129)*$AA129 -> 187.86354 | H129: =(331.44*$Y129)*$AA129 -> 167.38486 | I129: =(339.03*$Y129)*$AA129 -> 171.21798 | J129: =(371.99*$Y129)*$AA129 -> 187.86354 | K129: =(331.44*$Y129)*$AA129 -> 167.38486 | L129: =(339.03*$Y129)*$AA129 -> 171.21798 | M129: =(371.99*$Y129)*$AA129 -> 187.86354 | O129: =(30.8*$Y129)*$AA129 -> 15.554712 | P129: =(31.5*$Y129)*$AA129 -> 15.908228 | Q129: =(34.6*$Y129)*$AA129 -> 17.473799 | R129: =(30.8*$Y129)*$AA129 -> 15.554712 | S129: =(31.5*$Y129)*$AA129 -> 15.908228 | T129: =(34.6*$Y129)*$AA129 -> 17.473799 | U129: =(30.8*$Y129)*$AA129 -> 15.554712 | V129: =(31.5*$Y129)*$AA129 -> 15.908228 | W129: =(34.6*$Y129)*$AA129 -> 17.473799 | Y129: 0.49512069 | AA129: 1.02
B130: New Zealand | C130: Auckland | D130: APAC | E130: =(331.44*$Y130)*$AA130 -> 234.23624 | F130: =(339.03*$Y130)*$AA130 -> 239.60027 | G130: =(371.99*$Y130)*$AA130 -> 262.89386 | H130: =(331.44*$Y130)*$AA130 -> 234.23624 | I130: =(339.03*$Y130)*$AA130 -> 239.60027 | J130: =(371.99*$Y130)*$AA130 -> 262.89386 | K130: =(331.44*$Y130)*$AA130 -> 234.23624 | L130: =(339.03*$Y130)*$AA130 -> 239.60027 | M130: =(371.99*$Y130)*$AA130 -> 262.89386 | O130: =(30.8*$Y130)*$AA130 -> 21.767066 | P130: =(31.5*$Y130)*$AA130 -> 22.261772 | Q130: =(34.6*$Y130)*$AA130 -> 24.452613 | R130: =(30.8*$Y130)*$AA130 -> 21.767066 | S130: =(31.5*$Y130)*$AA130 -> 22.261772 | T130: =(34.6*$Y130)*$AA130 -> 24.452613 | U130: =(30.8*$Y130)*$AA130 -> 21.767066 | V130: =(31.5*$Y130)*$AA130 -> 22.261772 | W130: =(34.6*$Y130)*$AA130 -> 24.452613 | Y130: 0.66987954 | AA130: 1.055
B131: Pakistan | C131: Karachi | D131: APAC | E131: =(331.44*$Y131)*$AA131 -> 127.6044 | F131: =(339.03*$Y131)*$AA131 -> 130.52655 | G131: =(371.99*$Y131)*$AA131 -> 143.21615 | H131: =(331.44*$Y131)*$AA131 -> 127.6044 | I131: =(339.03*$Y131)*$AA131 -> 130.52655 | J131: =(371.99*$Y131)*$AA131 -> 143.21615 | K131: =(331.44*$Y131)*$AA131 -> 127.6044 | L131: =(339.03*$Y131)*$AA131 -> 130.52655 | M131: =(371.99*$Y131)*$AA131 -> 143.21615 | O131: =(30.8*$Y131)*$AA131 -> 11.858 | P131: =(31.5*$Y131)*$AA131 -> 12.1275 | Q131: =(34.6*$Y131)*$AA131 -> 13.321 | R131: =(30.8*$Y131)*$AA131 -> 11.858 | S131: =(31.5*$Y131)*$AA131 -> 12.1275 | T131: =(34.6*$Y131)*$AA131 -> 13.321 | U131: =(30.8*$Y131)*$AA131 -> 11.858 | V131: =(31.5*$Y131)*$AA131 -> 12.1275 | W131: =(34.6*$Y131)*$AA131 -> 13.321 | Y131: 0.35 | AA131: 1.1
B132: Philippines | C132: Manila | D132: APAC | E132: =(331.44*$Y132)*$AA132 -> 180.9331 | F132: =(339.03*$Y132)*$AA132 -> 185.07648 | G132: =(371.99*$Y132)*$AA132 -> 203.06934 | H132: =(331.44*$Y132)*$AA132 -> 180.9331 | I132: =(339.03*$Y132)*$AA132 -> 185.07648 | J132: =(371.99*$Y132)*$AA132 -> 203.06934 | K132: =(331.44*$Y132)*$AA132 -> 180.9331 | L132: =(339.03*$Y132)*$AA132 -> 185.07648 | M132: =(371.99*$Y132)*$AA132 -> 203.06934 | O132: =(30.8*$Y132)*$AA132 -> 16.81372 | P132: =(31.5*$Y132)*$AA132 -> 17.19585 | Q132: =(34.6*$Y132)*$AA132 -> 18.88814 | R132: =(30.8*$Y132)*$AA132 -> 16.81372 | S132: =(31.5*$Y132)*$AA132 -> 17.19585 | T132: =(34.6*$Y132)*$AA132 -> 18.88814 | U132: =(30.8*$Y132)*$AA132 -> 16.81372 | V132: =(31.5*$Y132)*$AA132 -> 17.19585 | W132: =(34.6*$Y132)*$AA132 -> 18.88814 | Y132: 0.53 | AA132: 1.03
B133: Singapore | C133: Singapore | D133: APAC | E133: =(331.44*$Y133)*$AA133 -> 319.17672 | F133: =(339.03*$Y133)*$AA133 -> 326.48589 | G133: =(371.99*$Y133)*$AA133 -> 358.22637 | H133: =(331.44*$Y133)*$AA133 -> 319.17672 | I133: =(339.03*$Y133)*$AA133 -> 326.48589 | J133: =(371.99*$Y133)*$AA133 -> 358.22637 | K133: =(331.44*$Y133)*$AA133 -> 319.17672 | L133: =(339.03*$Y133)*$AA133 -> 326.48589 | M133: =(371.99*$Y133)*$AA133 -> 358.22637 | O133: =(30.8*$Y133)*$AA133 -> 29.6604 | P133: =(31.5*$Y133)*$AA133 -> 30.3345 | Q133: =(34.6*$Y133)*$AA133 -> 33.3198 | R133: =(30.8*$Y133)*$AA133 -> 29.6604 | S133: =(31.5*$Y133)*$AA133 -> 30.3345 | T133: =(34.6*$Y133)*$AA133 -> 33.3198 | U133: =(30.8*$Y133)*$AA133 -> 29.6604 | V133: =(31.5*$Y133)*$AA133 -> 30.3345 | W133: =(34.6*$Y133)*$AA133 -> 33.3198 | Y133: 0.9 | AA133: 1.07
B134: South Korea | C134: Seoul | D134: APAC | E134: =(331.44*$Y134)*$AA134 -> 191.77118 | F134: =(339.03*$Y134)*$AA134 -> 196.16276 | G134: =(371.99*$Y134)*$AA134 -> 215.23341 | H134: =(331.44*$Y134)*$AA134 -> 191.77118 | I134: =(339.03*$Y134)*$AA134 -> 196.16276 | J134: =(371.99*$Y134)*$AA134 -> 215.23341 | K134: =(331.44*$Y134)*$AA134 -> 191.77118 | L134: =(339.03*$Y134)*$AA134 -> 196.16276 | M134: =(371.99*$Y134)*$AA134 -> 215.23341 | O134: =(30.8*$Y134)*$AA134 -> 17.82088 | P134: =(31.5*$Y134)*$AA134 -> 18.2259 | Q134: =(34.6*$Y134)*$AA134 -> 20.01956 | R134: =(30.8*$Y134)*$AA134 -> 17.82088 | S134: =(31.5*$Y134)*$AA134 -> 18.2259 | T134: =(34.6*$Y134)*$AA134 -> 20.01956 | U134: =(30.8*$Y134)*$AA134 -> 17.82088 | V134: =(31.5*$Y134)*$AA134 -> 18.2259 | W134: =(34.6*$Y134)*$AA134 -> 20.01956 | Y134: 0.55 | AA134: 1.052
B135: Taiwan | C135: Taipei | D135: APAC | E135: =(331.44*$Y135)*$AA135 -> 183.7822 | F135: =(339.03*$Y135)*$AA135 -> 187.99083 | G135: =(371.99*$Y135)*$AA135 -> 206.26702 | H135: =(331.44*$Y135)*$AA135 -> 183.7822 | I135: =(339.03*$Y135)*$AA135 -> 187.99083 | J135: =(371.99*$Y135)*$AA135 -> 206.26702 | K135: =(331.44*$Y135)*$AA135 -> 183.7822 | L135: =(339.03*$Y135)*$AA135 -> 187.99083 | M135: =(371.99*$Y135)*$AA135 -> 206.26702 | O135: =(30.8*$Y135)*$AA135 -> 17.078481 | P135: =(31.5*$Y135)*$AA135 -> 17.466629 | Q135: =(34.6*$Y135)*$AA135 -> 19.185567 | R135: =(30.8*$Y135)*$AA135 -> 17.078481 | S135: =(31.5*$Y135)*$AA135 -> 17.466629 | T135: =(34.6*$Y135)*$AA135 -> 19.185567 | U135: =(30.8*$Y135)*$AA135 -> 17.078481 | V135: =(31.5*$Y135)*$AA135 -> 17.466629 | W135: =(34.6*$Y135)*$AA135 -> 19.185567 | Y135: 0.53368253 | AA135: 1.039
B136: Thailand | C136: Bangkok | D136: APAC | E136: =(331.44*$Y136)*$AA136 -> 110.73537 | F136: =(339.03*$Y136)*$AA136 -> 113.27122 | G136: =(371.99*$Y136)*$AA136 -> 124.28328 | H136: =(331.44*$Y136)*$AA136 -> 110.73537 | I136: =(339.03*$Y136)*$AA136 -> 113.27122 | J136: =(371.99*$Y136)*$AA136 -> 124.28328 | K136: =(331.44*$Y136)*$AA136 -> 110.73537 | L136: =(339.03*$Y136)*$AA136 -> 113.27122 | M136: =(371.99*$Y136)*$AA136 -> 124.28328 | O136: =(30.8*$Y136)*$AA136 -> 10.290397 | P136: =(31.5*$Y136)*$AA136 -> 10.52427 | Q136: =(34.6*$Y136)*$AA136 -> 11.559992 | R136: =(30.8*$Y136)*$AA136 -> 10.290397 | S136: =(31.5*$Y136)*$AA136 -> 10.52427 | T136: =(34.6*$Y136)*$AA136 -> 11.559992 | U136: =(30.8*$Y136)*$AA136 -> 10.290397 | V136: =(31.5*$Y136)*$AA136 -> 10.52427 | W136: =(34.6*$Y136)*$AA136 -> 11.559992 | Y136: 0.33244161 | AA136: 1.005
B137: Vietnam | C137: Hanoi | D137: APAC | E137: =(331.44*$Y137)*$AA137 -> 134.14906 | F137: =(339.03*$Y137)*$AA137 -> 137.22108 | G137: =(371.99*$Y137)*$AA137 -> 150.56152 | H137: =(331.44*$Y137)*$AA137 -> 134.14906 | I137: =(339.03*$Y137)*$AA137 -> 137.22108 | J137: =(371.99*$Y137)*$AA137 -> 150.56152 | K137: =(331.44*$Y137)*$AA137 -> 134.14906 | L137: =(339.03*$Y137)*$AA137 -> 137.22108 | M137: =(371.99*$Y137)*$AA137 -> 150.56152 | O137: =(30.8*$Y137)*$AA137 -> 12.466181 | P137: =(31.5*$Y137)*$AA137 -> 12.749503 | Q137: =(34.6*$Y137)*$AA137 -> 14.004217 | R137: =(30.8*$Y137)*$AA137 -> 12.466181 | S137: =(31.5*$Y137)*$AA137 -> 12.749503 | T137: =(34.6*$Y137)*$AA137 -> 14.004217 | U137: =(30.8*$Y137)*$AA137 -> 12.466181 | V137: =(31.5*$Y137)*$AA137 -> 12.749503 | W137: =(34.6*$Y137)*$AA137 -> 14.004217 | Y137: 0.39105908 | AA137: 1.035
B138: United Kingdom | C138: London | D138: EMEA | E138: =(331.44*$Y138)*$AA138 -> 353.64648 | F138: =(339.03*$Y138)*$AA138 -> 361.74501 | G138: =(371.99*$Y138)*$AA138 -> 396.91333 | H138: =(331.44*$Y138)*$AA138 -> 353.64648 | I138: =(339.03*$Y138)*$AA138 -> 361.74501 | J138: =(371.99*$Y138)*$AA138 -> 396.91333 | K138: =(331.44*$Y138)*$AA138 -> 353.64648 | L138: =(339.03*$Y138)*$AA138 -> 361.74501 | M138: =(371.99*$Y138)*$AA138 -> 396.91333 | O138: =(30.8*$Y138)*$AA138 -> 32.8636 | P138: =(31.5*$Y138)*$AA138 -> 33.6105 | Q138: =(34.6*$Y138)*$AA138 -> 36.9182 | R138: =(30.8*$Y138)*$AA138 -> 32.8636 | S138: =(31.5*$Y138)*$AA138 -> 33.6105 | T138: =(34.6*$Y138)*$AA138 -> 36.9182 | U138: =(30.8*$Y138)*$AA138 -> 32.8636 | V138: =(31.5*$Y138)*$AA138 -> 33.6105 | W138: =(34.6*$Y138)*$AA138 -> 36.9182 | Y138: 1 | AA138: 1.067
B139: Zimbabwe | C139: Harare | D139: EMEA | E139: =(331.44*$Y139)*$AA139 -> 206.81856 | F139: =(339.03*$Y139)*$AA139 -> 211.55472 | G139: =(371.99*$Y139)*$AA139 -> 232.12176 | H139: =(331.44*$Y139)*$AA139 -> 206.81856 | I139: =(339.03*$Y139)*$AA139 -> 211.55472 | J139: =(371.99*$Y139)*$AA139 -> 232.12176 | K139: =(331.44*$Y139)*$AA139 -> 206.81856 | L139: =(339.03*$Y139)*$AA139 -> 211.55472 | M139: =(371.99*$Y139)*$AA139 -> 232.12176 | O139: =(30.8*$Y139)*$AA139 -> 19.2192 | P139: =(31.5*$Y139)*$AA139 -> 19.656 | Q139: =(34.6*$Y139)*$AA139 -> 21.5904 | R139: =(30.8*$Y139)*$AA139 -> 19.2192 | S139: =(31.5*$Y139)*$AA139 -> 19.656 | T139: =(34.6*$Y139)*$AA139 -> 21.5904 | U139: =(30.8*$Y139)*$AA139 -> 19.2192 | V139: =(31.5*$Y139)*$AA139 -> 19.656 | W139: =(34.6*$Y139)*$AA139 -> 21.5904 | Y139: 0.6 | AA139: 1.04
H147: 0.09290304
I149: =E139*H147 -> 19.214073

Sheet Table 1_Activity BYOB Sqm
E1: ACTIVITY SPACE
E2: FIT OUT $/M2 | I2: FURNITURE $/M2 | M2: TECHNOLOGY $/M2 | Q2: 2023 Professional Fees (%) | X2: TOTAL FITOUT COST $/M2
E4: Low | F4: Medium | G4: High | I4: Low | J4: Medium | K4: High | M4: Low | N4: Medium | O4: High | X4: Low | Y4: Medium | Z4: High
B5: COUNTRY | C5: CITY | D5: REGION | Q5: Arch | R5: M&E Eng | S5: PM | T5: QS | U5: Other | V5: Total
B6: United States | C6: Cincinnati | D6: AMERICAS | E6: 1812.7573 | F6: 2640.9279 | G6: 3159.8936 | I6: 187.98909 | J6: 248.4105 | K6: 287.63363 | M6: 412.61379 | N6: 422.06268 | O6: 463.09499 | Q6: 0.08 | R6: 0.05 | S6: 0.03 | T6: 0.015 | U6: 0.02 | V6: =SUBTOTAL(9,Q6:U6) -> 0 | X6: =(E6+I6+M6)*(1+V6) -> 2413.3602 | Y6: =(F6+J6+N6)*(1+V6) -> 3311.4011 | Z6: =(G6+K6+O6)*(1+V6) -> 3910.6222
B7: United States | C7: Charlotte | D7: AMERICAS | E7: 1693.3113 | F7: 2466.1542 | G7: 2950.4485 | I7: 175.60213 | J7: 232.04226 | K7: 268.6809 | M7: 385.42588 | N7: 394.25216 | O7: 432.58078 | Q7: 0.08 | R7: 0.05 | S7: 0.03 | T7: 0.015 | U7: 0.02 | V7: =SUBTOTAL(9,Q7:U7) -> 0 | X7: =(E7+I7+M7)*(1+V7) -> 2254.3393 | Y7: =(F7+J7+N7)*(1+V7) -> 3092.4486 | Z7: =(G7+K7+O7)*(1+V7) -> 3651.7102
B8: United States | C8: Charleston (SC) | D8: AMERICAS | E8: 1693.3113 | F8: 2466.1542 | G8: 2950.4485 | I8: 175.60213 | J8: 232.04226 | K8: 268.6809 | M8: 385.42588 | N8: 394.25216 | O8: 432.58078 | Q8: 0.08 | R8: 0.05 | S8: 0.03 | T8: 0.015 | U8: 0.02 | V8: =SUBTOTAL(9,Q8:U8) -> 0 | X8: =(E8+I8+M8)*(1+V8) -> 2254.3393 | Y8: =(F8+J8+N8)*(1+V8) -> 3092.4486 | Z8: =(G8+K8+O8)*(1+V8) -> 3651.7102
B9: United States | C9: Chicago | D9: AMERICAS | E9: 2218.4928 | F9: 3234.6057 | G9: 3871.3426 | I9: 230.06524 | J9: 304.01031 | K9: 352.01244 | M9: 504.96594 | N9: 516.5297 | O9: 566.74596 | Q9: 0.08 | R9: 0.05 | S9: 0.03 | T9: 0.015 | U9: 0.02 | V9: =SUBTOTAL(9,Q9:U9) -> 0 | X9: =(E9+I9+M9)*(1+V9) -> 2953.524 | Y9: =(F9+J9+N9)*(1+V9) -> 4055.1457 | Z9: =(G9+K9+O9)*(1+V9) -> 4790.101
B10: United States | C10: Cleveland | D10: AMERICAS | E10: 1758.2914 | F10: 2556.5694 | G10: 3071.177 | I10: 182.34079 | J10: 240.94679 | K10: 278.99142 | M10: 400.21644 | N10: 409.38142 | O10: 449.18088 | Q10: 0.08 | R10: 0.05 | S10: 0.03 | T10: 0.015 | U10: 0.02 | V10: =SUBTOTAL(9,Q10:U10) -> 0 | X10: =(E10+I10+M10)*(1+V10) -> 2340.8486 | Y10: =(F10+J10+N10)*(1+V10) -> 3206.8976 | Z10: =(G10+K10+O10)*(1+V10) -> 3799.3493
B11: United States | C11: Boston | D11: AMERICAS | E11: 2159.7181 | F11: 3148.6057 | G11: 3768.2819 | I11: 223.9701 | J11: 295.95613 | K11: 342.68654 | M11: 491.58783 | N11: 502.84523 | O11: 551.73111 | Q11: 0.08 | R11: 0.05 | S11: 0.03 | T11: 0.015 | U11: 0.02 | V11: =SUBTOTAL(9,Q11:U11) -> 0 | X11: =(E11+I11+M11)*(1+V11) -> 2875.276 | Y11: =(F11+J11+N11)*(1+V11) -> 3947.407 | Z11: =(G11+K11+O11)*(1+V11) -> 4662.6996
B12: United States | C12: Baltimore | D12: AMERICAS | E12: 1765.812 | F12: 2572.7882 | G12: 3092.4575 | I12: 183.12071 | J12: 241.97737 | K12: 280.18473 | M12: 401.92826 | N12: 411.13244 | O12: 451.10214 | Q12: 0.08 | R12: 0.05 | S12: 0.03 | T12: 0.015 | U12: 0.02 | V12: =SUBTOTAL(9,Q12:U12) -> 0 | X12: =(E12+I12+M12)*(1+V12) -> 2350.861 | Y12: =(F12+J12+N12)*(1+V12) -> 3225.898 | Z12: =(G12+K12+O12)*(1+V12) -> 3823.7444
B13: United States | C13: Columbus | D13: AMERICAS | E13: 1717.8081 | F13: 2497.4426 | G13: 3000.0318 | I13: 178.14253 | J13: 235.39917 | K13: 272.56785 | M13: 391.00175 | N13: 399.95572 | O13: 438.83883 | Q13: 0.08 | R13: 0.05 | S13: 0.03 | T13: 0.015 | U13: 0.02 | V13: =SUBTOTAL(9,Q13:U13) -> 0 | X13: =(E13+I13+M13)*(1+V13) -> 2286.9523 | Y13: =(F13+J13+N13)*(1+V13) -> 3132.7975 | Z13: =(G13+K13+O13)*(1+V13) -> 3711.4385
B14: United States | C14: Austin | D14: AMERICAS | E14: 1612.2665 | F14: 2322.8329 | G14: 2795.9229 | I14: 167.19752 | J14: 220.93632 | K14: 255.82138 | M14: 366.97874 | N14: 375.38258 | O14: 411.87673 | Q14: 0.08 | R14: 0.05 | S14: 0.03 | T14: 0.015 | U14: 0.02 | V14: =SUBTOTAL(9,Q14:U14) -> 0 | X14: =(E14+I14+M14)*(1+V14) -> 2146.4428 | Y14: =(F14+J14+N14)*(1+V14) -> 2919.1518 | Z14: =(G14+K14+O14)*(1+V14) -> 3463.621
B15: United States | C15: Atlanta | D15: AMERICAS | E15: 1701.2466 | F15: 2518.81 | G15: 3020.0353 | I15: 176.42506 | J15: 233.12968 | K15: 269.94002 | M15: 387.2321 | N15: 396.09974 | O15: 434.60798 | Q15: 0.08 | R15: 0.05 | S15: 0.03 | T15: 0.015 | U15: 0.02 | V15: =SUBTOTAL(9,Q15:U15) -> 0 | X15: =(E15+I15+M15)*(1+V15) -> 2264.9038 | Y15: =(F15+J15+N15)*(1+V15) -> 3148.0395 | Z15: =(G15+K15+O15)*(1+V15) -> 3724.5833
B16: United States | C16: Dallas | D16: AMERICAS | E16: 1620.2795 | F16: 2355 | G16: 2828.6365 | I16: 168.02849 | J16: 222.03437 | K16: 257.0928 | M16: 368.80262 | N16: 377.24822 | O16: 413.92374 | Q16: 0.08 | R16: 0.05 | S16: 0.03 | T16: 0.015 | U16: 0.02 | V16: =SUBTOTAL(9,Q16:U16) -> 0 | X16: =(E16+I16+M16)*(1+V16) -> 2157.1106 | Y16: =(F16+J16+N16)*(1+V16) -> 2954.2826 | Z16: =(G16+K16+O16)*(1+V16) -> 3499.653
B17: United States | C17: Denver | D17: AMERICAS | E17: 1730.6892 | F17: 2516.2556 | G17: 3022.6688 | I17: 179.47835 | J17: 237.16433 | K17: 274.61173 | M17: 393.93372 | N17: 402.95483 | O17: 442.12951 | Q17: 0.08 | R17: 0.05 | S17: 0.03 | T17: 0.015 | U17: 0.02 | V17: =SUBTOTAL(9,Q17:U17) -> 0 | X17: =(E17+I17+M17)*(1+V17) -> 2304.1013 | Y17: =(F17+J17+N17)*(1+V17) -> 3156.3748 | Z17: =(G17+K17+O17)*(1+V17) -> 3739.4101
... B70: Canada | C70: Toronto | D70: AMERICAS | E70: 1377.88 | F70: 2181.52 | G70: 2931.88 | I70: 143.238 | J70: 189.276 | K70: 219.162 | M70: 301.58388 | N70: 308.49018 | O70: 338.48114 | Q70: 0.08 | R70: 0.05 | S70: 0.03 | T70: 0.015 | U70: 0.02 | V70: =SUBTOTAL(9,Q70:U70) -> 0 | X70: =(E70+I70+M70)*(1+V70) -> 1822.7019 | Y70: =(F70+J70+N70)*(1+V70) -> 2679.2862 | Z70: =(G70+K70+O70)*(1+V70) -> 3489.5231
B71: Canada | C71: Montreal | D71: AMERICAS | E71: =E$25*0.58 -> 960.04103 | F71: =F$25*0.58 -> 1395.5172 | G71: =G$25*0.58 -> 1676.2467 | I71: 138.4634 | J71: 182.9668 | K71: 211.8566 | M71: 292.31974 | N71: 299.01389 | O71: 328.08358 | Q71: 0.08 | R71: 0.05 | S71: 0.03 | T71: 0.015 | U71: 0.02 | V71: =SUBTOTAL(9,Q71:U71) -> 0 | X71: =(E71+I71+M71)*(1+V71) -> 1390.8242 | Y71: =(F71+J71+N71)*(1+V71) -> 1877.4979 | Z71: =(G71+K71+O71)*(1+V71) -> 2216.1869
B72: Canada | C72: Vancouver | D72: AMERICAS | E72: =E$25*0.58 -> 960.04103 | F72: =F$25*0.58 -> 1395.5172 | G72: =G$25*0.58 -> 1676.2467 | I72: 138.4634 | J72: 182.9668 | K72: 211.8566 | M72: 292.31974 | N72: 299.01389 | O72: 328.08358 | Q72: 0.08 | R72: 0.05 | S72: 0.03 | T72: 0.015 | U72: 0.02 | V72: =SUBTOTAL(9,Q72:U72) -> 0 | X72: =(E72+I72+M72)*(1+V72) -> 1390.8242 | Y72: =(F72+J72+N72)*(1+V72) -> 1877.4979 | Z72: =(G72+K72+O72)*(1+V72) -> 2216.1869
B73: Canada | C73: Ottawa | D73: AMERICAS | E73: =E$25*0.59 -> 976.59347 | F73: =F$25*0.59 -> 1419.5778 | G73: =G$25*0.59 -> 1705.1475 | I73: 140.8507 | J73: 186.1214 | K73: 215.5093 | M73: 297.35974 | N73: 304.1693 | O73: 333.74019 | Q73: 0.08 | R73: 0.05 | S73: 0.03 | T73: 0.015 | U73: 0.02 | V73: =SUBTOTAL(9,Q73:U73) -> 0 | X73: =(E73+I73+M73)*(1+V73) -> 1414.8039 | Y73: =(F73+J73+N73)*(1+V73) -> 1909.8685 | Z73: =(G73+K73+O73)*(1+V73) -> 2254.397
B74: Austria | C74: Vienna | D74: EMEA | E74: 873.74731 | F74: 1173.392 | G74: 1411.0911 | I74: 133.38384 | J74: 187.1268 | K74: 219.95734 | M74: 197.95443 | N74: 202.48761 | O74: 222.17315 | Q74: 0.05 | R74: 0.08 | S74: 0.08 | T74: 0.012 | U74: 0.02 | V74: =SUBTOTAL(9,Q74:U74) -> 0 | X74: =(E74+I74+M74)*(1+V74) -> 1205.0856 | Y74: =(F74+J74+N74)*(1+V74) -> 1563.0064 | Z74: =(G74+K74+O74)*(1+V74) -> 1853.2216
B75: Belgium | C75: Brussels | D75: EMEA | E75: 913.27347 | F75: 1302.7311 | G75: 1620.4621 | I75: 139.41779 | J75: 195.59195 | K75: 229.90766 | M75: 207.87627 | N75: 212.63665 | O75: 233.30887 | Q75: lump sum | R75: 0.05 | S75: 0.09 | T75: 0.07 | U75: 0.05 | V75: =SUBTOTAL(9,Q75:U75) -> 0 | X75: =(E75+I75+M75)*(1+V75) -> 1260.5675 | Y75: =(F75+J75+N75)*(1+V75) -> 1710.9597 | Z75: =(G75+K75+O75)*(1+V75) -> 2083.6786
B76: Botswana | C76: Gabarone | D76: EMEA | E76: 860.94069 | F76: 1268.7336 | G76: 1716.5762 | I76: 131.42881 | J76: 184.38406 | K76: 216.73339 | M76: 191.40714 | N76: 195.79038 | O76: 214.82483 | Q76: 0.05 | R76: 0.02 | S76: 0.04 | T76: 0.03 | U76: 0.02 | V76: =SUBTOTAL(9,Q76:U76) -> 0 | X76: =(E76+I76+M76)*(1+V76) -> 1183.7766 | Y76: =(F76+J76+N76)*(1+V76) -> 1648.9081 | Z76: =(G76+K76+O76)*(1+V76) -> 2148.1344
B77: Bulgaria | C77: Sofia | D77: EMEA | E77: 967.29903 | F77: 967.29903 | G77: 967.29903 | I77: 147.66553 | J77: 207.16287 | K77: 243.50864 | M77: 215.05358 | N77: 219.97832 | O77: 241.36429 | Q77: 0.045 | R77: 0.005 | S77: 0.07 | T77: 0.03 | U77: 0 | V77: =SUBTOTAL(9,Q77:U77) -> 0 | X77: =(E77+I77+M77)*(1+V77) -> 1330.0181 | Y77: =(F77+J77+N77)*(1+V77) -> 1394.4402 | Z77: =(G77+K77+O77)*(1+V77) -> 1452.172
B78: Croatia | C78: Zagreb | D78: EMEA | E78: 1058.3843 | F78: 1058.3843 | G78: 1058.3843 | I78: 161.5634 | J78: 226.66047 | K78: 266.427 | M78: 235.29383 | N78: 240.68208 | O78: 264.08084 | Q78: 0.045 | R78: 0.005 | S78: 0.07 | T78: 0.03 | U78: n/a | V78: =SUBTOTAL(9,Q78:U78) -> 0 | X78: =(E78+I78+M78)*(1+V78) -> 1455.2415 | Y78: =(F78+J78+N78)*(1+V78) -> 1525.7268 | Z78: =(G78+K78+O78)*(1+V78) -> 1588.8921
B79: Czech Republic | C79: Prague | D79: EMEA | E79: 504.76086 | F79: 844.20455 | G79: 1154.8402 | I79: 77.055389 | J79: 108.10252 | K79: 127.06861 | M79: 114.89199 | N79: 117.52302 | O79: 128.94844 | Q79: 0.031 | R79: 0.054 | S79: 0.086 | T79: 0.016 | U79: 0.005 | V79: =SUBTOTAL(9,Q79:U79) -> 0 | X79: =(E79+I79+M79)*(1+V79) -> 696.70823 | Y79: =(F79+J79+N79)*(1+V79) -> 1069.8301 | Z79: =(G79+K79+O79)*(1+V79) -> 1410.8573
B80: Denmark | C80: Copenhagen | D80: EMEA | E80: 1346.7416 | F80: 1835.0192 | G80: 2580.5625 | I80: 205.58983 | J80: 288.42601 | K80: 339.02902 | M80: 299.41198 | N80: 306.26854 | O80: 336.04352 | V80: 0.24 | X80: =(E80+I80+M80)*(1+V80) -> 2296.1618 | Y80: =(F80+J80+N80)*(1+V80) -> 3012.8451 | Z80: =(G80+K80+O80)*(1+V80) -> 4036.9875
B81: Ethiopia | C81: Addis Ababa | D81: EMEA | E81: 828.67683 | F81: 1147.6344 | G81: 1833.9745 | I81: 126.5035 | J81: 177.47425 | K81: 208.61128 | M81: 182.47952 | N81: 186.65832 | O81: 204.80497 | Q81: 0.05 | R81: 0.02 | S81: 0.04 | T81: 0.03 | U81: 0.02 | V81: =SUBTOTAL(9,Q81:U81) -> 0 | X81: =(E81+I81+M81)*(1+V81) -> 1137.6599 | Y81: =(F81+J81+N81)*(1+V81) -> 1511.767 | Z81: =(G81+K81+O81)*(1+V81) -> 2247.3908
B82: Finland | C82: Helsinki | D82: EMEA | E82: 1237.1231 | F82: 1685.6572 | G82: 2370.5167 | I82: 188.85577 | J82: 264.94947 | K82: 311.43363 | M82: 275.04124 | N82: 281.3397 | O82: 308.69114 | Q82: 0.04 | R82: 0.04 | S82: 0.08 | T82: 0.005 | U82: 0.02 | V82: =SUBTOTAL(9,Q82:U82) -> 0 | X82: =(E82+I82+M82)*(1+V82) -> 1701.0201 | Y82: =(F82+J82+N82)*(1+V82) -> 2231.9464 | Z82: =(G82+K82+O82)*(1+V82) -> 2990.6415
B83: France | C83: Paris | D83: EMEA | E83: 1315.422 | F83: 1792.3444 | G83: 2520.5494 | I83: 200.80867 | J83: 281.71843 | K83: 331.14462 | M83: 292.44891 | N83: 299.14601 | O83: 328.22855 | Q83: 0.1 | R83: 0.04 | S83: 0.03 | T83: 0.02 | U83: n/a | V83: =SUBTOTAL(9,Q83:U83) -> 0 | X83: =(E83+I83+M83)*(1+V83) -> 1808.6796 | Y83: =(F83+J83+N83)*(1+V83) -> 2373.2088 | Z83: =(G83+K83+O83)*(1+V83) -> 3179.9226
B84: Germany | C84: Cologne | D84: EMEA | E84: 1218.5938 | F84: 1429.1247 | G84: 1720.9362 | I84: 186.02714 | J84: 260.98113 | K84: 306.76906 | M84: 277.37226 | N84: 283.72411 | O84: 311.30735 | Q84: 0.12 | R84: 0.06 | S84: 0.05 | T84: 0.03 | U84: n/a | V84: =SUBTOTAL(9,Q84:U84) -> 0 | X84: =(E84+I84+M84)*(1+V84) -> 1681.9932 | Y84: =(F84+J84+N84)*(1+V84) -> 1973.8299 | Z84: =(G84+K84+O84)*(1+V84) -> 2339.0126
B85: Ghana | C85: Accra | D85: EMEA | E85: 954.49576 | F85: 1403.1196 | G85: 1891.0942 | I85: 145.71067 | J85: 204.42036 | K85: 240.28497 | M85: 210.18559 | N85: 214.99886 | O85: 235.90073 | Q85: 0.05 | R85: 0.02 | S85: 0.04 | T85: 0.03 | U85: 0.02 | V85: =SUBTOTAL(9,Q85:U85) -> 0 | X85: =(E85+I85+M85)*(1+V85) -> 1310.392 | Y85: =(F85+J85+N85)*(1+V85) -> 1822.5388 | Z85: =(G85+K85+O85)*(1+V85) -> 2367.2799
B86: Hungary | C86: Budapest | D86: EMEA | E86: 971.50637 | F86: 1262.3664 | G86: 1412.3895 | I86: 148.30746 | J86: 208.06345 | K86: 244.56722 | M86: 215.98846 | N86: 220.93462 | O86: 242.41356 | Q86: 0.06 | R86: 0.04 | S86: 0.07 | T86: 0.03 | U86: 0.03 | V86: =SUBTOTAL(9,Q86:U86) -> 0 | X86: =(E86+I86+M86)*(1+V86) -> 1335.8023 | Y86: =(F86+J86+N86)*(1+V86) -> 1691.3645 | Z86: =(G86+K86+O86)*(1+V86) -> 1899.3703
B87: Ireland | C87: Dublin | D87: EMEA | E87: 1152.6034 | F87: 1576.491 | G87: 2005.5599 | I87: 175.95322 | J87: 246.84823 | K87: 290.15662 | M87: 261.1315 | N87: 267.11143 | O87: 293.07961 | Q87: 0.033 | R87: 0.015 | S87: 0.025 | T87: included | U87: 0.018 | V87: =SUBTOTAL(9,Q87:U87) -> 0 | X87: =(E87+I87+M87)*(1+V87) -> 1589.6881 | Y87: =(F87+J87+N87)*(1+V87) -> 2090.4506 | Z87: =(G87+K87+O87)*(1+V87) -> 2588.7961
B88: Israel | C88: Tel Aviv | D88: EMEA | E88: 1170.9677 | F88: 1170.9677 | G88: 1170.9677 | I88: 178.75836 | J88: 250.78361 | K88: 294.78244 | M88: 269.26161 | N88: 275.42772 | O88: 302.2044 | Q88: 0.05 | R88: 0.02 | S88: 0.05 | T88: 0.02 | U88: 0.03 | V88: =SUBTOTAL(9,Q88:U88) -> 0.17 | X88: =(E88+I88+M88)*(1+V88) -> 1894.2156 | Y88: =(F88+J88+N88)*(1+V88) -> 1985.6995 | Z88: =(G88+K88+O88)*(1+V88) -> 2068.5068
B89: Italy | C89: Rome | D89: EMEA | E89: 686.05942 | F89: 1162.8963 | G89: 1660.5453 | I89: 116.90696 | J89: 164.01108 | K89: 192.78606 | M89: 174.31193 | N89: 178.30368 | O89: 195.6381 | Q89: 0.05 | R89: 0.04 | S89: 0.02 | T89: 0.01 | U89: 0.02 | V89: =SUBTOTAL(9,Q89:U89) -> 0 | X89: =(E89+I89+M89)*(1+V89) -> 977.27831 | Y89: =(F89+J89+N89)*(1+V89) -> 1505.2111 | Z89: =(G89+K89+O89)*(1+V89) -> 2048.9695
B90: Kenya | C90: Nairobi | D90: EMEA | E90: 746.20234 | F90: 1095.9435 | G90: 1467.9148 | I90: 113.91317 | J90: 159.81103 | K90: 187.84914 | M90: 164.31816 | N90: 168.08105 | O90: 184.42165 | Q90: 0.05 | R90: 0.02 | S90: 0.04 | T90: 0.03 | U90: 0.02 | V90: =SUBTOTAL(9,Q90:U90) -> 0 | X90: =(E90+I90+M90)*(1+V90) -> 1024.4337 | Y90: =(F90+J90+N90)*(1+V90) -> 1423.8356 | Z90: =(G90+K90+O90)*(1+V90) -> 1840.1855
B91: Luxembourg | C91: Luxembourg | D91: EMEA | E91: 1009.3824 | F91: 1402.82 | G91: 1669.1711 | I91: 154.08951 | J91: 216.1752 | K91: 254.10214 | M91: 224.40919 | N91: 229.54817 | O91: 251.86451 | V91: 0.22 | X91: =(E91+I91+M91)*(1+V91) -> 1693.2149 | Y91: =(F91+J91+N91)*(1+V91) -> 2255.2229 | Z91: =(G91+K91+O91)*(1+V91) -> 2653.668
B92: Morocco | C92: Casablanca | D92: EMEA | E92: 1234.5493 | F92: 1682.1503 | G92: 2365.585 | I92: 188.46287 | J92: 264.39826 | K92: 310.78571 | M92: 271.85504 | N92: 278.08054 | O92: 305.11512 | Q92: 0.05 | R92: 0.02 | S92: 0.04 | T92: 0.03 | U92: 0.02 | V92: =SUBTOTAL(9,Q92:U92) -> 0 | X92: =(E92+I92+M92)*(1+V92) -> 1694.8672 | Y92: =(F92+J92+N92)*(1+V92) -> 2224.6291 | Z92: =(G92+K92+O92)*(1+V92) -> 2981.4858
B93: Netherlands | C93: Amsterdam | D93: EMEA | E93: 752.0674 | F93: 1066.1324 | G93: 1396.1473 | I93: 114.80852 | J93: 161.06713 | K93: 189.32561 | M93: 167.99828 | N93: 171.84545 | O93: 188.55201 | Q93: 0.04 | R93: 0.03 | S93: 0.06 | T93: 0.025 | U93: 0.02 | V93: =SUBTOTAL(9,Q93:U93) -> 0 | X93: =(E93+I93+M93)*(1+V93) -> 1034.8742 | Y93: =(F93+J93+N93)*(1+V93) -> 1399.0449 | Z93: =(G93+K93+O93)*(1+V93) -> 1774.0249
B94: Nigeria | C94: Abuja | D94: EMEA | E94: 963.3358 | F94: 1403.529 | G94: 1992.835 | I94: 147.06016 | J94: 206.31359 | K94: 242.51036 | M94: 212.13222 | N94: 216.99007 | O94: 238.08552 | Q94: 0.05 | R94: 0.02 | S94: 0.04 | T94: 0.03 | U94: 0.02 | V94: =SUBTOTAL(9,Q94:U94) -> 0 | X94: =(E94+I94+M94)*(1+V94) -> 1322.5282 | Y94: =(F94+J94+N94)*(1+V94) -> 1826.8327 | Z94: =(G94+K94+O94)*(1+V94) -> 2473.4309
B95: Norway | C95: Oslo | D95: EMEA | E95: 1248.9141 | F95: 1701.7231 | G95: 2393.11 | I95: 190.65575 | J95: 267.47469 | K95: 314.40189 | M95: 277.66265 | N95: 284.02114 | O95: 311.63326 | Q95: 0.04 | R95: 0.04 | S95: 0.08 | T95: 0.005 | U95: 0.02 | V95: =SUBTOTAL(9,Q95:U95) -> 0 | X95: =(E95+I95+M95)*(1+V95) -> 1717.2325 | Y95: =(F95+J95+N95)*(1+V95) -> 2253.219 | Z95: =(G95+K95+O95)*(1+V95) -> 3019.1452
B96: Poland | C96: Warsaw | D96: EMEA | E96: 1002.5789 | F96: 1381.4179 | G96: 1639.8664 | I96: 153.05091 | J96: 214.71813 | K96: 252.38944 | M96: 228.20368 | N96: 233.42956 | O96: 256.12324 | V96: 0.14 | X96: =(E96+I96+M96)*(1+V96) -> 1577.5702 | Y96: =(F96+J96+N96)*(1+V96) -> 2085.7048 | Z96: =(G96+K96+O96)*(1+V96) -> 2449.1522
B97: Romania | C97: Bucharest | D97: EMEA | E97: 791.21266 | F97: 1361.3709 | G97: 1695.3627 | I97: 120.78432 | J97: 169.4507 | K97: 199.18004 | M97: 176.74262 | N97: 180.79004 | O97: 198.36618 | Q97: 0.04 | R97: 0.03 | S97: 0.06 | T97: 0.04 | U97: 0.02 | V97: =SUBTOTAL(9,Q97:U97) -> 0 | X97: =(E97+I97+M97)*(1+V97) -> 1088.7396 | Y97: =(F97+J97+N97)*(1+V97) -> 1711.6117 | Z97: =(G97+K97+O97)*(1+V97) -> 2092.9089
B98: Rwanda | C98: Kigali | D98: EMEA | E98: 825.60974 | F98: 1270.6612 | G98: 1716.0124 | I98: 126.03529 | J98: 176.81738 | K98: 207.83917 | M98: 181.80413 | N98: 185.96746 | O98: 204.04694 | Q98: 0.05 | R98: 0.02 | S98: 0.04 | T98: 0.03 | U98: 0.02 | V98: =SUBTOTAL(9,Q98:U98) -> 0 | X98: =(E98+I98+M98)*(1+V98) -> 1133.4492 | Y98: =(F98+J98+N98)*(1+V98) -> 1633.4461 | Z98: =(G98+K98+O98)*(1+V98) -> 2127.8985
B99: Senegal | C99: Dakar | D99: EMEA | E99: 960.78474 | F99: 1330.5906 | G99: 2126.3473 | I99: 146.67073 | J99: 205.76724 | K99: 241.86815 | M99: 211.57046 | N99: 216.41544 | O99: 237.45504 | Q99: 0.05 | R99: 0.02 | S99: 0.04 | T99: 0.03 | U99: 0.02 | V99: =SUBTOTAL(9,Q99:U99) -> 0 | X99: =(E99+I99+M99)*(1+V99) -> 1319.0259 | Y99: =(F99+J99+N99)*(1+V99) -> 1752.7733 | Z99: =(G99+K99+O99)*(1+V99) -> 2605.6705
B100: Serbia | C100: Belgrade | D100: EMEA | E100: 925.8187 | F100: 925.8187 | G100: 925.8187 | I100: 141.33288 | J100: 198.27867 | K100: 233.06574 | M100: 205.83098 | N100: 210.54453 | O100: 231.01336 | Q100: 0.045 | R100: 0.005 | S100: 0.07 | T100: 0.03 | U100: n/a | V100: =SUBTOTAL(9,Q100:U100) -> 0 | X100: =(E100+I100+M100)*(1+V100) -> 1272.9826 | Y100: =(F100+J100+N100)*(1+V100) -> 1334.6419 | Z100: =(G100+K100+O100)*(1+V100) -> 1389.8978
B101: Slovakia | C101: Bratislava | D101: EMEA | E101: 1442.5164 | F101: 1664.3682 | G101: 1801.1298 | I101: 220.21055 | J101: 308.9377 | K101: 363.13939 | M101: 354.30262 | N101: 362.41617 | O101: 397.64974 | V101: 0.192 | X101: =(E101+I101+M101)*(1+V101) -> 2404.2993 | Y101: =(F101+J101+N101)*(1+V101) -> 2784.1808 | Z101: =(G101+K101+O101)*(1+V101) -> 3053.8073
B102: Slovenia | C102: Ljubljana | D102: EMEA | E102: 1137.7633 | F102: 1137.7633 | G102: 1137.7633 | I102: 173.69516 | J102: 243.68035 | K102: 286.43294 | M102: 252.96199 | N102: 258.75484 | O102: 283.91061 | Q102: 0.045 | R102: 0.005 | S102: 0.07 | T102: 0.03 | U102: n/a | V102: =SUBTOTAL(9,Q102:U102) -> 0 | X102: =(E102+I102+M102)*(1+V102) -> 1564.4205 | Y102: =(F102+J102+N102)*(1+V102) -> 1640.1985 | Z102: =(G102+K102+O102)*(1+V102) -> 1708.1068
B103: South Africa | C103: Johannesburg | D103: EMEA | E103: 767.68974 | F103: 1088.4363 | G103: 1356.516 | I103: 117.19338 | J103: 164.4129 | K103: 193.25838 | M103: 169.04981 | N103: 172.92106 | O103: 189.73219 | Q103: 0.05 | R103: 0.02 | S103: 0.04 | T103: 0.03 | U103: 0.02 | V103: =SUBTOTAL(9,Q103:U103) -> 0 | X103: =(E103+I103+M103)*(1+V103) -> 1053.9329 | Y103: =(F103+J103+N103)*(1+V103) -> 1425.7702 | Z103: =(G103+K103+O103)*(1+V103) -> 1739.5066
B104: Spain | C104: Madrid | D104: EMEA | E104: 686.05942 | F104: 1162.8963 | G104: 1660.5453 | I104: 104.73192 | J104: 146.93047 | K104: 172.70874 | M104: 168.50598 | N104: 172.36478 | O104: 189.12183 | Q104: 0.05 | R104: 0.03 | S104: 0.03 | T104: 0.02 | U104: 0.05 | V104: =SUBTOTAL(9,Q104:U104) -> 0 | X104: =(E104+I104+M104)*(1+V104) -> 959.29732 | Y104: =(F104+J104+N104)*(1+V104) -> 1482.1916 | Z104: =(G104+K104+O104)*(1+V104) -> 2022.3759
B105: Sweden | C105: Stockholm | D105: EMEA | E105: 1247.6312 | F105: 1699.9752 | G105: 2390.652 | I105: 190.45992 | J105: 267.19996 | K105: 314.07896 | M105: 283.98167 | N105: 290.48487 | O105: 318.72539 | V105: 0.16 | X105: =(E105+I105+M105)*(1+V105) -> 1997.6045 | Y105: =(F105+J105+N105)*(1+V105) -> 2618.8857 | Z105: =(G105+K105+O105)*(1+V105) -> 3507.2093
B106: Switzerland | C106: Geneva | D106: EMEA | E106: 1298.5024 | F106: 1781.9916 | G106: 2194.8238 | I106: 198.22577 | J106: 278.09482 | K106: 326.88527 | M106: 283.18848 | N106: 289.67352 | O106: 317.83515 | Q106: 0.14 | R106: 0.08 | S106: 0.04 | T106: 0.02 | U106: 0.01 | V106: =SUBTOTAL(9,Q106:U106) -> 0 | X106: =(E106+I106+M106)*(1+V106) -> 1779.9166 | Y106: =(F106+J106+N106)*(1+V106) -> 2349.7599 | Z106: =(G106+K106+O106)*(1+V106) -> 2839.5442
B107: Switzerland | C107: Zurich | D107: EMEA | E107: 2004.5162 | F107: 2731.2781 | G107: 3840.9592 | I107: 306.00388 | J107: 429.29885 | K107: 504.61735 | M107: 437.162 | N107: 447.17305 | O107: 490.64655 | Q107: 0.14 | R107: 0.08 | S107: 0.04 | T107: 0.02 | U107: 0.01 | V107: =SUBTOTAL(9,Q107:U107) -> 0 | X107: =(E107+I107+M107)*(1+V107) -> 2747.6821 | Y107: =(F107+J107+N107)*(1+V107) -> 3607.75 | Z107: =(G107+K107+O107)*(1+V107) -> 4836.2231
B108: Turkey | C108: Istanbul | D108: EMEA | E108: 1091.5972 | F108: 1487.3691 | G108: 2091.6668 | I108: 166.64019 | J108: 233.78279 | K108: 274.7989 | M108: 346.69634 | N108: 354.63572 | O108: 389.11288 | Q108: 0.05 | R108: 0.01 | S108: 0.03 | T108: 0.01 | U108: 0.01 | V108: =SUBTOTAL(9,Q108:U108) -> 0 | X108: =(E108+I108+M108)*(1+V108) -> 1604.9337 | Y108: =(F108+J108+N108)*(1+V108) -> 2075.7876 | Z108: =(G108+K108+O108)*(1+V108) -> 2755.5786
B109: UAE | C109: Abu Dhabi | D109: EMEA | E109: 1499.8652 | F109: 2043.6596 | G109: 2873.9707 | I109: 133.24317 | J109: 183.22862 | K109: 192.69612 | M109: 322.33975 | N109: 329.72135 | O109: 361.77638 | Q109: incl | R109: incl | S109: incl | T109: incl | U109: 0.12 | V109: =SUBTOTAL(9,Q109:U109) -> 0 | X109: =(E109+I109+M109)*(1+V109) -> 1955.4481 | Y109: =(F109+J109+N109)*(1+V109) -> 2556.6096 | Z109: =(G109+K109+O109)*(1+V109) -> 3428.4432
B110: UAE | C110: Dubai | D110: EMEA | E110: 1499.8652 | F110: 2043.6596 | G110: 2873.9707 | I110: 133.24317 | J110: 183.22862 | K110: 192.69612 | M110: 322.33975 | N110: 329.72135 | O110: 361.77638 | Q110: incl | R110: incl | S110: incl | T110: incl | U110: 0.12 | V110: =SUBTOTAL(9,Q110:U110) -> 0 | X110: =(E110+I110+M110)*(1+V110) -> 1955.4481 | Y110: =(F110+J110+N110)*(1+V110) -> 2556.6096 | Z110: =(G110+K110+O110)*(1+V110) -> 3428.4432
B111: Uganda | C111: Kampala | D111: EMEA | E111: 945.77248 | F111: 1309.8001 | G111: 2093.1231 | I111: 144.379 | J111: 202.55213 | K111: 238.08896 | M111: 208.26468 | N111: 213.03395 | O111: 233.7448 | Q111: 0.05 | R111: 0.02 | S111: 0.04 | T111: 0.03 | U111: 0.02 | V111: =SUBTOTAL(9,Q111:U111) -> 0 | X111: =(E111+I111+M111)*(1+V111) -> 1298.4161 | Y111: =(F111+J111+N111)*(1+V111) -> 1725.3862 | Z111: =(G111+K111+O111)*(1+V111) -> 2564.9569
B112: China | C112: Hong Kong | D112: APAC | E112: 987.4649 | F112: 1487.1148 | G112: 1927.5031 | I112: 95.5045 | J112: 131.3325 | K112: 138.1185 | M112: 204.82992 | N112: 209.52054 | O112: 229.88982 | Q112: 0.04 | R112: 0.02 | S112: 0.04 | T112: 0.02 | U112: 0.02 | V112: =SUBTOTAL(9,Q112:U112) -> 0 | X112: =(E112+I112+M112)*(1+V112) -> 1287.7993 | Y112: =(F112+J112+N112)*(1+V112) -> 1827.9678 | Z112: =(G112+K112+O112)*(1+V112) -> 2295.5114
B113: Australia | C113: Sydney | D113: APAC | E113: 1240.5316 | F113: 1794.1552 | G113: 2201.2012 | I113: 110.20482 | J113: 151.54756 | K113: 159.37808 | M113: 276.50051 | N113: 282.83239 | O113: 310.32894 | Q113: 0.05 | R113: 0.05 | S113: 0.03 | T113: 0.05 | U113: 0.005 | V113: =SUBTOTAL(9,Q113:U113) -> 0 | X113: =(E113+I113+M113)*(1+V113) -> 1627.237 | Y113: =(F113+J113+N113)*(1+V113) -> 2228.5351 | Z113: =(G113+K113+O113)*(1+V113) -> 2670.9083
B114: Australia | C114: Brisbane | D114: APAC | E114: 1265.3423 | F114: 1830.0383 | G114: 2245.2253 | I114: 112.40891 | J114: 154.57851 | K114: 162.56564 | M114: 282.03052 | N114: 288.48903 | O114: 316.53552 | Q114: 0.05 | R114: 0.05 | S114: 0.03 | T114: 0.05 | U114: 0.005 | V114: =SUBTOTAL(9,Q114:U114) -> 0 | X114: =(E114+I114+M114)*(1+V114) -> 1659.7817 | Y114: =(F114+J114+N114)*(1+V114) -> 2273.1058 | Z114: =(G114+K114+O114)*(1+V114) -> 2724.3264
B115: Australia | C115: Melborne | D115: APAC | E115: 1290.1529 | F115: 1865.9214 | G115: 2289.2493 | I115: 114.61301 | J115: 157.60946 | K115: 165.7532 | M115: 287.56053 | N115: 294.14568 | O115: 322.7421 | Q115: 0.05 | R115: 0.05 | S115: 0.03 | T115: 0.05 | U115: 0.005 | V115: =SUBTOTAL(9,Q115:U115) -> 0 | X115: =(E115+I115+M115)*(1+V115) -> 1692.3264 | Y115: =(F115+J115+N115)*(1+V115) -> 2317.6765 | Z115: =(G115+K115+O115)*(1+V115) -> 2777.7446
B116: Australia | C116: Perth | D116: APAC | E116: 1277.7476 | F116: 1847.9798 | G116: 2267.2373 | I116: 113.51096 | J116: 156.09399 | K116: 164.15942 | M116: 284.79552 | N116: 291.31736 | O116: 319.63881 | Q116: 0.05 | R116: 0.05 | S116: 0.03 | T116: 0.05 | U116: 0.005 | V116: =SUBTOTAL(9,Q116:U116) -> 0 | X116: =(E116+I116+M116)*(1+V116) -> 1676.0541 | Y116: =(F116+J116+N116)*(1+V116) -> 2295.3912 | Z116: =(G116+K116+O116)*(1+V116) -> 2751.0355
B117: China | C117: Beijing | D117: APAC | E117: 812.25928 | F117: 1219.4384 | G117: 1658.157 | I117: 91.0966 | J117: 125.271 | K117: 131.7438 | M117: 196.0799 | N117: 200.57015 | O117: 220.06928 | Q117: 0.05 | R117: 0.02 | S117: 0.04 | T117: 0.02 | U117: 0.02 | V117: =SUBTOTAL(9,Q117:U117) -> 0 | X117: =(E117+I117+M117)*(1+V117) -> 1099.4358 | Y117: =(F117+J117+N117)*(1+V117) -> 1545.2796 | Z117: =(G117+K117+O117)*(1+V117) -> 2009.9701
B118: China | C118: Guangzhou | D118: APAC | E118: 771.93229 | F118: 1160.7156 | G118: 1578.9138 | I118: 88.158 | J118: 121.23 | K118: 127.494 | M118: 192.69922 | N118: 197.11204 | O118: 216.27499 | Q118: 0.05 | R118: 0.02 | S118: 0.04 | T118: 0.02 | U118: 0.02 | V118: =SUBTOTAL(9,Q118:U118) -> 0 | X118: =(E118+I118+M118)*(1+V118) -> 1052.7895 | Y118: =(F118+J118+N118)*(1+V118) -> 1479.0576 | Z118: =(G118+K118+O118)*(1+V118) -> 1922.6827
B119: China | C119: Shanghai | D119: APAC | E119: 809.38724 | F119: 1216.6628 | G119: 1655.7329 | I119: 91.0966 | J119: 125.271 | K119: 131.7438 | M119: 189.31853 | N119: 193.65394 | O119: 212.48069 | Q119: 0.05 | R119: 0.02 | S119: 0.04 | T119: 0.02 | U119: 0.02 | V119: =SUBTOTAL(9,Q119:U119) -> 0 | X119: =(E119+I119+M119)*(1+V119) -> 1089.8024 | Y119: =(F119+J119+N119)*(1+V119) -> 1535.5877 | Z119: =(G119+K119+O119)*(1+V119) -> 1999.9574
B120: India | C120: Bangalore | D120: APAC | E120: 453.5755 | F120: 562.75089 | G120: 758.58852 | I120: 39.6711 | J120: 54.5535 | K120: 57.3723 | M120: 99.399807 | N120: 101.67607 | O120: 111.56087 | Q120: 0.03 | R120: 0.015 | S120: 0.05 | T120: 0.025 | U120: 0.03 | V120: =SUBTOTAL(9,Q120:U120) -> 0 | X120: =(E120+I120+M120)*(1+V120) -> 592.64641 | Y120: =(F120+J120+N120)*(1+V120) -> 718.98046 | Z120: =(G120+K120+O120)*(1+V120) -> 927.52168
B121: India | C121: Chennai | D121: APAC | E121: 449.08465 | F121: 557.1791 | G121: 751.07774 | I121: 39.278317 | J121: 54.013366 | K121: 56.804257 | M121: 98.41565 | N121: 100.66938 | O121: 110.45631 | Q121: 0.03 | R121: 0.015 | S121: 0.05 | T121: 0.025 | U121: 0.03 | V121: =SUBTOTAL(9,Q121:U121) -> 0 | X121: =(E121+I121+M121)*(1+V121) -> 586.77862 | Y121: =(F121+J121+N121)*(1+V121) -> 711.86184 | Z121: =(G121+K121+O121)*(1+V121) -> 918.3383
B122: India | C122: Hyderbad | D122: APAC | E122: 449.08465 | F122: 557.1791 | G122: 751.07774 | I122: 39.278317 | J122: 54.013366 | K122: 56.804257 | M122: 98.41565 | N122: 100.66938 | O122: 110.45631 | Q122: 0.03 | R122: 0.015 | S122: 0.05 | T122: 0.025 | U122: 0.03 | V122: =SUBTOTAL(9,Q122:U122) -> 0 | X122: =(E122+I122+M122)*(1+V122) -> 586.77862 | Y122: =(F122+J122+N122)*(1+V122) -> 711.86184 | Z122: =(G122+K122+O122)*(1+V122) -> 918.3383
... B130: New Zealand | C130: Auckland | D130: APAC | E130: 1048.5908 | F130: 1495.5901 | G130: 1911.2608 | I130: 93.153411 | J130: 128.09941 | K130: 134.71836 | M130: 234.23624 | N130: 239.60027 | O130: 262.89386 | Q130: 0.04 | R130: 0.03 | S130: 0.04 | T130: 0.02 | U130: 0.02 | V130: =SUBTOTAL(9,Q130:U130) -> 0 | X130: =(E130+I130+M130)*(1+V130) -> 1375.9804 | Y130: =(F130+J130+N130)*(1+V130) -> 1863.2898 | Z130: =(G130+K130+O130)*(1+V130) -> 2308.8731
B131: Pakistan | C131: Karachi | D131: APAC | E131: 781.64636 | F131: 837.30438 | G131: 891.45326 | I131: 51.4255 | J131: 70.7175 | K131: 74.3715 | M131: 127.6044 | N131: 130.52655 | O131: 143.21615 | Q131: 0.02 | R131: 0.015 | S131: 0.015 | T131: included | U131: n/a | V131: =SUBTOTAL(9,Q131:U131) -> 0 | X131: =(E131+I131+M131)*(1+V131) -> 960.67626 | Y131: =(F131+J131+N131)*(1+V131) -> 1038.5484 | Z131: =(G131+K131+O131)*(1+V131) -> 1109.0409
B132: Philippines | C132: Manila | D132: APAC | E132: 828.97673 | F132: 1204.3772 | G132: 1547.1324 | I132: 73.465 | J132: 101.025 | K132: 106.245 | M132: 180.9331 | N132: 185.07648 | O132: 203.06934 | Q132: 0.03 | R132: 0.03 | S132: 0.03 | T132: 0.01 | U132: 0.01 | V132: =SUBTOTAL(9,Q132:U132) -> 0 | X132: =(E132+I132+M132)*(1+V132) -> 1083.3748 | Y132: =(F132+J132+N132)*(1+V132) -> 1490.4786 | Z132: =(G132+K132+O132)*(1+V132) -> 1856.4467
B133: Singapore | C133: Singapore | D133: APAC | E133: 1323.1459 | F133: 2024.6085 | G133: 2400.293 | I133: 132.237 | J133: 181.845 | K133: 191.241 | M133: 319.17672 | N133: 326.48589 | O133: 358.22637 | Q133: 0.07 | R133: 0.07 | S133: 0.1 | T133: included | U133: n/a | V133: =SUBTOTAL(9,Q133:U133) -> 0 | X133: =(E133+I133+M133)*(1+V133) -> 1774.5596 | Y133: =(F133+J133+N133)*(1+V133) -> 2532.9394 | Z133: =(G133+K133+O133)*(1+V133) -> 2949.7604
B134: South Korea | C134: Seoul | D134: APAC | E134: 850.50803 | F134: 1451.4087 | G134: 1585.8699 | I134: 88.158 | J134: 121.23 | K134: 127.494 | M134: 191.77118 | N134: 196.16276 | O134: 215.23341 | Q134: 0.03 | R134: 0.02 | S134: 0.04 | T134: 0.015 | U134: 0.015 | V134: =SUBTOTAL(9,Q134:U134) -> 0 | X134: =(E134+I134+M134)*(1+V134) -> 1130.4372 | Y134: =(F134+J134+N134)*(1+V134) -> 1768.8015 | Z134: =(G134+K134+O134)*(1+V134) -> 1928.5973
B135: Taiwan | C135: Taipei | D135: APAC | E135: 835.39583 | F135: 1257.1377 | G135: 1731.7612 | I135: 76.4036 | J135: 105.066 | K135: 110.4948 | M135: 183.7822 | N135: 187.99083 | O135: 206.26702 | Q135: 0.04 | R135: 0.02 | S135: 0.04 | T135: 0.02 | U135: 0.02 | V135: =SUBTOTAL(9,Q135:U135) -> 0 | X135: =(E135+I135+M135)*(1+V135) -> 1095.5816 | Y135: =(F135+J135+N135)*(1+V135) -> 1550.1945 | Z135: =(G135+K135+O135)*(1+V135) -> 2048.523
B136: Thailand | C136: Bangkok | D136: APAC | E136: 520.3849 | F136: 830.90911 | G136: 1167.4521 | I136: 46.22931 | J136: 63.571988 | K136: 66.856777 | M136: 110.73537 | N136: 113.27122 | O136: 124.28328 | Q136: 0.03 | R136: 0.015 | S136: 0.03 | T136: n/a | U136: 0.015 | V136: =SUBTOTAL(9,Q136:U136) -> 0 | X136: =(E136+I136+M136)*(1+V136) -> 677.34958 | Y136: =(F136+J136+N136)*(1+V136) -> 1007.7523 | Z136: =(G136+K136+O136)*(1+V136) -> 1358.5922
B137: Vietnam | C137: Hanoi | D137: APAC | E137: 612.14131 | F137: 768.3072 | G137: 986.1624 | I137: 54.380652 | J137: 74.781262 | K137: 78.645238 | M137: 134.14906 | N137: 137.22108 | O137: 150.56152 | Q137: 0.03 | R137: 0.03 | S137: 0.04 | T137: 0.03 | U137: 0.015 | V137: =SUBTOTAL(9,Q137:U137) -> 0 | X137: =(E137+I137+M137)*(1+V137) -> 800.67102 | Y137: =(F137+J137+N137)*(1+V137) -> 980.30955 | Z137: =(G137+K137+O137)*(1+V137) -> 1215.3692
B138: United Kingdom | C138: London | D138: EMEA | E138: 1565.3423 | F138: 2132.8763 | G138: 2999.4348 | I138: 238.9608 | J138: 335.2428 | K138: 394.0596 | M138: 353.64648 | N138: 361.74501 | O138: 396.91333 | Q138: 0.05 | R138: 0.01 | S138: 0.05 | T138: 0.02 | U138: 0.02 | V138: =SUBTOTAL(9,Q138:U138) -> 0.15 | X138: =(E138+I138+M138)*(1+V138) -> 2481.642 | Y138: =(F138+J138+N138)*(1+V138) -> 3254.3437 | Z138: =(G138+K138+O138)*(1+V138) -> 4358.9689
B139: Zimbabwe | C139: Harare | D139: EMEA | E139: 945.77248 | F139: 1309.8001 | G139: 2093.1231 | I139: 144.379 | J139: 202.55213 | K139: 238.08896 | M139: 206.81856 | N139: 211.55472 | O139: 232.12176 | Q139: 0.05 | R139: 0.02 | S139: 0.04 | T139: 0.03 | U139: 0.02 | V139: =SUBTOTAL(9,Q139:U139) -> 0 | X139: =(E139+I139+M139)*(1+V139) -> 1296.97 | Y139: =(F139+J139+N139)*(1+V139) -> 1723.907 | Z139: =(G139+K139+O139)*(1+V139) -> 2563.3338

Sheet Table 1_Activity BYOB SqFt
E1: ACTIVITY SPACE
E2: FIT OUT $/SqFt | I2: FURNITURE $/SqFt | M2: TECHNOLOGY $/SqFt | Q2: 2023 Professional Fees (%) | X2: TOTAL FITOUT COST $/SqFt
E4: Low | F4: Medium | G4: High | I4: Low | J4: Medium | K4: High | M4: Low | N4: Medium | O4: High | X4: Low | Y4: Medium | Z4: High
B5: COUNTRY | C5: CITY | D5: REGION | Q5: Arch | R5: M&E Eng | S5: PM | T5: QS | U5: Other | V5: Total
B6: United States | C6: Cincinnati | D6: AMERICAS | E6: 168.4093 | F6: 245.34823 | G6: 293.56133 | I6: 17.465748 | J6: 23.080301 | K6: 26.718343 | M6: 38.343304 | N6: 39.214743 | O6: 43.073972 | Q6: 0.08 | R6: 0.05 | S6: 0.03 | T6: 0.015 | U6: 0.02 | V6: =SUBTOTAL(9,Q6:U6) -> 0 | X6: =(E6+I6+M6)*(1+V6) -> 224.21835 | Y6: =(F6+J6+N6)*(1+V6) -> 307.64328 | Z6: =(G6+K6+O6)*(1+V6) -> 363.35365
B7: United States | C7: Charlotte | D7: AMERICAS | E7: 157.31249 | F7: 229.11135 | G7: 274.10341 | I7: 16.314897 | J7: 21.559496 | K7: 24.95782 | M7: 35.816791 | N7: 36.630809 | O7: 40.235745 | Q7: 0.08 | R7: 0.05 | S7: 0.03 | T7: 0.015 | U7: 0.02 | V7: =SUBTOTAL(9,Q7:U7) -> 0 | X7: =(E7+I7+M7)*(1+V7) -> 209.44417 | Y7: =(F7+J7+N7)*(1+V7) -> 287.30166 | Z7: =(G7+K7+O7)*(1+V7) -> 339.29697
B8: United States | C8: Charleston (SC) | D8: AMERICAS | E8: 157.31249 | F8: 229.11135 | G8: 274.10341 | I8: 16.314897 | J8: 21.559496 | K8: 24.95782 | M8: 35.816791 | N8: 36.630809 | O8: 40.235745 | Q8: 0.08 | R8: 0.05 | S8: 0.03 | T8: 0.015 | U8: 0.02 | V8: =SUBTOTAL(9,Q8:U8) -> 0 | X8: =(E8+I8+M8)*(1+V8) -> 209.44417 | Y8: =(F8+J8+N8)*(1+V8) -> 287.30166 | Z8: =(G8+K8+O8)*(1+V8) -> 339.29697
B9: United States | C9: Chicago | D9: AMERICAS | E9: 206.10305 | F9: 300.50225 | G9: 359.65657 | I9: 21.374972 | J9: 28.246187 | K9: 32.698503 | M9: 46.925389 | N9: 47.991876 | O9: 52.714886 | Q9: 0.08 | R9: 0.05 | S9: 0.03 | T9: 0.015 | U9: 0.02 | V9: =SUBTOTAL(9,Q9:U9) -> 0 | X9: =(E9+I9+M9)*(1+V9) -> 274.40341 | Y9: =(F9+J9+N9)*(1+V9) -> 376.74032 | Z9: =(G9+K9+O9)*(1+V9) -> 445.06996
B10: United States | C10: Cleveland | D10: AMERICAS | E10: 163.34929 | F10: 237.51113 | G10: 285.31936 | I10: 16.940974 | J10: 22.386833 | K10: 25.915566 | M10: 37.191245 | N10: 38.0365 | O10: 41.779775 | Q10: 0.08 | R10: 0.05 | S10: 0.03 | T10: 0.015 | U10: 0.02 | V10: =SUBTOTAL(9,Q10:U10) -> 0 | X10: =(E10+I10+M10)*(1+V10) -> 217.48151 | Y10: =(F10+J10+N10)*(1+V10) -> 297.93447 | Z10: =(G10+K10+O10)*(1+V10) -> 353.0147
B11: United States | C11: Boston | D11: AMERICAS | E11: 200.64274 | F11: 292.51266 | G11: 350.082 | I11: 20.808683 | J11: 27.497858 | K11: 31.832218 | M11: 45.682191 | N11: 46.720422 | O11: 51.318305 | Q11: 0.08 | R11: 0.05 | S11: 0.03 | T11: 0.015 | U11: 0.02 | V11: =SUBTOTAL(9,Q11:U11) -> 0 | X11: =(E11+I11+M11)*(1+V11) -> 267.13361 | Y11: =(F11+J11+N11)*(1+V11) -> 366.73094 | Z11: =(G11+K11+O11)*(1+V11) -> 433.23252
B12: United States | C12: Baltimore | D12: AMERICAS | E12: 164.04797 | F12: 239.0179 | G12: 287.29636 | I12: 17.013435 | J12: 22.482587 | K12: 26.026413 | M12: 37.350321 | N12: 38.199192 | O12: 41.958477 | Q12: 0.08 | R12: 0.05 | S12: 0.03 | T12: 0.015 | U12: 0.02 | V12: =SUBTOTAL(9,Q12:U12) -> 0 | X12: =(E12+I12+M12)*(1+V12) -> 218.41173 | Y12: =(F12+J12+N12)*(1+V12) -> 299.69968 | Z12: =(G12+K12+O12)*(1+V12) -> 355.28125
B13: United States | C13: Columbus | D13: AMERICAS | E13: 159.58829 | F13: 232.01812 | G13: 278.70981 | I13: 16.550921 | J13: 21.871393 | K13: 25.318879 | M13: 36.334944 | N13: 37.160739 | O13: 40.817827 | Q13: 0.08 | R13: 0.05 | S13: 0.03 | T13: 0.015 | U13: 0.02 | V13: =SUBTOTAL(9,Q13:U13) -> 0 | X13: =(E13+I13+M13)*(1+V13) -> 212.47416 | Y13: =(F13+J13+N13)*(1+V13) -> 291.05025 | Z13: =(G13+K13+O13)*(1+V13) -> 344.84652
B14: United States | C14: Austin | D14: AMERICAS | E14: 149.78324 | F14: 215.79648 | G14: 259.74763 | I14: 15.534038 | J14: 20.527622 | K14: 23.763296 | M14: 34.102538 | N14: 34.877596 | O14: 38.309994 | Q14: 0.08 | R14: 0.05 | S14: 0.03 | T14: 0.015 | U14: 0.02 | V14: =SUBTOTAL(9,Q14:U14) -> 0 | X14: =(E14+I14+M14)*(1+V14) -> 199.41982 | Y14: =(F14+J14+N14)*(1+V14) -> 271.2017 | Z14: =(G14+K14+O14)*(1+V14) -> 321.82092
B15: United States | C15: Atlanta | D15: AMERICAS | E15: 158.0497 | F15: 234.00321 | G15: 280.56818 | I15: 16.391353 | J15: 21.66053 | K15: 25.07478 | M15: 35.984639 | N15: 36.802471 | O15: 40.424302 | Q15: 0.08 | R15: 0.05 | S15: 0.03 | T15: 0.015 | U15: 0.02 | V15: =SUBTOTAL(9,Q15:U15) -> 0 | X15: =(E15+I15+M15)*(1+V15) -> 210.42569 | Y15: =(F15+J15+N15)*(1+V15) -> 292.46621 | Z15: =(G15+K15+O15)*(1+V15) -> 346.06726
B16: United States | C16: Dallas | D16: AMERICAS | E16: 150.52766 | F16: 218.78488 | G16: 262.78679 | I16: 15.611242 | J16: 20.629644 | K16: 23.8814 | M16: 34.272027 | N16: 35.050937 | O16: 38.500394 | Q16: 0.08 | R16: 0.05 | S16: 0.03 | T16: 0.015 | U16: 0.02 | V16: =SUBTOTAL(9,Q16:U16) -> 0 | X16: =(E16+I16+M16)*(1+V16) -> 200.41093 | Y16: =(F16+J16+N16)*(1+V16) -> 274.46546 | Z16: =(G16+K16+O16)*(1+V16) -> 325.16858
B17: United States | C17: Denver | D17: AMERICAS | E17: 160.78498 | F17: 233.76589 | G17: 280.81284 | I17: 16.67503 | J17: 22.035398 | K17: 25.508736 | M17: 36.607406 | N17: 37.439392 | O17: 41.123904 | Q17: 0.08 | R17: 0.05 | S17: 0.03 | T17: 0.015 | U17: 0.02 | V17: =SUBTOTAL(9,Q17:U17) -> 0 | X17: =(E17+I17+M17)*(1+V17) -> 214.06742 | Y17: =(F17+J17+N17)*(1+V17) -> 293.24068 | Z17: =(G17+K17+O17)*(1+V17) -> 347.44548
... B70: Canada | C70: Toronto | D70: AMERICAS | E70: 128.02 | F70: 202.76 | G70: 272.32 | I70: 13.308 | J70: 17.586 | K70: 20.358 | M70: 28.025536 | N70: 28.66248 | O70: 31.483232 | Q70: 0.08 | R70: 0.05 | S70: 0.03 | T70: 0.015 | U70: 0.02 | V70: =SUBTOTAL(9,Q70:U70) -> 0 | X70: =(E70+I70+M70)*(1+V70) -> 169.35354 | Y70: =(F70+J70+N70)*(1+V70) -> 249.00848 | Z70: =(G70+K70+O70)*(1+V70) -> 324.16123
B71: Canada | C71: Montreal | D71: AMERICAS | E71: =E$25*0.58 -> 89.190005 | F71: =F$25*0.58 -> 129.64674 | G71: =G$25*0.58 -> 155.72715 | I71: 12.8644 | J71: 16.9998 | K71: 19.6794 | M71: 27.164639 | N71: 27.782018 | O71: 30.516121 | Q71: 0.08 | R71: 0.05 | S71: 0.03 | T71: 0.015 | U71: 0.02 | V71: =SUBTOTAL(9,Q71:U71) -> 0 | X71: =(E71+I71+M71)*(1+V71) -> 129.21904 | Y71: =(F71+J71+N71)*(1+V71) -> 174.42855 | Z71: =(G71+K71+O71)*(1+V71) -> 205.92267
B72: Canada | C72: Vancouver | D72: AMERICAS | E72: =E$25*0.58 -> 89.190005 | F72: =F$25*0.58 -> 129.64674 | G72: =G$25*0.58 -> 155.72715 | I72: 12.8644 | J72: 16.9998 | K72: 19.6794 | M72: 27.164639 | N72: 27.782018 | O72: 30.516121 | Q72: 0.08 | R72: 0.05 | S72: 0.03 | T72: 0.015 | U72: 0.02 | V72: =SUBTOTAL(9,Q72:U72) -> 0 | X72: =(E72+I72+M72)*(1+V72) -> 129.21904 | Y72: =(F72+J72+N72)*(1+V72) -> 174.42855 | Z72: =(G72+K72+O72)*(1+V72) -> 205.92267
B73: Canada | C73: Ottawa | D73: AMERICAS | E73: =E$25*0.59 -> 90.727764 | F73: =F$25*0.59 -> 131.88202 | G73: =G$25*0.59 -> 158.4121 | I73: 13.0862 | J73: 17.2929 | K73: 20.0187 | M73: 27.632995 | N73: 28.261018 | O73: 31.042261 | Q73: 0.08 | R73: 0.05 | S73: 0.03 | T73: 0.015 | U73: 0.02 | V73: =SUBTOTAL(9,Q73:U73) -> 0 | X73: =(E73+I73+M73)*(1+V73) -> 131.44696 | Y73: =(F73+J73+N73)*(1+V73) -> 177.43594 | Z73: =(G73+K73+O73)*(1+V73) -> 209.47306
B74: Austria | C74: Vienna | D74: EMEA | E74: 81.173121 | F74: 109.0108 | G74: 131.09359 | I74: 12.39434 | J74: 17.385835 | K74: 20.454278 | M74: 18.395476 | N74: 18.813555 | O74: 20.665048 | Q74: 0.05 | R74: 0.08 | S74: 0.08 | T74: 0.012 | U74: 0.02 | V74: =SUBTOTAL(9,Q74:U74) -> 0 | X74: =(E74+I74+M74)*(1+V74) -> 111.96294 | Y74: =(F74+J74+N74)*(1+V74) -> 145.21019 | Z74: =(G74+K74+O74)*(1+V74) -> 172.21291
B75: Belgium | C75: Brussels | D75: EMEA | E75: 84.845191 | F75: 121.0267 | G75: 150.54463 | I75: 12.955029 | J75: 18.172327 | K75: 21.379578 | M75: 19.31749 | N75: 19.756524 | O75: 21.700817 | Q75: lump sum | R75: 0.05 | S75: 0.09 | T75: 0.07 | U75: 0.05 | V75: =SUBTOTAL(9,Q75:U75) -> 0 | X75: =(E75+I75+M75)*(1+V75) -> 117.11771 | Y75: =(F75+J75+N75)*(1+V75) -> 158.95555 | Z75: =(G75+K75+O75)*(1+V75) -> 193.62502
B76: Botswana | C76: Gabarone | D76: EMEA | E76: 79.983357 | F76: 117.86825 | G76: 159.47385 | I76: 12.212675 | J76: 17.131008 | K76: 20.154477 | M76: 17.78705 | N76: 18.191301 | O76: 19.981557 | Q76: 0.05 | R76: 0.02 | S76: 0.04 | T76: 0.03 | U76: 0.02 | V76: =SUBTOTAL(9,Q76:U76) -> 0 | X76: =(E76+I76+M76)*(1+V76) -> 109.98308 | Y76: =(F76+J76+N76)*(1+V76) -> 153.19056 | Z76: =(G76+K76+O76)*(1+V76) -> 199.60988
B77: Bulgaria | C77: Sofia | D77: EMEA | E77: 89.8645 | F77: 150.766 | G77: 188.793 | I77: 13.721428 | J77: 19.247373 | K77: 22.644361 | M77: 19.984462 | N77: 20.438655 | O77: 22.450078 | Q77: 0.045 | R77: 0.005 | S77: 0.07 | T77: 0.03 | U77: 0 | V77: =SUBTOTAL(9,Q77:U77) -> 0 | X77: =(E77+I77+M77)*(1+V77) -> 123.57039 | Y77: =(F77+J77+N77)*(1+V77) -> 190.45203 | Z77: =(G77+K77+O77)*(1+V77) -> 233.88744
B78: Croatia | C78: Zagreb | D78: EMEA | E78: 98.3223 | F78: 164.9619 | G78: 206.5742 | I78: 15.012851 | J78: 21.058883 | K78: 24.775586 | M78: 21.865345 | N78: 22.362285 | O78: 24.563018 | Q78: 0.045 | R78: 0.005 | S78: 0.07 | T78: 0.03 | U78: n/a | V78: =SUBTOTAL(9,Q78:U78) -> 0 | X78: =(E78+I78+M78)*(1+V78) -> 135.2005 | Y78: =(F78+J78+N78)*(1+V78) -> 208.38307 | Z78: =(G78+K78+O78)*(1+V78) -> 255.9128
B79: Czech Republic | C79: Prague | D79: EMEA | E79: 46.893436 | F79: 78.42853 | G79: 107.28729 | I79: 7.1601681 | J79: 10.043738 | K79: 11.816367 | M79: 10.676663 | N79: 10.919314 | O79: 11.993914 | Q79: 0.031 | R79: 0.054 | S79: 0.086 | T79: 0.016 | U79: 0.005 | V79: =SUBTOTAL(9,Q79:U79) -> 0 | X79: =(E79+I79+M79)*(1+V79) -> 64.730267 | Y79: =(F79+J79+N79)*(1+V79) -> 99.391583 | Z79: =(G79+K79+O79)*(1+V79) -> 131.09757
B80: Denmark | C80: Copenhagen | D80: EMEA | E80: 125.11537 | F80: 170.47748 | G80: 239.74015 | I80: 19.103891 | J80: 26.797481 | K80: 31.526995 | M80: 27.823706 | N80: 28.456063 | O80: 31.256501 | V80: 0.24 | X80: =(E80+I80+M80)*(1+V80) -> 213.33328 | Y80: =(F80+J80+N80)*(1+V80) -> 279.90647 | Z80: =(G80+K80+O80)*(1+V80) -> 375.12932
B81: Ethiopia | C81: Addis Ababa | D81: EMEA | E81: 76.98597 | F81: 106.61786 | G81: 170.38042 | I81: 11.755003 | J81: 16.489022 | K81: 19.399185 | M81: 16.957426 | N81: 17.342822 | O81: 19.049576 | Q81: 0.05 | R81: 0.02 | S81: 0.04 | T81: 0.03 | U81: 0.02 | V81: =SUBTOTAL(9,Q81:U81) -> 0 | X81: =(E81+I81+M81)*(1+V81) -> 105.6984 | Y81: =(F81+J81+N81)*(1+V81) -> 140.4497 | Z81: =(G81+K81+O81)*(1+V81) -> 208.82918
B82: Finland | C82: Helsinki | D82: EMEA | E82: 114.93156 | F82: 156.6014 | G82: 220.22642 | I82: 17.548923 | J82: 24.616291 | K82: 28.960844 | M82: 25.558986 | N82: 26.139872 | O82: 28.712367 | Q82: 0.04 | R82: 0.04 | S82: 0.08 | T82: 0.005 | U82: 0.02 | V82: =SUBTOTAL(9,Q82:U82) -> 0 | X82: =(E82+I82+M82)*(1+V82) -> 158.03947 | Y82: =(F82+J82+N82)*(1+V82) -> 207.35757 | Z82: =(G82+K82+O82)*(1+V82) -> 277.89963
B83: France | C83: Paris | D83: EMEA | E83: 122.20571 | F83: 166.51289 | G83: 234.1648 | I83: 18.659614 | J83: 26.174284 | K83: 30.793809 | M83: 27.176643 | N83: 27.794294 | O83: 30.529605 | Q83: 0.1 | R83: 0.04 | S83: 0.03 | T83: 0.02 | U83: n/a | V83: =SUBTOTAL(9,Q83:U83) -> 0 | X83: =(E83+I83+M83)*(1+V83) -> 168.04197 | Y83: =(F83+J83+N83)*(1+V83) -> 220.48146 | Z83: =(G83+K83+O83)*(1+V83) -> 295.48821
B84: Germany | C84: Cologne | D84: EMEA | E84: 113.21015 | F84: 132.76895 | G84: 159.8789 | I84: 17.28608 | J84: 24.247594 | K84: 28.527076 | M84: 25.775602 | N84: 26.361412 | O84: 28.955709 | Q84: 0.12 | R84: 0.06 | S84: 0.05 | T84: 0.03 | U84: n/a | V84: =SUBTOTAL(9,Q84:U84) -> 0 | X84: =(E84+I84+M84)*(1+V84) -> 156.27183 | Y84: =(F84+J84+N84)*(1+V84) -> 183.37795 | Z84: =(G84+K84+O84)*(1+V84) -> 217.36169
B85: Ghana | C85: Accra | D85: EMEA | E85: 88.674836 | F85: 130.35302 | G85: 175.68697 | I85: 13.539778 | J85: 18.992568 | K85: 22.344585 | M85: 19.532091 | N85: 19.976002 | O85: 21.941895 | Q85: 0.05 | R85: 0.02 | S85: 0.04 | T85: 0.03 | U85: 0.02 | V85: =SUBTOTAL(9,Q85:U85) -> 0 | X85: =(E85+I85+M85)*(1+V85) -> 121.74671 | Y85: =(F85+J85+N85)*(1+V85) -> 169.32159 | Z85: =(G85+K85+O85)*(1+V85) -> 219.97345
B86: Hungary | C86: Budapest | D86: EMEA | E86: 90.255161 | F86: 117.27672 | G86: 131.21421 | I86: 13.781078 | J86: 19.331046 | K86: 22.742801 | M86: 20.071339 | N86: 20.527506 | O86: 22.547673 | Q86: 0.06 | R86: 0.04 | S86: 0.07 | T86: 0.03 | U86: 0.03 | V86: =SUBTOTAL(9,Q86:U86) -> 0 | X86: =(E86+I86+M86)*(1+V86) -> 124.10758 | Y86: =(F86+J86+N86)*(1+V86) -> 157.13527 | Z86: =(G86+K86+O86)*(1+V86) -> 176.50469
B87: Ireland | C87: Dublin | D87: EMEA | E87: 107.07948 | F87: 146.45961 | G87: 186.3211 | I87: 16.349988 | J87: 22.934516 | K87: 26.982251 | M87: 24.266384 | N87: 24.817892 | O87: 27.260288 | Q87: 0.033 | R87: 0.015 | S87: 0.025 | T87: included | U87: 0.018 | V87: =SUBTOTAL(9,Q87:U87) -> 0 | X87: =(E87+I87+M87)*(1+V87) -> 147.69586 | Y87: =(F87+J87+N87)*(1+V87) -> 194.21202 | Z87: =(G87+K87+O87)*(1+V87) -> 240.56363
B88: Israel | C88: Tel Aviv | D88: EMEA | E88: 108.7866 | F88: 146.8246 | G88: 157.5392 | I88: 16.610647 | J88: 23.300149 | K88: 27.412416 | M88: 25.021897 | N88: 25.590577 | O88: 28.109015 | Q88: 0.05 | R88: 0.02 | S88: 0.05 | T88: 0.02 | U88: 0.03 | V88: =SUBTOTAL(9,Q88:U88) -> 0.17 | X88: =(E88+I88+M88)*(1+V88) -> 175.9904 | Y88: =(F88+J88+N88)*(1+V88) -> 228.98693 | Z88: =(G88+K88+O88)*(1+V88) -> 249.28094
B89: Italy | C89: Rome | D89: EMEA | E89: 71.145826 | F89: 119.54629 | G89: 140.7853 | I89: 10.86327 | J89: 15.238167 | K89: 17.927566 | M89: 16.198429 | N89: 16.566575 | O89: 18.196936 | Q89: 0.05 | R89: 0.04 | S89: 0.02 | T89: 0.01 | U89: 0.02 | V89: =SUBTOTAL(9,Q89:U89) -> 0 | X89: =(E89+I89+M89)*(1+V89) -> 98.207525 | Y89: =(F89+J89+N89)*(1+V89) -> 151.35103 | Z89: =(G89+K89+O89)*(1+V89) -> 176.9098
B90: Kenya | C90: Nairobi | D90: EMEA | E90: 69.323902 | F90: 101.81565 | G90: 136.37263 | I90: 10.58508 | J90: 14.847943 | K90: 17.468472 | M90: 15.26973 | N90: 15.616769 | O90: 17.153657 | Q90: 0.05 | R90: 0.02 | S90: 0.04 | T90: 0.03 | U90: 0.02 | V90: =SUBTOTAL(9,Q90:U90) -> 0 | X90: =(E90+I90+M90)*(1+V90) -> 95.178712 | Y90: =(F90+J90+N90)*(1+V90) -> 132.28036 | Z90: =(G90+K90+O90)*(1+V90) -> 170.99476
B91: Luxembourg | C91: Luxembourg | D91: EMEA | E91: 93.77393 | F91: 130.32518 | G91: 155.0698 | I91: 14.31836 | J91: 20.084703 | K91: 23.629472 | M91: 20.853859 | N91: 21.32781 | O91: 23.426737 | V91: 0.22 | X91: =(E91+I91+M91)*(1+V91) -> 157.3143 | Y91: =(F91+J91+N91)*(1+V91) -> 209.51999 | Z91: =(G91+K91+O91)*(1+V91) -> 246.59374
B92: Morocco | C92: Casablanca | D92: EMEA | E92: 114.69245 | F92: 156.2756 | G92: 219.76825 | I92: 17.512413 | J92: 24.565077 | K92: 28.900592 | M92: 25.262899 | N92: 25.837056 | O92: 28.37975 | Q92: 0.05 | R92: 0.02 | S92: 0.04 | T92: 0.03 | U92: 0.02 | V92: =SUBTOTAL(9,Q92:U92) -> 0 | X92: =(E92+I92+M92)*(1+V92) -> 157.46776 | Y92: =(F92+J92+N92)*(1+V92) -> 206.67773 | Z92: =(G92+K92+O92)*(1+V92) -> 277.04859
B93: Netherlands | C93: Amsterdam | D93: EMEA | E93: 69.86878 | F93: 99.046131 | G93: 129.70527 | I93: 10.668278 | J93: 14.964646 | K93: 17.605772 | M93: 15.611715 | N93: 15.966527 | O93: 17.537836 | Q93: 0.04 | R93: 0.03 | S93: 0.06 | T93: 0.025 | U93: 0.02 | V93: =SUBTOTAL(9,Q93:U93) -> 0 | X93: =(E93+I93+M93)*(1+V93) -> 96.148773 | Y93: =(F93+J93+N93)*(1+V93) -> 129.9773 | Z93: =(G93+K93+O93)*(1+V93) -> 164.84888
B94: Nigeria | C94: Abuja | D94: EMEA | E94: 89.496096 | F94: 130.39105 | G94: 185.13893 | I94: 13.665177 | J94: 19.168468 | K94: 22.551529 | M94: 19.712987 | N94: 20.16101 | O94: 22.145109 | Q94: 0.05 | R94: 0.02 | S94: 0.04 | T94: 0.03 | U94: 0.02 | V94: =SUBTOTAL(9,Q94:U94) -> 0 | X94: =(E94+I94+M94)*(1+V94) -> 122.87426 | Y94: =(F94+J94+N94)*(1+V94) -> 169.72053 | Z94: =(G94+K94+O94)*(1+V94) -> 229.83556
B95: Norway | C95: Oslo | D95: EMEA | E95: 116.02697 | F95: 158.09397 | G95: 222.32539 | I95: 17.716181 | J95: 24.850907 | K95: 29.236869 | M95: 25.802587 | N95: 26.38901 | O95: 28.986023 | Q95: 0.04 | R95: 0.04 | S95: 0.08 | T95: 0.005 | U95: 0.02 | V95: =SUBTOTAL(9,Q95:U95) -> 0 | X95: =(E95+I95+M95)*(1+V95) -> 159.54574 | Y95: =(F95+J95+N95)*(1+V95) -> 209.33388 | Z95: =(G95+K95+O95)*(1+V95) -> 280.54828
B96: Poland | C96: Warsaw | D96: EMEA | E96: 93.141873 | F96: 128.33688 | G96: 152.34734 | I96: 14.221851 | J96: 19.949328 | K96: 23.470205 | M96: 21.206473 | N96: 21.688438 | O96: 23.822856 | V96: 0.14 | X96: =(E96+I96+M96)*(1+V96) -> 146.57002 | Y96: =(F96+J96+N96)*(1+V96) -> 193.7711 | Z96: =(G96+K96+O96)*(1+V96) -> 227.59005
B97: Romania | C97: Bucharest | D97: EMEA | E97: 73.505463 | F97: 126.47447 | G97: 157.50306 | I97: 11.223564 | J97: 15.743559 | K97: 18.522156 | M97: 16.424308 | N97: 16.797588 | O97: 18.450684 | Q97: 0.04 | R97: 0.03 | S97: 0.06 | T97: 0.04 | U97: 0.02 | V97: =SUBTOTAL(9,Q97:U97) -> 0 | X97: =(E97+I97+M97)*(1+V97) -> 101.15334 | Y97: =(F97+J97+N97)*(1+V97) -> 159.01562 | Z97: =(G97+K97+O97)*(1+V97) -> 194.4759
B98: Rwanda | C98: Kigali | D98: EMEA | E98: 76.70103 | F98: 118.04733 | G98: 159.42147 | I98: 11.711495 | J98: 16.427993 | K98: 19.327385 | M98: 16.894663 | N98: 17.278633 | O98: 18.97907 | Q98: 0.05 | R98: 0.02 | S98: 0.04 | T98: 0.03 | U98: 0.02 | V98: =SUBTOTAL(9,Q98:U98) -> 0 | X98: =(E98+I98+M98)*(1+V98) -> 105.30719 | Y98: =(F98+J98+N98)*(1+V98) -> 151.75396 | Z98: =(G98+K98+O98)*(1+V98) -> 197.72793
B99: Senegal | C99: Dakar | D99: EMEA | E99: 89.259097 | F99: 123.61491 | G99: 197.54252 | I99: 13.628989 | J99: 19.117707 | K99: 22.491809 | M99: 19.660784 | N99: 20.10762 | O99: 22.086465 | Q99: 0.05 | R99: 0.02 | S99: 0.04 | T99: 0.03 | U99: 0.02 | V99: =SUBTOTAL(9,Q99:U99) -> 0 | X99: =(E99+I99+M99)*(1+V99) -> 122.54887 | Y99: =(F99+J99+N99)*(1+V99) -> 162.84023 | Z99: =(G99+K99+O99)*(1+V99) -> 242.12079
B100: Serbia | C100: Belgrade | D100: EMEA | E100: 86.010652 | F100: 146.28104 | G100: 182.81609 | I100: 13.132983 | J100: 18.421948 | K100: 21.673255 | M100: 19.127427 | N100: 19.562141 | O100: 21.487304 | Q100: 0.045 | R100: 0.005 | S100: 0.07 | T100: 0.03 | U100: n/a | V100: =SUBTOTAL(9,Q100:U100) -> 0 | X100: =(E100+I100+M100)*(1+V100) -> 118.27106 | Y100: =(F100+J100+N100)*(1+V100) -> 184.26513 | Z100: =(G100+K100+O100)*(1+V100) -> 225.97665
B101: Slovakia | C101: Bratislava | D101: EMEA | E101: 134.01307 | F101: 154.62361 | G101: 167.32907 | I101: 20.462482 | J101: 28.70321 | K101: 33.769067 | M101: 32.924573 | N101: 33.672859 | O101: 36.986696 | V101: 0.192 | X101: =(E101+I101+M101)*(1+V101) -> 223.38095 | Y101: =(F101+J101+N101)*(1+V101) -> 258.66362 | Z101: =(G101+K101+O101)*(1+V101) -> 283.79712
B102: Slovenia | C102: Ljubljana | D102: EMEA | E102: 105.7053 | F102: 177.3311 | G102: 222.0678 | I102: 16.140163 | J102: 22.64019 | K102: 26.635979 | M102: 23.507209 | N102: 24.041464 | O102: 26.407449 | Q102: 0.045 | R102: 0.005 | S102: 0.07 | T102: 0.03 | U102: n/a | V102: =SUBTOTAL(9,Q102:U102) -> 0 | X102: =(E102+I102+M102)*(1+V102) -> 145.35267 | Y102: =(F102+J102+N102)*(1+V102) -> 224.01275 | Z102: =(G102+K102+O102)*(1+V102) -> 275.11123
B103: South Africa | C103: Johannesburg | D103: EMEA | E103: 71.32013 | F103: 101.11821 | G103: 126.02344 | I103: 10.889885 | J103: 15.2755 | K103: 17.971488 | M103: 15.709432 | N103: 16.066464 | O103: 17.647608 | Q103: 0.05 | R103: 0.02 | S103: 0.04 | T103: 0.03 | U103: 0.02 | V103: =SUBTOTAL(9,Q103:U103) -> 0 | X103: =(E103+I103+M103)*(1+V103) -> 97.919447 | Y103: =(F103+J103+N103)*(1+V103) -> 132.46018 | Z103: =(G103+K103+O103)*(1+V103) -> 161.64253
B104: Spain | C104: Madrid | D104: EMEA | E104: 63.736487 | F104: 108.03572 | G104: 154.26845 | I104: 9.7319368 | J104: 13.651219 | K104: 16.060536 | M104: 15.658895 | N104: 16.014779 | O104: 17.590837 | Q104: 0.05 | R104: 0.03 | S104: 0.03 | T104: 0.02 | U104: 0.05 | V104: =SUBTOTAL(9,Q104:U104) -> 0 | X104: =(E104+I104+M104)*(1+V104) -> 89.127319 | Y104: =(F104+J104+N104)*(1+V104) -> 137.70172 | Z104: =(G104+K104+O104)*(1+V104) -> 187.91982
B105: Sweden | C105: Stockholm | D105: EMEA | E105: 115.90779 | F105: 157.93158 | G105: 222.09703 | I105: 17.697984 | J105: 24.825382 | K105: 29.206838 | M105: 26.389801 | N105: 26.989569 | O105: 29.645685 | V105: 0.16 | X105: =(E105+I105+M105)*(1+V105) -> 185.59487 | Y105: =(F105+J105+N105)*(1+V105) -> 243.30598 | Z105: =(G105+K105+O105)*(1+V105) -> 325.90148
B106: Switzerland | C106: Geneva | D106: EMEA | E106: 120.63384 | F106: 165.55109 | G106: 203.90414 | I106: 18.419605 | J106: 25.837617 | K106: 30.397723 | M106: 26.316091 | N106: 26.914184 | O106: 29.562882 | Q106: 0.14 | R106: 0.08 | S106: 0.04 | T106: 0.02 | U106: 0.01 | V106: =SUBTOTAL(9,Q106:U106) -> 0 | X106: =(E106+I106+M106)*(1+V106) -> 165.36953 | Y106: =(F106+J106+N106)*(1+V106) -> 218.30289 | Z106: =(G106+K106+O106)*(1+V106) -> 263.86475
B107: Switzerland | C107: Zurich | D107: EMEA | E107: 186.22414 | F107: 253.74198 | G107: 356.83388 | I107: 28.4346 | J107: 39.885889 | K107: 46.925389 | M107: 40.624516 | N107: 41.547801 | O107: 45.636632 | Q107: 0.14 | R107: 0.08 | S107: 0.04 | T107: 0.02 | U107: 0.01 | V107: =SUBTOTAL(9,Q107:U107) -> 0 | X107: =(E107+I107+M107)*(1+V107) -> 255.28325 | Y107: =(F107+J107+N107)*(1+V107) -> 335.17567 | Z107: =(G107+K107+O107)*(1+V107) -> 449.3959
B108: Turkey | C108: Istanbul | D108: EMEA | E108: 101.41187 | F108: 138.17998 | G108: 194.32063 | I108: 15.484599 | J108: 21.720614 | K108: 25.554106 | M108: 32.217739 | N108: 32.94996 | O108: 36.192655 | Q108: 0.05 | R108: 0.01 | S108: 0.03 | T108: 0.01 | U108: 0.01 | V108: =SUBTOTAL(9,Q108:U108) -> 0 | X108: =(E108+I108+M108)*(1+V108) -> 149.11421 | Y108: =(F108+J108+N108)*(1+V108) -> 192.85056 | Z108: =(G108+K108+O108)*(1+V108) -> 256.06739
B109: UAE | C109: Abu Dhabi | D109: EMEA | E109: 139.3409 | F109: 189.86065 | G109: 266.99844 | I109: 12.378474 | J109: 17.021536 | K109: 17.901178 | M109: 29.954333 | N109: 30.635114 | O109: 33.649998 | Q109: incl | R109: incl | S109: incl | T109: incl | U109: 0.12 | V109: =SUBTOTAL(9,Q109:U109) -> 0 | X109: =(E109+I109+M109)*(1+V109) -> 181.67371 | Y109: =(F109+J109+N109)*(1+V109) -> 237.5173 | Z109: =(G109+K109+O109)*(1+V109) -> 318.54961
B110: UAE | C110: Dubai | D110: EMEA | E110: 139.3409 | F110: 189.86065 | G110: 266.99844 | I110: 12.378474 | J110: 17.021536 | K110: 17.901178 | M110: 29.954333 | N110: 30.635114 | O110: 33.649998 | Q110: incl | R110: incl | S110: incl | T110: incl | U110: 0.12 | V110: =SUBTOTAL(9,Q110:U110) -> 0 | X110: =(E110+I110+M110)*(1+V110) -> 181.67371 | Y110: =(F110+J110+N110)*(1+V110) -> 237.5173 | Z110: =(G110+K110+O110)*(1+V110) -> 318.54961
B111: Uganda | C111: Kampala | D111: EMEA | E111: 87.864423 | F111: 121.68342 | G111: 194.45592 | I111: 13.416036 | J111: 18.818992 | K111: 22.140375 | M111: 19.353584 | N111: 19.793439 | O111: 21.741364 | Q111: 0.05 | R111: 0.02 | S111: 0.04 | T111: 0.03 | U111: 0.02 | V111: =SUBTOTAL(9,Q111:U111) -> 0 | X111: =(E111+I111+M111)*(1+V111) -> 120.63404 | Y111: =(F111+J111+N111)*(1+V111) -> 160.29586 | Z111: =(G111+K111+O111)*(1+V111) -> 238.33766
B112: China | C112: Hong Kong | D112: APAC | E112: 91.738579 | F112: 138.15762 | G112: 179.07107 | I112: 8.8725 | J112: 12.2005 | K112: 12.831 | M112: 19.0344 | N112: 19.467 | O112: 21.3828 | Q112: 0.04 | R112: 0.02 | S112: 0.04 | T112: 0.02 | U112: 0.02 | V112: =SUBTOTAL(9,Q112:U112) -> 0 | X112: =(E112+I112+M112)*(1+V112) -> 119.64548 | Y112: =(F112+J112+N112)*(1+V112) -> 169.82512 | Z112: =(G112+K112+O112)*(1+V112) -> 213.28487
B113: Australia | C113: Sydney | D113: APAC | E113: 115.24927 | F113: 166.68263 | G113: 204.49848 | I113: 10.23818 | J113: 14.078435 | K113: 14.805983 | M113: 25.694592 | N113: 26.27856 | O113: 28.864704 | Q113: 0.05 | R113: 0.05 | S113: 0.03 | T113: 0.05 | U113: 0.005 | V113: =SUBTOTAL(9,Q113:U113) -> 0 | X113: =(E113+I113+M113)*(1+V113) -> 151.18204 | Y113: =(F113+J113+N113)*(1+V113) -> 207.03963 | Z113: =(G113+K113+O113)*(1+V113) -> 248.16917
B114: Australia | C114: Brisbane | D114: APAC | E114: 117.55426 | F114: 170.01629 | G114: 208.58845 | I114: 10.5105 | J114: 14.4529 | K114: 15.1998 | M114: 26.208484 | N114: 26.804131 | O114: 29.441998 | Q114: 0.05 | R114: 0.05 | S114: 0.03 | T114: 0.05 | U114: 0.005 | V114: =SUBTOTAL(9,Q114:U114) -> 0 | X114: =(E114+I114+M114)*(1+V114) -> 154.27324 | Y114: =(F114+J114+N114)*(1+V114) -> 211.27332 | Z114: =(G114+K114+O114)*(1+V114) -> 253.23025
B115: Australia | C115: Melborne | D115: APAC | E115: 119.85924 | F115: 173.34994 | G115: 212.67842 | I115: 10.647 | J115: 14.6406 | K115: 15.3972 | M115: 26.722376 | N115: 27.329702 | O115: 30.019292 | Q115: 0.05 | R115: 0.05 | S115: 0.03 | T115: 0.05 | U115: 0.005 | V115: =SUBTOTAL(9,Q115:U115) -> 0 | X115: =(E115+I115+M115)*(1+V115) -> 157.22862 | Y115: =(F115+J115+N115)*(1+V115) -> 215.32024 | Z115: =(G115+K115+O115)*(1+V115) -> 258.09492
B116: Australia | C116: Perth | D116: APAC | E116: 118.70675 | F116: 171.68311 | G116: 210.63344 | I116: 10.5105 | J116: 14.4529 | K116: 15.1998 | M116: 26.46543 | N116: 27.066917 | O116: 29.730645 | Q116: 0.05 | R116: 0.05 | S116: 0.03 | T116: 0.05 | U116: 0.005 | V116: =SUBTOTAL(9,Q116:U116) -> 0 | X116: =(E116+I116+M116)*(1+V116) -> 155.68268 | Y116: =(F116+J116+N116)*(1+V116) -> 213.20293 | Z116: =(G116+K116+O116)*(1+V116) -> 255.56388
B117: China | C117: Beijing | D117: APAC | E117: 75.46143 | F117: 113.28965 | G117: 154.04798 | I117: 8.463 | J117: 11.6374 | K117: 12.2388 | M117: 18.22128 | N117: 18.6354 | O117: 20.46936 | Q117: 0.05 | R117: 0.02 | S117: 0.04 | T117: 0.02 | U117: 0.02 | V117: =SUBTOTAL(9,Q117:U117) -> 0 | X117: =(E117+I117+M117)*(1+V117) -> 102.14571 | Y117: =(F117+J117+N117)*(1+V117) -> 143.56245 | Z117: =(G117+K117+O117)*(1+V117) -> 186.75614
B118: China | C118: Guangzhou | D118: APAC | E118: 71.714926 | F118: 107.83411 | G118: 146.68603 | I118: 8.19 | J118: 11.262 | K118: 11.844 | M118: 17.90712 | N118: 18.3141 | O118: 20.11644 | Q118: 0.05 | R118: 0.02 | S118: 0.04 | T118: 0.02 | U118: 0.02 | V118: =SUBTOTAL(9,Q118:U118) -> 0 | X118: =(E118+I118+M118)*(1+V118) -> 97.812046 | Y118: =(F118+J118+N118)*(1+V118) -> 137.41021 | Z118: =(G118+K118+O118)*(1+V118) -> 178.64647
B119: China | C119: Shanghai | D119: APAC | E119: 75.194608 | F119: 113.03178 | G119: 153.82277 | I119: 8.463 | J119: 11.6374 | K119: 12.2388 | M119: 17.59296 | N119: 17.9928 | O119: 19.76352 | Q119: 0.05 | R119: 0.02 | S119: 0.04 | T119: 0.02 | U119: 0.02 | V119: =SUBTOTAL(9,Q119:U119) -> 0 | X119: =(E119+I119+M119)*(1+V119) -> 101.25057 | Y119: =(F119+J119+N119)*(1+V119) -> 142.66198 | Z119: =(G119+K119+O119)*(1+V119) -> 185.82509
B120: India | C120: Bangalore | D120: APAC | E120: 42.138583 | F120: 52.281319 | G120: 70.475247 | I120: 3.6855 | J120: 5.0679 | K120: 5.3298 | M120: 9.2370084 | N120: 9.4469404 | O120: 10.376639 | Q120: 0.03 | R120: 0.015 | S120: 0.05 | T120: 0.025 | U120: 0.03 | V120: =SUBTOTAL(9,Q120:U120) -> 0 | X120: =(E120+I120+M120)*(1+V120) -> 55.061092 | Y120: =(F120+J120+N120)*(1+V120) -> 66.796159 | Z120: =(G120+K120+O120)*(1+V120) -> 86.181687
B121: India | C121: Chennai | D121: APAC | E121: 41.72137 | F121: 51.763682 | G121: 69.777473 | I121: 3.6855 | J121: 5.0679 | K121: 5.3298 | M121: 9.1455528 | N121: 9.3534063 | O121: 10.2739 | Q121: 0.03 | R121: 0.015 | S121: 0.05 | T121: 0.025 | U121: 0.03 | V121: =SUBTOTAL(9,Q121:U121) -> 0 | X121: =(E121+I121+M121)*(1+V121) -> 54.552423 | Y121: =(F121+J121+N121)*(1+V121) -> 66.184989 | Z121: =(G121+K121+O121)*(1+V121) -> 85.381173
B122: India | C122: Hyderbad | D122: APAC | E122: 41.72137 | F122: 51.763682 | G122: 69.777473 | I122: 3.6855 | J122: 5.0679 | K122: 5.3298 | M122: 9.1455528 | N122: 9.3534063 | O122: 10.2739 | Q122: 0.03 | R122: 0.015 | S122: 0.05 | T122: 0.025 | U122: 0.03 | V122: =SUBTOTAL(9,Q122:U122) -> 0 | X122: =(E122+I122+M122)*(1+V122) -> 54.552423 | Y122: =(F122+J122+N122)*(1+V122) -> 66.184989 | Z122: =(G122+K122+O122)*(1+V122) -> 85.381173
... B130: New Zealand | C130: Auckland | D130: APAC | E130: 97.417365 | F130: 138.94501 | G130: 177.56211 | I130: 8.6540806 | J130: 11.900153 | K130: 12.515132 | M130: 21.767066 | N130: 22.261772 | O130: 24.452613 | Q130: 0.04 | R130: 0.03 | S130: 0.04 | T130: 0.02 | U130: 0.02 | V130: =SUBTOTAL(9,Q130:U130) -> 0 | X130: =(E130+I130+M130)*(1+V130) -> 127.83851 | Y130: =(F130+J130+N130)*(1+V130) -> 173.10693 | Z130: =(G130+K130+O130)*(1+V130) -> 214.52986
B131: Pakistan | C131: Karachi | D131: APAC | E131: 72.617393 | F131: 77.788197 | G131: 82.818798 | I131: 4.7775 | J131: 6.5695 | K131: 6.909 | M131: 11.858 | N131: 12.1275 | O131: 13.321 | Q131: 0.02 | R131: 0.015 | S131: 0.015 | T131: included | U131: n/a | V131: =SUBTOTAL(9,Q131:U131) -> 0 | X131: =(E131+I131+M131)*(1+V131) -> 89.252893 | Y131: =(F131+J131+N131)*(1+V131) -> 96.485197 | Z131: =(G131+K131+O131)*(1+V131) -> 103.0488
B132: Philippines | C132: Manila | D132: APAC | E132: 77.014533 | F132: 111.89041 | G132: 143.73344 | I132: 6.825 | J132: 9.385 | K132: 9.87 | M132: 16.81372 | N132: 17.19585 | O132: 18.88814 | Q132: 0.03 | R132: 0.03 | S132: 0.03 | T132: 0.01 | U132: 0.01 | V132: =SUBTOTAL(9,Q132:U132) -> 0 | X132: =(E132+I132+M132)*(1+V132) -> 100.65325 | Y132: =(F132+J132+N132)*(1+V132) -> 138.47126 | Z132: =(G132+K132+O132)*(1+V132) -> 172.49158
B133: Singapore | C133: Singapore | D133: APAC | E133: 122.9244 | F133: 188.09247 | G133: 222.99473 | I133: 12.285 | J133: 16.893 | K133: 17.766 | M133: 29.6604 | N133: 30.3345 | O133: 33.3198 | Q133: 0.07 | R133: 0.07 | S133: 0.1 | T133: included | U133: n/a | V133: =SUBTOTAL(9,Q133:U133) -> 0 | X133: =(E133+I133+M133)*(1+V133) -> 164.8698 | Y133: =(F133+J133+N133)*(1+V133) -> 235.31997 | Z133: =(G133+K133+O133)*(1+V133) -> 274.08053
B134: South Korea | C134: Seoul | D134: APAC | E134: 79.014858 | F134: 134.84041 | G134: 147.33228 | I134: 8.19 | J134: 11.262 | K134: 11.844 | M134: 17.82088 | N134: 18.2259 | O134: 20.01956 | Q134: 0.03 | R134: 0.02 | S134: 0.04 | T134: 0.015 | U134: 0.015 | V134: =SUBTOTAL(9,Q134:U134) -> 0 | X134: =(E134+I134+M134)*(1+V134) -> 105.02574 | Y134: =(F134+J134+N134)*(1+V134) -> 164.32831 | Z134: =(G134+K134+O134)*(1+V134) -> 179.19584
B135: Taiwan | C135: Taipei | D135: APAC | E135: 77.610887 | F135: 116.79202 | G135: 160.88604 | I135: 7.098 | J135: 9.7604 | K135: 10.2648 | M135: 17.078481 | N135: 17.466629 | O135: 19.185567 | Q135: 0.04 | R135: 0.02 | S135: 0.04 | T135: 0.02 | U135: 0.02 | V135: =SUBTOTAL(9,Q135:U135) -> 0 | X135: =(E135+I135+M135)*(1+V135) -> 101.78737 | Y135: =(F135+J135+N135)*(1+V135) -> 144.01905 | Z135: =(G135+K135+O135)*(1+V135) -> 190.3364
B136: Thailand | C136: Bangkok | D136: APAC | E136: 48.345386 | F136: 77.194057 | G136: 108.45996 | I136: 4.2947668 | J136: 5.9056977 | K136: 6.2108935 | M136: 10.290397 | N136: 10.52427 | O136: 11.559992 | Q136: 0.03 | R136: 0.015 | S136: 0.03 | T136: n/a | U136: 0.015 | V136: =SUBTOTAL(9,Q136:U136) -> 0 | X136: =(E136+I136+M136)*(1+V136) -> 62.93055 | Y136: =(F136+J136+N136)*(1+V136) -> 93.624024 | Z136: =(G136+K136+O136)*(1+V136) -> 126.23084
B137: Vietnam | C137: Hanoi | D137: APAC | E137: 56.869843 | F137: 71.378144 | G137: 91.617573 | I137: 5.0520377 | J137: 6.9470145 | K137: 7.3060238 | M137: 12.466181 | N137: 12.749503 | O137: 14.004217 | Q137: 0.03 | R137: 0.03 | S137: 0.04 | T137: 0.03 | U137: 0.015 | V137: =SUBTOTAL(9,Q137:U137) -> 0 | X137: =(E137+I137+M137)*(1+V137) -> 74.388062 | Y137: =(F137+J137+N137)*(1+V137) -> 91.074662 | Z137: =(G137+K137+O137)*(1+V137) -> 112.92781
B138: United Kingdom | C138: London | D138: EMEA | E138: 145.42387 | F138: 198.14908 | G138: 278.65435 | I138: 22.2048 | J138: 31.1472 | K138: 36.6444 | M138: 32.8636 | N138: 33.6105 | O138: 36.9182 | Q138: 0.05 | R138: 0.01 | S138: 0.05 | T138: 0.02 | U138: 0.02 | V138: =SUBTOTAL(9,Q138:U138) -> 0.15 | X138: =(E138+I138+M138)*(1+V138) -> 230.56611 | Y138: =(F138+J138+N138)*(1+V138) -> 302.34279 | Z138: =(G138+K138+O138)*(1+V138) -> 405.04949
B139: Zimbabwe | C139: Harare | D139: EMEA | E139: 87.864423 | F139: 121.68342 | G139: 194.45592 | I139: 13.416036 | J139: 18.818992 | K139: 22.140375 | M139: 19.2192 | N139: 19.656 | O139: 21.5904 | Q139: 0.05 | R139: 0.02 | S139: 0.04 | T139: 0.03 | U139: 0.02 | V139: =SUBTOTAL(9,Q139:U139) -> 0 | X139: =(E139+I139+M139)*(1+V139) -> 120.49966 | Y139: =(F139+J139+N139)*(1+V139) -> 160.15842 | Z139: =(G139+K139+O139)*(1+V139) -> 238.18669

Sheet Table 2_Team BYOB Sqm
E1: TEAM SPACE
E2: FIT OUT $/M2 | I2: FURNITURE $/M2 | M2: TECHNOLOGY $/M2 | Q2: 2023 Professional Fees (%) | X2: TOTAL FITOUT COST $/M2
E4: Low | F4: Medium | G4: High | I4: Low | J4: Medium | K4: High | M4: Low | N4: Medium | O4: High | X4: Low | Y4: Medium | Z4: High
B5: COUNTRY | C5: CITY | D5: REGION | Q5: Arch | R5: M&E Eng | S5: PM | T5: QS | U5: Other | V5: Total
B6: United States | C6: Cincinnati | D6: AMERICAS | E6: 1744.1546 | F6: 2478.8513 | G6: 2933.1367 | I6: 150.67948 | J6: 242.19749 | K6: 289.88575 | M6: 412.61379 | N6: 422.06268 | O6: 463.09499 | Q6: 0.08 | R6: 0.05 | S6: 0.03 | T6: 0.015 | U6: 0.02 | V6: =SUBTOTAL(9,Q6:U6) -> 0 | X6: =(E6+I6+M6)*(1+V6) -> 2307.4479 | Y6: =(F6+J6+N6)*(1+V6) -> 3143.1115 | Z6: =(G6+K6+O6)*(1+V6) -> 3686.1175
B7: United States | C7: Charlotte | D7: AMERICAS | E7: 1671.2387 | F7: 2376.9915 | G7: 2805.8961 | I7: 140.75092 | J7: 226.23863 | K7: 270.78462 | M7: 385.42588 | N7: 394.25216 | O7: 432.58078 | Q7: 0.08 | R7: 0.05 | S7: 0.03 | T7: 0.015 | U7: 0.02 | V7: =SUBTOTAL(9,Q7:U7) -> 0 | X7: =(E7+I7+M7)*(1+V7) -> 2197.4155 | Y7: =(F7+J7+N7)*(1+V7) -> 2997.4823 | Z7: =(G7+K7+O7)*(1+V7) -> 3509.2615
B8: United States | C8: Charleston (SC) | D8: AMERICAS | E8: 1671.2387 | F8: 2376.9915 | G8: 2805.8961 | I8: 140.75092 | J8: 226.23863 | K8: 270.78462 | M8: 385.42588 | N8: 394.25216 | O8: 432.58078 | Q8: 0.08 | R8: 0.05 | S8: 0.03 | T8: 0.015 | U8: 0.02 | V8: =SUBTOTAL(9,Q8:U8) -> 0 | X8: =(E8+I8+M8)*(1+V8) -> 2197.4155 | Y8: =(F8+J8+N8)*(1+V8) -> 2997.4823 | Z8: =(G8+K8+O8)*(1+V8) -> 3509.2615
B9: United States | C9: Chicago | D9: AMERICAS | E9: 2189.4729 | F9: 3117.3779 | G9: 3681.2884 | I9: 184.40491 | J9: 296.40668 | K9: 354.76864 | M9: 504.96594 | N9: 516.5297 | O9: 566.74596 | Q9: 0.08 | R9: 0.05 | S9: 0.03 | T9: 0.015 | U9: 0.02 | V9: =SUBTOTAL(9,Q9:U9) -> 0 | X9: =(E9+I9+M9)*(1+V9) -> 2878.8438 | Y9: =(F9+J9+N9)*(1+V9) -> 3930.3143 | Z9: =(G9+K9+O9)*(1+V9) -> 4602.803
B10: United States | C10: Cleveland | D10: AMERICAS | E10: 1711.5122 | F10: 2430.6211 | G10: 2880.7703 | I10: 146.15218 | J10: 234.92044 | K10: 281.17587 | M10: 400.21644 | N10: 409.38142 | O10: 449.18088 | Q10: 0.08 | R10: 0.05 | S10: 0.03 | T10: 0.015 | U10: 0.02 | V10: =SUBTOTAL(9,Q10:U10) -> 0 | X10: =(E10+I10+M10)*(1+V10) -> 2257.8808 | Y10: =(F10+J10+N10)*(1+V10) -> 3074.9229 | Z10: =(G10+K10+O10)*(1+V10) -> 3611.127
B11: United States | C11: Boston | D11: AMERICAS | E11: 2131.4759 | F11: 3034.5182 | G11: 3583.3207 | I11: 179.51945 | J11: 288.55395 | K11: 345.36972 | M11: 491.58783 | N11: 502.84523 | O11: 551.73111 | Q11: 0.08 | R11: 0.05 | S11: 0.03 | T11: 0.015 | U11: 0.02 | V11: =SUBTOTAL(9,Q11:U11) -> 0 | X11: =(E11+I11+M11)*(1+V11) -> 2802.5832 | Y11: =(F11+J11+N11)*(1+V11) -> 3825.9173 | Z11: =(G11+K11+O11)*(1+V11) -> 4480.4216
B12: United States | C12: Baltimore | D12: AMERICAS | E12: 1745.5316 | F12: 2479.1447 | G12: 2938.3734 | I12: 146.77731 | J12: 235.92525 | K12: 282.37853 | M12: 401.92826 | N12: 411.13244 | O12: 451.10214 | Q12: 0.08 | R12: 0.05 | S12: 0.03 | T12: 0.015 | U12: 0.02 | V12: =SUBTOTAL(9,Q12:U12) -> 0 | X12: =(E12+I12+M12)*(1+V12) -> 2294.2371 | Y12: =(F12+J12+N12)*(1+V12) -> 3126.2024 | Z12: =(G12+K12+O12)*(1+V12) -> 3671.8541
B13: United States | C13: Columbus | D13: AMERICAS | E13: 1672.1208 | F13: 2374.4356 | G13: 2814.0716 | I13: 142.78714 | J13: 229.51158 | K13: 274.70201 | M13: 391.00175 | N13: 399.95572 | O13: 438.83883 | Q13: 0.08 | R13: 0.05 | S13: 0.03 | T13: 0.015 | U13: 0.02 | V13: =SUBTOTAL(9,Q13:U13) -> 0 | X13: =(E13+I13+M13)*(1+V13) -> 2205.9097 | Y13: =(F13+J13+N13)*(1+V13) -> 3003.9029 | Z13: =(G13+K13+O13)*(1+V13) -> 3527.6124
